Workbook

Sheet JUL 25
A1: SITA DEVI PANDEY HOUSING PROJECT
A2: 11/1B/1 GANPAT RAI KHEMKA LANE LILUAH HOWRAH(W. B.) 711204
A3: FOR THE MONTH OF - JUL 2025 | U3: 44
A4: SNO | B4: NAME | C4: ROOM | D4: DATE OF | E4: ELECTRIC | F4: MTLY | G4: ELECTRIC | K4: MISC | L4: B/F & | M4: TOTAL | N4: AMT | O4: B/F OR | P4: PAYMENT | Q4: REMARKS
C5: NO | D5: ALLOTMENT | E5: SECURITY | F5: RENT | G5: NEW | H5: PRE | I5: TOTAL | J5: COST | K5: RENT | L5: ADV | M5: AMT DUE | N5: PAID | O5: ADV | P5: DATE
A6: 1 | B6: AKHILESH RAI | C6: G/1 | D6: 38754 | E6: 0 | F6: 1900 | G6: 1644 | H6: ='JUN 25'!G6 -> 1590 | I6: =G6-H6 -> 54 | J6: =I6*12 -> 648 | K6: 300 | L6: ='JUN 25'!O6 -> 5336 | M6: =F6+J6+K6+L6 -> 8184 | N6: 0 | O6: =M6-N6 -> 8184 | Q6: ALLOTED WEF MAY 2025. ADV 5000. RENT 1900
A7: 2 | B7: LAXMI SHARMA | C7: G/2 | D7: 37653 | E7: 0 | F7: 1900 | G7: 724 | H7: ='JUN 25'!G7 -> 699 | I7: =G7-H7 -> 25 | J7: =I7*12 -> 300 | K7: 300 | L7: ='JUN 25'!O7 -> 1960 | M7: =F7+J7+K7+L7 -> 4460 | N7: 0 | O7: =M7-N7 -> 4460 | Q7: AGAIN ALLT WEF JUN 25. ADV NIL RENT 1900
A8: 3 | B8: PANKAJ PATEL | C8: G/3 | D8: 37895 | E8: 0 | F8: 2200 | G8: 4518 | H8: ='JUN 25'!G8 -> 4503 | I8: =G8-H8 -> 15 | J8: =I8*12 -> 180 | K8: 300 | L8: ='JUN 25'!O8 -> 22710 | M8: =F8+J8+K8+L8 -> 25390 | N8: 0 | O8: =M8-N8 -> 25390 | Q8: ALLOTED WEF JUL 21. ADV 5K, RENT 2200 FM JUL 24.
A9: 4 | B9: BADRI MANDAL | C9: G/4 | D9: 38292 | E9: 500 | F9: 2000 | G9: 4697 | H9: ='JUN 25'!G9 -> 4667 | I9: =G9-H9 -> 30 | J9: =I9*12 -> 360 | K9: 300 | L9: ='JUN 25'!O9 -> 14018 | M9: =F9+J9+K9+L9 -> 16678 | N9: 0 | O9: =M9-N9 -> 16678 | Q9: ALLOTED WEF 01 DEC 2022. RENT 2000. ADV 5000
A10: 5 | B10: VACANT | C10: G/5 | F10: 0 | G10: 4304 | H10: ='JUN 25'!G10 -> 4299 | I10: =G10-H10 -> 5 | J10: =I10*12 -> 60 | K10: 0 | L10: ='JUN 25'!O10 -> 24 | M10: =F10+J10+K10+L10 -> 84 | N10: 0 | O10: =M10-N10 -> 84 | Q10: VACANT FROM JUL 24
A11: 6 | B11: VIVEK MANDAL | C11: G/6 | D11: 37667 | E11: 500 | F11: 2000 | G11: 2301 | H11: ='JUN 25'!G11 -> 2262 | I11: =G11-H11 -> 39 | J11: =I11*12 -> 468 | K11: 300 | L11: ='JUN 25'!O11 -> 35876 | M11: =F11+J11+K11+L11 -> 38644 | N11: 0 | O11: =M11-N11 -> 38644 | Q11: ALLOTED WEF JUN 24. ADV 4000, RENT 2000
A12: 7 | B12: RAM P SHRESTHA | C12: G/7 | D12: 37773 | E12: 500 | F12: 2200 | G12: 5090 | H12: ='JUN 25'!G12 -> 5067 | I12: =G12-H12 -> 23 | J12: =I12*12 -> 276 | K12: 300 | L12: ='JUN 25'!O12 -> 8220 | M12: =F12+J12+K12+L12 -> 10996 | N12: 0 | O12: =M12-N12 -> 10996 | Q12: ALLOTED WEF SEP 21. ADV 10000. RENT 2000
A13: 8 | B13: AJAY BAG | C13: G/8 | D13: 37469 | E13: 500 | F13: 1800 | G13: 3687 | H13: ='JUN 25'!G13 -> 3658 | I13: =G13-H13 -> 29 | J13: =I13*12 -> 348 | K13: 300 | L13: ='JUN 25'!O13 -> 18698 | M13: =F13+J13+K13+L13 -> 21146 | N13: 0 | O13: =M13-N13 -> 21146 | Q13: ALLOTED WEF MAR 22. ADV 10000. RENT 1800
A14: 9 | B14: NEW | C14: G/9 | D14: 37347 | E14: 500 | F14: 2000 | G14: 12867 | H14: ='JUN 25'!G14 -> 12861 | I14: =G14-H14 -> 6 | J14: =I14*12 -> 72 | K14: 300 | L14: ='JUN 25'!O14 -> 0 | M14: =F14+J14+K14+L14 -> 2372 | N14: 0 | O14: =M14-N14 -> 2372 | Q14: ALLOTED WEF JUL 25. ADV 5K. RENT 2000
A15: 10 | B15: PRAMOD MANDAL | C15: G/10 | D15: 37165 | E15: 500 | F15: 2000 | G15: 4173 | H15: ='JUN 25'!G15 -> 4117 | I15: =G15-H15 -> 56 | J15: =I15*12 -> 672 | K15: 300 | L15: ='JUN 25'!O15 -> 0 | M15: =F15+J15+K15+L15 -> 2972 | N15: 0 | O15: =M15-N15 -> 2972 | Q15: ALLOTED WEF SEP 22. ADV 10000 RENT 2000
A16: 11 | B16: VACANT | C16: 1/1 | D16: 38443 | E16: 0 | F16: 0 | G16: 882 | H16: ='JUN 25'!G16 -> 865 | I16: =G16-H16 -> 17 | J16: =I16*12 -> 204 | K16: 0 | L16: ='JUN 25'!O16 -> 0 | M16: =F16+J16+K16+L16 -> 204 | N16: 0 | O16: =M16-N16 -> 204 | Q16: VACANT FROM DEC 24
A17: 12 | B17: VACANT | C17: 1/2 | D17: 38292 | F17: 0 | G17: 6912 | H17: ='JUN 25'!G17 -> 6912 | I17: =G17-H17 -> 0 | J17: =I17*12 -> 0 | K17: 0 | L17: ='JUN 25'!O17 -> 0 | M17: =F17+J17+K17+L17 -> 0 | N17: 0 | O17: =M17-N17 -> 0 | Q17: VACANT FROM FEB 25.
A18: 13 | B18: VACAMT | C18: 1/3 | D18: 38292 | E18: 500 | F18: 0 | G18: 5661 | H18: 5661 | I18: =G18-H18 -> 0 | J18: =I18*12 -> 0 | K18: 0 | L18: ='JUN 25'!O18 -> 0 | M18: =F18+J18+K18+L18 -> 0 | N18: 0 | O18: =M18-N18 -> 0 | Q18: VACANT FROM AUG 24
A19: 14 | B19: VACANT | C19: 1/4 | D19: 38292 | E19: 500 | F19: 0 | G19: 4194 | H19: ='JUN 25'!G19 -> 4194 | I19: =G19-H19 -> 0 | J19: =I19*12 -> 0 | K19: 0 | L19: ='JUN 25'!O19 -> 0 | M19: =F19+J19+K19+L19 -> 0 | N19: 0 | O19: =M19-N19 -> 0 | Q19: VACANT FROM MAY 2025
A20: 15 | B20: VACANT | C20: 1/5 | D20: 37469 | E20: 500 | F20: 0 | G20: 4250 | H20: 4250 | I20: =G20-H20 -> 0 | J20: =I20*12 -> 0 | K20: 0 | L20: ='JUN 25'!O20 -> 0 | M20: =F20+J20+K20+L20 -> 0 | N20: 0 | O20: =M20-N20 -> 0 | Q20: VACANT WEF NOV 2023
A21: 16 | B21: SHAILENDRA PANDEY | C21: 1/6 | D21: 37681 | E21: 500 | F21: 3000 | G21: 3718 | H21: ='JUN 25'!G21 -> 3636 | I21: =G21-H21 -> 82 | J21: =I21*12 -> 984 | K21: 400 | L21: ='JUN 25'!O21 -> 42646 | M21: =F21+J21+K21+L21 -> 47030 | N21: 0 | O21: =M21-N21 -> 47030 | Q21: RENT INCREASED WEF MAR 24 FROM 2300. ADV 10000
A22: 17 | B22: BIRENDAR YADAV | C22: 2/1 | D22: 38292 | E22: 500 | F22: 2800 | G22: 908 | H22: ='JUN 25'!G22 -> 879 | I22: =G22-H22 -> 29 | J22: =I22*12 -> 348 | K22: 400 | L22: ='JUN 25'!O22 -> 49824 | M22: =F22+J22+K22+L22 -> 53372 | N22: 0 | O22: =M22-N22 -> 53372 | Q22: RENT INCREASED WEF DEC 22 FROM 2200. ADV NIL
A23: 18 | B23: HARI SHANKER SHUKLA | C23: 2/2 | D23: 38292 | E23: 500 | F23: 3100 | G23: 1101 | H23: ='JUN 25'!G23 -> 1078 | I23: =G23-H23 -> 23 | J23: =I23*12 -> 276 | K23: 400 | L23: ='JUN 25'!O23 -> 24394 | M23: =F23+J23+K23+L23 -> 28170 | N23: 0 | O23: =M23-N23 -> 28170 | Q23: RENT INCRESED WEF JUL 24 FROM 2700. ADV 10000
A24: 19 | B24: SHIV SHANKER PANDEY | C24: 2/3 | D24: 37681 | E24: 500 | F24: 2800 | G24: 5582 | H24: ='JUN 25'!G24 -> 5561 | I24: =G24-H24 -> 21 | J24: =I24*12 -> 252 | K24: 400 | L24: ='JUN 25'!O24 -> 0 | M24: =F24+J24+K24+L24 -> 3452 | N24: 0 | O24: =M24-N24 -> 3452 | Q24: REALLOTED WEF DEC 22. RENT 2800. ADV NIL
A25: 20 | B25: PRAKASH PANDEY | C25: 2/4 | D25: 37681 | E25: 0 | F25: 2800 | G25: 1350 | H25: ='JUN 25'!G25 -> 1310 | I25: =G25-H25 -> 40 | J25: =I25*12 -> 480 | K25: 400 | L25: ='JUN 25'!O25 -> 3916 | M25: =F25+J25+K25+L25 -> 7596 | N25: 0 | O25: =M25-N25 -> 7596 | Q25: ALLOTED FROM DEC 23. ADV NIL. RENT 2800
A26: 21 | B26: VACANT | C26: 2/5 | D26: 37681 | E26: 500 | F26: 0 | G26: 3439 | H26: ='JUN 25'!G26 -> 3439 | I26: =G26-H26 -> 0 | J26: =I26*12 -> 0 | K26: 0 | L26: 0 | M26: =F26+J26+K26+L26 -> 0 | N26: 0 | O26: =M26-N26 -> 0 | Q26: VACATED WEF JUN 25.
A27: 22 | B27: SUNITA SINGH | C27: 2/6 | D27: 37681 | E27: 0 | F27: 3100 | G27: 5202 | H27: ='JUN 25'!G27 -> 5171 | I27: =G27-H27 -> 31 | J27: =I27*12 -> 372 | K27: 400 | L27: ='JUN 25'!O27 -> -4 | M27: =F27+J27+K27+L27 -> 3868 | N27: 0 | O27: =M27-N27 -> 3868 | Q27: ALLOTED WEF MAY 2025. ADV 15000, RENT 3100
C28: TOTAL | E28: =SUM(E6:E27) -> 7000 | F28: =SUM(F6:F27) -> 35600 | I28: =SUM(I6:I27) -> 525 | J28: =SUM(J6:J27) -> 6300 | K28: =SUM(K6:K27) -> 5100 | L28: =SUM(L6:L27) -> 227618 | M28: =SUM(M6:M27) -> 274618 | N28: =SUM(N6:N27) -> 0 | O28: =SUM(O6:O27) -> 274618

Sheet JUN 25
A1: SITA DEVI PANDEY HOUSING PROJECT
A2: 11/1B/1 GANPAT RAI KHEMKA LANE LILUAH HOWRAH(W. B.) 711204
A3: FOR THE MONTH OF - JUN 2025 | U3: 44
A4: SNO | B4: NAME | C4: ROOM | D4: DATE OF | E4: ELECTRIC | F4: MTLY | G4: ELECTRIC | K4: MISC | L4: B/F & | M4: TOTAL | N4: AMT | O4: B/F OR | P4: PAYMENT | Q4: REMARKS
C5: NO | D5: ALLOTMENT | E5: SECURITY | F5: RENT | G5: NEW | H5: PRE | I5: TOTAL | J5: COST | K5: RENT | L5: ADV | M5: AMT DUE | N5: PAID | O5: ADV | P5: DATE
A6: 1 | B6: AKHILESH RAI | C6: G/1 | D6: 38754 | E6: 0 | F6: 1900 | G6: 1590 | H6: ='MAY 25'!G6 -> 1544 | I6: =G6-H6 -> 46 | J6: =I6*12 -> 552 | K6: 300 | L6: ='MAY 25'!O6 -> 2584 | M6: =F6+J6+K6+L6 -> 5336 | N6: 0 | O6: =M6-N6 -> 5336 | Q6: ALLOTED WEF MAY 2025. ADV 5000. RENT 1900
A7: 2 | B7: LAXMI SHARMA | C7: G/2 | D7: 37653 | E7: 0 | F7: 1900 | G7: 699 | H7: ='MAY 25'!G7 -> 689 | I7: =G7-H7 -> 10 | J7: =I7*12 -> 120 | K7: 300 | L7: ='MAY 25'!O7 -> -360 | M7: =F7+J7+K7+L7 -> 1960 | N7: 0 | O7: =M7-N7 -> 1960 | Q7: AGAIN ALLT WEF JUN 25. ADV NIL RENT 1900
A8: 3 | B8: PANKAJ PATEL | C8: G/3 | D8: 37895 | E8: 0 | F8: 2200 | G8: 4503 | H8: ='MAY 25'!G8 -> 4481 | I8: =G8-H8 -> 22 | J8: =I8*12 -> 264 | K8: 300 | L8: ='MAY 25'!O8 -> 19946 | M8: =F8+J8+K8+L8 -> 22710 | N8: 0 | O8: =M8-N8 -> 22710 | Q8: ALLOTED WEF JUL 21. ADV 5K, RENT 2200 FM JUL 24.
A9: 4 | B9: BADRI MANDAL | C9: G/4 | D9: 38292 | E9: 500 | F9: 2000 | G9: 4667 | H9: 4622 | I9: =G9-H9 -> 45 | J9: =I9*12 -> 540 | K9: 300 | L9: ='MAY 25'!O9 -> 11178 | M9: =F9+J9+K9+L9 -> 14018 | N9: 0 | O9: =M9-N9 -> 14018 | Q9: ALLOTED WEF 01 DEC 2022. RENT 2000. ADV 5000
A10: 5 | B10: VACANT | C10: G/5 | F10: 0 | G10: 4299 | H10: ='MAY 25'!G10 -> 4297 | I10: =G10-H10 -> 2 | J10: =I10*12 -> 24 | K10: 0 | L10: ='MAY 25'!O10 -> 0 | M10: =F10+J10+K10+L10 -> 24 | N10: 0 | O10: =M10-N10 -> 24 | Q10: VACANT FROM JUL 24
A11: 6 | B11: VIVEK MANDAL | C11: G/6 | D11: 37667 | E11: 500 | F11: 2000 | G11: 2262 | H11: ='MAY 25'!G11 -> 2224 | I11: =G11-H11 -> 38 | J11: =I11*12 -> 456 | K11: 300 | L11: ='MAY 25'!O11 -> 33120 | M11: =F11+J11+K11+L11 -> 35876 | N11: 0 | O11: =M11-N11 -> 35876 | Q11: ALLOTED WEF JUN 24. ADV 4000, RENT 2000
A12: 7 | B12: RAM P SHRESTHA | C12: G/7 | D12: 37773 | E12: 500 | F12: 2200 | G12: 5067 | H12: ='MAY 25'!G12 -> 5046 | I12: =G12-H12 -> 21 | J12: =I12*12 -> 252 | K12: 300 | L12: ='MAY 25'!O12 -> 5468 | M12: =F12+J12+K12+L12 -> 8220 | N12: 0 | O12: =M12-N12 -> 8220 | Q12: ALLOTED WEF SEP 21. ADV 10000. RENT 2000
A13: 8 | B13: AJAY BAG | C13: G/8 | D13: 37469 | E13: 500 | F13: 1800 | G13: 3658 | H13: ='MAY 25'!G13 -> 3620 | I13: =G13-H13 -> 38 | J13: =I13*12 -> 456 | K13: 300 | L13: ='MAY 25'!O13 -> 26142 | M13: =F13+J13+K13+L13 -> 28698 | N13: 10000 | O13: =M13-N13 -> 18698 | Q13: ALLOTED WEF MAR 22. ADV 10000. RENT 1800
A14: 9 | B14: VACANT | C14: G/9 | D14: 37347 | E14: 500 | F14: 0 | G14: 12861 | H14: ='MAY 25'!G14 -> 12861 | I14: =G14-H14 -> 0 | J14: =I14*12 -> 0 | K14: 0 | L14: ='MAY 25'!O14 -> 0 | M14: =F14+J14+K14+L14 -> 0 | N14: 0 | O14: =M14-N14 -> 0 | Q14: VACATED WEF OCT 24.
A15: 10 | B15: PRAMOD MANDAL | C15: G/10 | D15: 37165 | E15: 500 | F15: 2000 | G15: 4117 | H15: ='MAY 25'!G15 -> 4050 | I15: =G15-H15 -> 67 | J15: =I15*12 -> 804 | K15: 300 | L15: ='MAY 25'!O15 -> 0 | M15: =F15+J15+K15+L15 -> 3104 | N15: 3104 | O15: =M15-N15 -> 0 | Q15: ALLOTED WEF SEP 22. ADV 10000 RENT 2000
A16: 11 | B16: VACANT | C16: 1/1 | D16: 38443 | E16: 0 | F16: 0 | G16: 865 | H16: ='MAY 25'!G16 -> 865 | I16: =G16-H16 -> 0 | J16: =I16*12 -> 0 | K16: 0 | L16: ='MAY 25'!O16 -> 0 | M16: =F16+J16+K16+L16 -> 0 | N16: 0 | O16: =M16-N16 -> 0 | Q16: VACANT FROM DEC 24
A17: 12 | B17: VACANT | C17: 1/2 | D17: 38292 | F17: 0 | G17: 6912 | H17: ='MAY 25'!G17 -> 6912 | I17: =G17-H17 -> 0 | J17: =I17*12 -> 0 | K17: 0 | L17: ='MAY 25'!O17 -> 0 | M17: =F17+J17+K17+L17 -> 0 | N17: 0 | O17: =M17-N17 -> 0 | Q17: VACANT FROM FEB 25.
A18: 13 | B18: VACAMT | C18: 1/3 | D18: 38292 | E18: 500 | F18: 0 | G18: 5655 | H18: ='MAY 25'!G18 -> 5655 | I18: =G18-H18 -> 0 | J18: =I18*12 -> 0 | K18: 0 | L18: ='MAY 25'!O18 -> 0 | M18: =F18+J18+K18+L18 -> 0 | N18: 0 | O18: =M18-N18 -> 0 | Q18: VACANT FROM AUG 24
A19: 14 | B19: VACANT | C19: 1/4 | D19: 38292 | E19: 500 | F19: 0 | G19: 4194 | H19: ='MAY 25'!G19 -> 4194 | I19: =G19-H19 -> 0 | J19: =I19*12 -> 0 | K19: 0 | L19: 0 | M19: =F19+J19+K19+L19 -> 0 | N19: 0 | O19: =M19-N19 -> 0 | Q19: VACATED FROM MAY 2025. REFUND 3228
A20: 15 | B20: VACANT | C20: 1/5 | D20: 37469 | E20: 500 | F20: 0 | G20: 4247 | H20: 4247 | I20: =G20-H20 -> 0 | J20: =I20*12 -> 0 | K20: 0 | L20: ='MAY 25'!O20 -> 0 | M20: =F20+J20+K20+L20 -> 0 | N20: 0 | O20: =M20-N20 -> 0 | Q20: VACANT WEF NOV 2023
A21: 16 | B21: SHAILENDRA PANDEY | C21: 1/6 | D21: 37681 | E21: 500 | F21: 3000 | G21: 3636 | H21: ='MAY 25'!G21 -> 3609 | I21: =G21-H21 -> 27 | J21: =I21*12 -> 324 | K21: 5400 | L21: ='MAY 25'!O21 -> 33922 | M21: =F21+J21+K21+L21 -> 42646 | N21: 0 | O21: =M21-N21 -> 42646 | Q21: RENT INCREASED WEF MAR 24 FROM 2300. ADV 10000
A22: 17 | B22: BIRENDAR YADAV | C22: 2/1 | D22: 38292 | E22: 500 | F22: 2800 | G22: 879 | H22: ='MAY 25'!G22 -> 848 | I22: =G22-H22 -> 31 | J22: =I22*12 -> 372 | K22: 3400 | L22: ='MAY 25'!O22 -> 43252 | M22: =F22+J22+K22+L22 -> 49824 | N22: 0 | O22: =M22-N22 -> 49824 | Q22: RENT INCREASED WEF DEC 22 FROM 2200. ADV NIL
A23: 18 | B23: HARI SHANKER SHUKLA | C23: 2/2 | D23: 38292 | E23: 500 | F23: 3100 | G23: 1078 | H23: ='MAY 25'!G23 -> 1070 | I23: =G23-H23 -> 8 | J23: =I23*12 -> 96 | K23: 1400 | L23: ='MAY 25'!O23 -> 19798 | M23: =F23+J23+K23+L23 -> 24394 | N23: 0 | O23: =M23-N23 -> 24394 | Q23: RENT INCRESED WEF JUL 24 FROM 2700. ADV 10000
A24: 19 | B24: SHIV SHANKER PANDEY | C24: 2/3 | D24: 37681 | E24: 500 | F24: 2800 | G24: 5561 | H24: ='MAY 25'!G24 -> 5544 | I24: =G24-H24 -> 17 | J24: =I24*12 -> 204 | K24: 400 | L24: ='MAY 25'!O24 -> 10 | M24: =F24+J24+K24+L24 -> 3414 | N24: 3414 | O24: =M24-N24 -> 0 | Q24: REALLOTED WEF DEC 22. RENT 2800. ADV NIL
A25: 20 | B25: PRAKASH PANDEY | C25: 2/4 | D25: 37681 | E25: 0 | F25: 2800 | G25: 1310 | H25: ='MAY 25'!G25 -> 1268 | I25: =G25-H25 -> 42 | J25: =I25*12 -> 504 | K25: 400 | L25: ='MAY 25'!O25 -> 4212 | M25: =F25+J25+K25+L25 -> 7916 | N25: 4000 | O25: =M25-N25 -> 3916 | Q25: ALLOTED FROM DEC 23. ADV NIL. RENT 2800
A26: 21 | B26: PAPPU | C26: 2/5 | D26: 37681 | E26: 500 | F26: 3000 | G26: 3439 | H26: ='MAY 25'!G26 -> 3412 | I26: =G26-H26 -> 27 | J26: =I26*12 -> 324 | K26: 400 | L26: ='MAY 25'!O26 -> 4896 | M26: =F26+J26+K26+L26 -> 8620 | N26: 10000 | O26: =M26-N26 -> -1380 | Q26: VACATED JUN 25. RETURNED 1380
A27: 22 | B27: SUNITA SINGH | C27: 2/6 | D27: 37681 | E27: 0 | F27: 3100 | G27: 5171 | H27: ='MAY 25'!G27 -> 5153 | I27: =G27-H27 -> 18 | J27: =I27*12 -> 216 | K27: 400 | L27: ='MAY 25'!O27 -> 0 | M27: =F27+J27+K27+L27 -> 3716 | N27: 3720 | O27: =M27-N27 -> -4 | Q27: ALLOTED WEF MAY 2025. ADV 15000, RENT 3100
C28: TOTAL | E28: =SUM(E6:E27) -> 7000 | F28: =SUM(F6:F27) -> 36600 | I28: =SUM(I6:I27) -> 459 | J28: =SUM(J6:J27) -> 5508 | K28: =SUM(K6:K27) -> 14200 | L28: =SUM(L6:L27) -> 204168 | M28: =SUM(M6:M27) -> 260476 | N28: =SUM(N6:N27) -> 34238 | O28: =SUM(O6:O27) -> 226238

Sheet MAY 25
A1: SITA DEVI PANDEY HOUSING PROJECT
A2: 11/1B/1 GANPAT RAI KHEMKA LANE LILUAH HOWRAH(W. B.) 711204
A3: FOR THE MONTH OF - MAY 2025 | U3: 44
A4: SNO | B4: NAME | C4: ROOM | D4: DATE OF | E4: ELECTRIC | F4: MTLY | G4: ELECTRIC | K4: MISC | L4: B/F & | M4: TOTAL | N4: AMT | O4: B/F OR | P4: PAYMENT | Q4: REMARKS
C5: NO | D5: ALLOTMENT | E5: SECURITY | F5: RENT | G5: NEW | H5: PRE | I5: TOTAL | J5: COST | K5: RENT | L5: ADV | M5: AMT DUE | N5: PAID | O5: ADV | P5: DATE
A6: 1 | B6: AKHILESH RAI | C6: G/1 | D6: 38754 | E6: 0 | F6: 1900 | G6: 1544 | H6: ='APR 25'!G6 -> 1512 | I6: =G6-H6 -> 32 | J6: =I6*12 -> 384 | K6: 300 | L6: 0 | M6: =F6+J6+K6+L6 -> 2584 | N6: 0 | O6: =M6-N6 -> 2584 | Q6: ALLOTED WEF MAY 2025. ADV 5000. RENT 1900
A7: 2 | B7: LAXMI SHARMA | C7: G/2 | D7: 37653 | E7: 0 | F7: 1900 | G7: 689 | H7: ='APR 25'!G7 -> 681 | I7: =G7-H7 -> 8 | J7: =I7*12 -> 96 | K7: 300 | L7: ='APR 25'!O7 -> 2344 | M7: =F7+J7+K7+L7 -> 4640 | N7: 5000 | O7: =M7-N7 -> -360 | Q7: VACATED ON MAY 2025. REFUND 360
A8: 3 | B8: PANKAJ PATEL | C8: G/3 | D8: 37895 | E8: 0 | F8: 2200 | G8: 4481 | H8: ='APR 25'!G8 -> 4474 | I8: =G8-H8 -> 7 | J8: =I8*12 -> 84 | K8: 300 | L8: ='APR 25'!O8 -> 20362 | M8: =F8+J8+K8+L8 -> 22946 | N8: 3000 | O8: =M8-N8 -> 19946 | Q8: ALLOTED WEF JUL 21. ADV 5K, RENT 2200 FM JUL 24.
A9: 4 | B9: BADRI MANDAL | C9: G/4 | D9: 38292 | E9: 500 | F9: 2000 | G9: 4671 | H9: ='APR 25'!G9 -> 4581 | I9: =G9-H9 -> 90 | J9: =I9*12 -> 1080 | K9: 300 | L9: ='APR 25'!O9 -> 7798 | M9: =F9+J9+K9+L9 -> 11178 | N9: 0 | O9: =M9-N9 -> 11178 | Q9: ALLOTED WEF 01 DEC 2022. RENT 2000. ADV 5000
A10: 5 | B10: VACANT | C10: G/5 | F10: 0 | G10: 4297 | H10: ='APR 25'!G10 -> 4297 | I10: =G10-H10 -> 0 | J10: =I10*12 -> 0 | K10: 0 | L10: ='APR 25'!O10 -> 0 | M10: =F10+J10+K10+L10 -> 0 | N10: 0 | O10: =M10-N10 -> 0 | Q10: VACANT FROM JUL 24
A11: 6 | B11: VIVEK MANDAL | C11: G/6 | D11: 37667 | E11: 500 | F11: 2000 | G11: 2224 | H11: ='APR 25'!G11 -> 2152 | I11: =G11-H11 -> 72 | J11: =I11*12 -> 864 | K11: 300 | L11: ='APR 25'!O11 -> 29956 | M11: =F11+J11+K11+L11 -> 33120 | N11: 0 | O11: =M11-N11 -> 33120 | Q11: ALLOTED WEF JUN 24. ADV 4000, RENT 2000
A12: 7 | B12: RAM P SHRESTHA | C12: G/7 | D12: 37773 | E12: 500 | F12: 2200 | G12: 5046 | H12: ='APR 25'!G12 -> 5007 | I12: =G12-H12 -> 39 | J12: =I12*12 -> 468 | K12: 300 | L12: ='APR 25'!O12 -> 8170 | M12: =F12+J12+K12+L12 -> 11138 | N12: 5670 | O12: =M12-N12 -> 5468 | Q12: ALLOTED WEF SEP 21. ADV 10000. RENT 2000
A13: 8 | B13: AJAY BAG | C13: G/8 | D13: 37469 | E13: 500 | F13: 1800 | G13: 3620 | H13: ='APR 25'!G13 -> 3501 | I13: =G13-H13 -> 119 | J13: =I13*12 -> 1428 | K13: 300 | L13: ='APR 25'!O13 -> 22614 | M13: =F13+J13+K13+L13 -> 26142 | N13: 0 | O13: =M13-N13 -> 26142 | Q13: ALLOTED WEF MAR 22. ADV 10000. RENT 1800
A14: 9 | B14: VACANT | C14: G/9 | D14: 37347 | E14: 500 | F14: 0 | G14: 12861 | H14: ='APR 25'!G14 -> 12861 | I14: =G14-H14 -> 0 | J14: =I14*12 -> 0 | K14: 0 | L14: ='APR 25'!O14 -> 0 | M14: =F14+J14+K14+L14 -> 0 | O14: =M14-N14 -> 0 | Q14: VACATED WEF OCT 24.
A15: 10 | B15: PRAMOD MANDAL | C15: G/10 | D15: 37165 | E15: 500 | F15: 2000 | G15: 4050 | H15: ='APR 25'!G15 -> 3938 | I15: =G15-H15 -> 112 | J15: =I15*12 -> 1344 | K15: 300 | L15: ='APR 25'!O15 -> -8 | M15: =F15+J15+K15+L15 -> 3636 | N15: 3636 | O15: =M15-N15 -> 0 | Q15: ALLOTED WEF SEP 22. ADV 10000 RENT 2000
A16: 11 | B16: VACANT | C16: 1/1 | D16: 38443 | E16: 0 | F16: 0 | G16: 865 | H16: ='APR 25'!G16 -> 865 | I16: =G16-H16 -> 0 | J16: =I16*12 -> 0 | K16: 0 | L16: ='APR 25'!O16 -> 0 | M16: =F16+J16+K16+L16 -> 0 | N16: 0 | O16: =M16-N16 -> 0 | Q16: VACANT FROM DEC 24
A17: 12 | B17: VACANT | C17: 1/2 | D17: 38292 | F17: 0 | G17: 6912 | H17: ='APR 25'!G17 -> 6912 | I17: =G17-H17 -> 0 | J17: =I17*12 -> 0 | K17: 0 | L17: ='APR 25'!O17 -> 0 | M17: =F17+J17+K17+L17 -> 0 | N17: 0 | O17: =M17-N17 -> 0 | Q17: VACANT FROM FEB 25.
A18: 13 | B18: VACAMT | C18: 1/3 | D18: 38292 | E18: 500 | F18: 0 | G18: 5655 | H18: ='APR 25'!G18 -> 5655 | I18: =G18-H18 -> 0 | J18: =I18*12 -> 0 | K18: 0 | L18: ='APR 25'!O18 -> 0 | M18: =F18+J18+K18+L18 -> 0 | N18: 0 | O18: =M18-N18 -> 0 | Q18: VACANT FROM AUG 24
A19: 14 | B19: ANIL SHARMA | C19: 1/4 | D19: 38292 | E19: 500 | F19: 3000 | G19: 4194 | H19: ='APR 25'!G19 -> 4151 | I19: =G19-H19 -> 43 | J19: =I19*12 -> 516 | K19: 400 | L19: ='APR 25'!O19 -> 7856 | M19: =F19+J19+K19+L19 -> 11772 | N19: 15000 | O19: =M19-N19 -> -3228 | Q19: VACATED FROM MAY 2025. REFUNDED 3228
A20: 15 | B20: VACANT | C20: 1/5 | D20: 37469 | E20: 500 | F20: 0 | G20: 4246 | H20: ='APR 25'!G20 -> 4246 | I20: =G20-H20 -> 0 | J20: =I20*12 -> 0 | K20: 0 | L20: ='APR 25'!O20 -> 0 | M20: =F20+J20+K20+L20 -> 0 | N20: 0 | O20: =M20-N20 -> 0 | Q20: VACANT WEF NOV 2023
A21: 16 | B21: SHAILENDRA PANDEY | C21: 1/6 | D21: 37681 | E21: 500 | F21: 3000 | G21: 3609 | H21: ='APR 25'!G21 -> 3551 | I21: =G21-H21 -> 58 | J21: =I21*12 -> 696 | K21: 400 | L21: ='APR 25'!O21 -> 29826 | M21: =F21+J21+K21+L21 -> 33922 | N21: 0 | O21: =M21-N21 -> 33922 | Q21: RENT INCREASED WEF MAR 24 FROM 2300. ADV 10000
A22: 17 | B22: BIRENDAR YADAV | C22: 2/1 | D22: 38292 | E22: 500 | F22: 2800 | G22: 848 | H22: ='APR 25'!G22 -> 816 | I22: =G22-H22 -> 32 | J22: =I22*12 -> 384 | K22: 400 | L22: ='APR 25'!O22 -> 39668 | M22: =F22+J22+K22+L22 -> 43252 | N22: 0 | O22: =M22-N22 -> 43252 | Q22: RENT INCREASED WEF DEC 22 FROM 2200. ADV NIL
A23: 18 | B23: HARI SHANKER SHUKLA | C23: 2/2 | D23: 38292 | E23: 500 | F23: 3100 | G23: 1070 | H23: ='APR 25'!G23 -> 1025 | I23: =G23-H23 -> 45 | J23: =I23*12 -> 540 | K23: 400 | L23: ='APR 25'!O23 -> 15758 | M23: =F23+J23+K23+L23 -> 19798 | N23: 0 | O23: =M23-N23 -> 19798 | Q23: RENT INCRESED WEF JUL 24 FROM 2700. ADV 10000
A24: 19 | B24: SHIV SHANKER PANDEY | C24: 2/3 | D24: 37681 | E24: 500 | F24: 2800 | G24: 5544 | H24: ='APR 25'!G24 -> 5505 | I24: =G24-H24 -> 39 | J24: =I24*12 -> 468 | K24: 400 | L24: ='APR 25'!O24 -> 0 | M24: =F24+J24+K24+L24 -> 3668 | N24: 3658 | O24: =M24-N24 -> 10 | Q24: REALLOTED WEF DEC 22. RENT 2800. ADV NIL
A25: 20 | B25: PRAKASH PANDEY | C25: 2/4 | D25: 37681 | E25: 0 | F25: 2800 | G25: 1268 | H25: ='APR 25'!G25 -> 1157 | I25: =G25-H25 -> 111 | J25: =I25*12 -> 1332 | K25: 400 | L25: ='APR 25'!O25 -> 6680 | M25: =F25+J25+K25+L25 -> 11212 | N25: 7000 | O25: =M25-N25 -> 4212 | Q25: ALLOTED FROM DEC 23. ADV NIL. RENT 2800
A26: 21 | B26: PAPPU | C26: 2/5 | D26: 37681 | E26: 500 | F26: 3000 | G26: 3412 | H26: ='APR 25'!G26 -> 3355 | I26: =G26-H26 -> 57 | J26: =I26*12 -> 684 | K26: 400 | L26: ='APR 25'!O26 -> 812 | M26: =F26+J26+K26+L26 -> 4896 | N26: 0 | O26: =M26-N26 -> 4896 | Q26: ALLOTED WEF DEC 24. ADV 10K, RENT 3100
A27: 22 | B27: SUNITA SINGH | C27: 2/6 | D27: 37681 | E27: 0 | F27: 3100 | G27: 5153 | H27: ='APR 25'!G27 -> 5104 | I27: =G27-H27 -> 49 | J27: =I27*12 -> 588 | K27: 400 | L27: ='APR 25'!O27 -> 0 | M27: =F27+J27+K27+L27 -> 4088 | N27: 4088 | O27: =M27-N27 -> 0 | Q27: ALLOTED WEF MAY 2025. ADV 15000, RENT 3100
C28: TOTAL | E28: =SUM(E6:E27) -> 7000 | F28: =SUM(F6:F27) -> 39600 | I28: =SUM(I6:I27) -> 913 | J28: =SUM(J6:J27) -> 10956 | K28: =SUM(K6:K27) -> 5600 | L28: =SUM(L6:L27) -> 191836 | M28: =SUM(M6:M27) -> 247992 | N28: =SUM(N6:N27) -> 47052 | O28: =SUM(O6:O27) -> 200940

Sheet APR 25
A1: SITA DEVI PANDEY HOUSING PROJECT
A2: 11/1B/1 GANPAT RAI KHEMKA LANE LILUAH HOWRAH(W. B.) 711204
A3: FOR THE MONTH OF - APR 2025 | U3: 44
A4: SNO | B4: NAME | C4: ROOM | D4: DATE OF | E4: ELECTRIC | F4: MTLY | G4: ELECTRIC | K4: MISC | L4: B/F & | M4: TOTAL | N4: AMT | O4: B/F OR | P4: PAYMENT | Q4: REMARKS
C5: NO | D5: ALLOTMENT | E5: SECURITY | F5: RENT | G5: NEW | H5: PRE | I5: TOTAL | J5: COST | K5: RENT | L5: ADV | M5: AMT DUE | N5: PAID | O5: ADV | P5: DATE
A6: 1 | B6: SUNNY PRAJAPATI | C6: G/1 | D6: 38754 | E6: 0 | F6: 2200 | G6: 1512 | H6: ='MAR 25'!G6 -> 1479 | I6: =G6-H6 -> 33 | J6: =I6*12 -> 396 | K6: 300 | L6: 20828 | M6: =F6+J6+K6+L6 -> 23724 | N6: 20724 | O6: =M6-N6 -> 3000 | Q6: VACATED WEF MAY 2025. 3000 DUE
A7: 2 | B7: LAXMI SHARMA | C7: G/2 | D7: 37653 | E7: 0 | F7: 1900 | G7: 681 | H7: ='MAR 25'!G7 -> 669 | I7: =G7-H7 -> 12 | J7: =I7*12 -> 144 | K7: 300 | L7: ='MAR 25'!O7 -> 0 | M7: =F7+J7+K7+L7 -> 2344 | N7: 0 | O7: =M7-N7 -> 2344 | Q7: ALLOTED WEF 07-03-2025. ADV 5K.RENT 1900
A8: 3 | B8: PANKAJ PATEL | C8: G/3 | D8: 37895 | E8: 0 | F8: 2200 | G8: 4474 | H8: ='MAR 25'!G8 -> 4470 | I8: =G8-H8 -> 4 | J8: =I8*12 -> 48 | K8: 300 | L8: ='MAR 25'!O8 -> 22814 | M8: =F8+J8+K8+L8 -> 25362 | N8: 5000 | O8: =M8-N8 -> 20362 | Q8: ALLOTED WEF JUL 21. ADV 5K, RENT 2200 FM JUL 24.
A9: 4 | B9: BADRI MANDAL | C9: G/4 | D9: 38292 | E9: 500 | F9: 2000 | G9: 4581 | H9: ='MAR 25'!G9 -> 4541 | I9: =G9-H9 -> 40 | J9: =I9*12 -> 480 | K9: 300 | L9: ='MAR 25'!O9 -> 15018 | M9: =F9+J9+K9+L9 -> 17798 | N9: 10000 | O9: =M9-N9 -> 7798 | Q9: ALLOTED WEF 01 DEC 2022. RENT 2000. ADV 5000
A10: 5 | B10: VACANT | C10: G/5 | F10: 0 | G10: 4297 | H10: ='MAR 25'!G10 -> 4297 | I10: =G10-H10 -> 0 | J10: =I10*12 -> 0 | K10: 0 | L10: ='MAR 25'!O10 -> 0 | M10: =F10+J10+K10+L10 -> 0 | N10: 0 | O10: =M10-N10 -> 0 | Q10: VACANT FROM JUL 24
A11: 6 | B11: VIVEK MANDAL | C11: G/6 | D11: 37667 | E11: 500 | F11: 2000 | G11: 2152 | H11: ='MAR 25'!G11 -> 2100 | I11: =G11-H11 -> 52 | J11: =I11*12 -> 624 | K11: 300 | L11: ='MAR 25'!O11 -> 27032 | M11: =F11+J11+K11+L11 -> 29956 | N11: 0 | O11: =M11-N11 -> 29956 | Q11: ALLOTED WEF JUN 24. ADV 4000, RENT 2000
A12: 7 | B12: RAM P SHRESTHA | C12: G/7 | D12: 37773 | E12: 500 | F12: 2200 | G12: 5007 | H12: ='MAR 25'!G12 -> 4974 | I12: =G12-H12 -> 33 | J12: =I12*12 -> 396 | K12: 300 | L12: ='MAR 25'!O12 -> 7824 | M12: =F12+J12+K12+L12 -> 10720 | N12: 2550 | O12: =M12-N12 -> 8170 | Q12: ALLOTED WEF SEP 21. ADV 10000. RENT 2000
A13: 8 | B13: AJAY BAG | C13: G/8 | D13: 37469 | E13: 500 | F13: 1800 | G13: 3501 | H13: ='MAR 25'!G13 -> 3462 | I13: =G13-H13 -> 39 | J13: =I13*12 -> 468 | K13: 300 | L13: ='MAR 25'!O13 -> 20046 | M13: =F13+J13+K13+L13 -> 22614 | N13: 0 | O13: =M13-N13 -> 22614 | Q13: ALLOTED WEF MAR 22. ADV 10000. RENT 1800
A14: 9 | B14: VACANT | C14: G/9 | D14: 37347 | E14: 500 | F14: 0 | G14: 12861 | H14: ='MAR 25'!G14 -> 12861 | I14: =G14-H14 -> 0 | J14: =I14*12 -> 0 | K14: 0 | L14: ='MAR 25'!O14 -> 0 | M14: =F14+J14+K14+L14 -> 0 | O14: =M14-N14 -> 0 | Q14: VACATED WEF OCT 24.
A15: 10 | B15: PRAMOD MANDAL | C15: G/10 | D15: 37165 | E15: 500 | F15: 2000 | G15: 3938 | H15: ='MAR 25'!G15 -> 3872 | I15: =G15-H15 -> 66 | J15: =I15*12 -> 792 | K15: 300 | L15: ='MAR 25'!O15 -> 0 | M15: =F15+J15+K15+L15 -> 3092 | N15: 3100 | O15: =M15-N15 -> -8 | Q15: ALLOTED WEF SEP 22. ADV 10000 RENT 2000
A16: 11 | B16: VACANT | C16: 1/1 | D16: 38443 | E16: 0 | F16: 0 | G16: 865 | H16: ='MAR 25'!G16 -> 865 | I16: =G16-H16 -> 0 | J16: =I16*12 -> 0 | K16: 0 | L16: ='MAR 25'!O16 -> 72 | M16: =F16+J16+K16+L16 -> 72 | N16: 72 | O16: =M16-N16 -> 0 | Q16: VACANT FROM DEC 24
A17: 12 | B17: VACANT | C17: 1/2 | D17: 38292 | F17: 0 | G17: 6912 | H17: ='MAR 25'!G17 -> 6883 | I17: =G17-H17 -> 29 | J17: =I17*12 -> 348 | K17: 0 | L17: ='MAR 25'!O17 -> 468 | M17: =F17+J17+K17+L17 -> 816 | N17: 816 | O17: =M17-N17 -> 0 | Q17: VACANT FROM FEB 25.
A18: 13 | B18: VACAMT | C18: 1/3 | D18: 38292 | E18: 500 | F18: 0 | G18: 5655 | H18: ='MAR 25'!G18 -> 5618 | I18: =G18-H18 -> 37 | J18: =I18*12 -> 444 | K18: 0 | L18: ='MAR 25'!O18 -> 24 | M18: =F18+J18+K18+L18 -> 468 | N18: 468 | O18: =M18-N18 -> 0 | Q18: VACANT FROM AUG 24
A19: 14 | B19: ANIL SHARMA | C19: 1/4 | D19: 38292 | E19: 500 | F19: 3000 | G19: 4151 | H19: ='MAR 25'!G19 -> 4101 | I19: =G19-H19 -> 50 | J19: =I19*12 -> 600 | K19: 400 | L19: ='MAR 25'!O19 -> 3856 | M19: =F19+J19+K19+L19 -> 7856 | N19: 0 | O19: =M19-N19 -> 7856 | Q19: ADV 15K.19--5-24. RENT 3000
A20: 15 | B20: VACANT | C20: 1/5 | D20: 37469 | E20: 500 | F20: 0 | G20: 4246 | H20: ='MAR 25'!G20 -> 4245 | I20: =G20-H20 -> 1 | J20: =I20*12 -> 12 | K20: 0 | L20: ='MAR 25'!O20 -> 12 | M20: =F20+J20+K20+L20 -> 24 | N20: 24 | O20: =M20-N20 -> 0 | Q20: VACANT WEF NOV 2023
A21: 16 | B21: SHAILENDRA PANDEY | C21: 1/6 | D21: 37681 | E21: 500 | F21: 3000 | G21: 3551 | H21: ='MAR 25'!G21 -> 3488 | I21: =G21-H21 -> 63 | J21: =I21*12 -> 756 | K21: 400 | L21: ='MAR 25'!O21 -> 25670 | M21: =F21+J21+K21+L21 -> 29826 | N21: 0 | O21: =M21-N21 -> 29826 | Q21: RENT INCREASED WEF MAR 24 FROM 2300. ADV 10000
A22: 17 | B22: BIRENDAR YADAV | C22: 2/1 | D22: 38292 | E22: 500 | F22: 2800 | G22: 816 | H22: ='MAR 25'!G22 -> 779 | I22: =G22-H22 -> 37 | J22: =I22*12 -> 444 | K22: 400 | L22: ='MAR 25'!O22 -> 46024 | M22: =F22+J22+K22+L22 -> 49668 | N22: 10000 | O22: =M22-N22 -> 39668 | Q22: RENT INCREASED WEF DEC 22 FROM 2200. ADV NIL
A23: 18 | B23: HARI SHANKER SHUKLA | C23: 2/2 | D23: 38292 | E23: 500 | F23: 3100 | G23: 1025 | H23: ='MAR 25'!G23 -> 993 | I23: =G23-H23 -> 32 | J23: =I23*12 -> 384 | K23: 400 | L23: ='MAR 25'!O23 -> 11874 | M23: =F23+J23+K23+L23 -> 15758 | N23: 0 | O23: =M23-N23 -> 15758 | Q23: RENT INCRESED WEF JUL 24 FROM 2700. ADV 10000
A24: 19 | B24: SHIV SHANKER PANDEY | C24: 2/3 | D24: 37681 | E24: 500 | F24: 2800 | G24: 5505 | H24: ='MAR 25'!G24 -> 5476 | I24: =G24-H24 -> 29 | J24: =I24*12 -> 348 | K24: 400 | L24: ='MAR 25'!O24 -> -12 | M24: =F24+J24+K24+L24 -> 3536 | N24: 3536 | O24: =M24-N24 -> 0 | Q24: REALLOTED WEF DEC 22. RENT 2800. ADV NIL
A25: 20 | B25: PRAKASH PANDEY | C25: 2/4 | D25: 37681 | E25: 0 | F25: 2800 | G25: 1157 | H25: ='MAR 25'!G25 -> 1082 | I25: =G25-H25 -> 75 | J25: =I25*12 -> 900 | K25: 400 | L25: ='MAR 25'!O25 -> 6580 | M25: =F25+J25+K25+L25 -> 10680 | N25: 4000 | O25: =M25-N25 -> 6680 | Q25: ALLOTED FROM DEC 23. ADV NIL. RENT 2800
A26: 21 | B26: PAPPU | C26: 2/5 | D26: 37681 | E26: 500 | F26: 3000 | G26: 3355 | H26: ='MAR 25'!G26 -> 3310 | I26: =G26-H26 -> 45 | J26: =I26*12 -> 540 | K26: 400 | L26: ='MAR 25'!O26 -> 372 | M26: =F26+J26+K26+L26 -> 4312 | N26: 3500 | O26: =M26-N26 -> 812 | Q26: ALLOTED WEF DEC 24. ADV 10K, RENT 3100
A27: 22 | B27: VACANT | C27: 2/6 | D27: 37681 | E27: 0 | F27: 0 | G27: 5104 | H27: ='MAR 25'!G27 -> 5070 | I27: =G27-H27 -> 34 | J27: =I27*12 -> 408 | K27: 0 | L27: ='MAR 25'!O27 -> 0 | M27: =F27+J27+K27+L27 -> 408 | N27: 408 | O27: =M27-N27 -> 0 | Q27: VACATED WEF OCT 24.
C28: TOTAL | E28: =SUM(E6:E27) -> 7000 | F28: =SUM(F6:F27) -> 36800 | I28: =SUM(I6:I27) -> 711 | J28: =SUM(J6:J27) -> 8532 | K28: =SUM(K6:K27) -> 5200 | L28: =SUM(L6:L27) -> 208502 | M28: =SUM(M6:M27) -> 259034 | N28: =SUM(N6:N27) -> 64198 | O28: =SUM(O6:O27) -> 194836

Sheet MAR 25
A1: SITA DEVI PANDEY HOUSING PROJECT
A2: 11/1B/1 GANPAT RAI KHEMKA LANE LILUAH HOWRAH(W. B.) 711204
A3: FOR THE MONTH OF - MAR 2025 | U3: 44
A4: SNO | B4: NAME | C4: ROOM | D4: DATE OF | E4: ELECTRIC | F4: MTLY | G4: ELECTRIC | K4: MISC | L4: B/F & | M4: TOTAL | N4: AMT | O4: B/F OR | P4: PAYMENT | Q4: REMARKS
C5: NO | D5: ALLOTMENT | E5: SECURITY | F5: RENT | G5: NEW | H5: PRE | I5: TOTAL | J5: COST | K5: RENT | L5: ADV | M5: AMT DUE | N5: PAID | O5: ADV | P5: DATE
A6: 1 | B6: SUNNY PRAJAPATI | C6: G/1 | D6: 38754 | E6: 0 | F6: 2200 | G6: 1479 | H6: ='FEB 25'!G6 -> 1441 | I6: =G6-H6 -> 38 | J6: =I6*12 -> 456 | K6: 300 | L6: ='FEB 25'!O6 -> 15372 | M6: =F6+J6+K6+L6 -> 18328 | N6: 0 | O6: =M6-N6 -> 18328 | Q6: ALLOTED WEF SEP 21. ADV 10000. RENT 2000
A7: 2 | B7: LAXMI SHARMA | C7: G/2 | D7: 37653 | E7: 0 | F7: 1900 | G7: 669 | H7: 661 | I7: =G7-H7 -> 8 | J7: =I7*12 -> 96 | K7: 300 | L7: ='FEB 25'!O7 -> 0 | M7: =F7+J7+K7+L7 -> 2296 | N7: 2296 | O7: =M7-N7 -> 0 | Q7: ALLOTED WEF 07-03-2025. ADV 5K.RENT 1900
A8: 3 | B8: PANKAJ PATEL | C8: G/3 | D8: 37895 | E8: 0 | F8: 2200 | G8: 4470 | H8: ='FEB 25'!G8 -> 4453 | I8: =G8-H8 -> 17 | J8: =I8*12 -> 204 | K8: 300 | L8: ='FEB 25'!O8 -> 20110 | M8: =F8+J8+K8+L8 -> 22814 | N8: 0 | O8: =M8-N8 -> 22814 | Q8: ALLOTED WEF JUL 21. ADV 5K, RENT 2200 FM JUL 24.
A9: 4 | B9: BADRI MANDAL | C9: G/4 | D9: 38292 | E9: 500 | F9: 2000 | G9: 4541 | H9: ='FEB 25'!G9 -> 4489 | I9: =G9-H9 -> 52 | J9: =I9*12 -> 624 | K9: 300 | L9: ='FEB 25'!O9 -> 12094 | M9: =F9+J9+K9+L9 -> 15018 | N9: 0 | O9: =M9-N9 -> 15018 | Q9: ALLOTED WEF 01 DEC 2022. RENT 2000. ADV 5000
A10: 5 | B10: VACANT | C10: G/5 | F10: 0 | G10: 4297 | H10: ='FEB 25'!G10 -> 4286 | I10: =G10-H10 -> 11 | J10: =I10*12 -> 132 | K10: 0 | L10: ='FEB 25'!O10 -> 0 | M10: =F10+J10+K10+L10 -> 132 | N10: 132 | O10: =M10-N10 -> 0 | Q10: VACANT FROM JUL 24
A11: 6 | B11: VIVEK MANDAL | C11: G/6 | D11: 37667 | E11: 500 | F11: 2000 | G11: 2100 | H11: ='FEB 25'!G11 -> 2047 | I11: =G11-H11 -> 53 | J11: =I11*12 -> 636 | K11: 300 | L11: ='FEB 25'!O11 -> 24096 | M11: =F11+J11+K11+L11 -> 27032 | N11: 0 | O11: =M11-N11 -> 27032 | Q11: ALLOTED WEF JUN 24. ADV 4000, RENT 2000
A12: 7 | B12: RAM P SHRESTHA | C12: G/7 | D12: 37773 | E12: 500 | F12: 2200 | G12: 4974 | H12: ='FEB 25'!G12 -> 4953 | I12: =G12-H12 -> 21 | J12: =I12*12 -> 252 | K12: 300 | L12: ='FEB 25'!O12 -> 5072 | M12: =F12+J12+K12+L12 -> 7824 | N12: 0 | O12: =M12-N12 -> 7824 | Q12: ALLOTED WEF SEP 21. ADV 10000. RENT 2000
A13: 8 | B13: AJAY BAG | C13: G/8 | D13: 37469 | E13: 500 | F13: 1800 | G13: 3462 | H13: ='FEB 25'!G13 -> 3365 | I13: =G13-H13 -> 97 | J13: =I13*12 -> 1164 | K13: 300 | L13: ='FEB 25'!O13 -> 16782 | M13: =F13+J13+K13+L13 -> 20046 | N13: 0 | O13: =M13-N13 -> 20046 | Q13: ALLOTED WEF MAR 22. ADV 10000. RENT 1800
A14: 9 | B14: VACANT | C14: G/9 | D14: 37347 | E14: 500 | F14: 0 | G14: 12861 | H14: ='FEB 25'!G14 -> 12861 | I14: =G14-H14 -> 0 | J14: =I14*12 -> 0 | K14: 0 | L14: ='FEB 25'!O14 -> 0 | M14: =F14+J14+K14+L14 -> 0 | N14: 0 | O14: =M14-N14 -> 0 | Q14: VACATED WEF OCT 24.
A15: 10 | B15: PRAMOD MANDAL | C15: G/10 | D15: 37165 | E15: 500 | F15: 2000 | G15: 3872 | H15: ='FEB 25'!G15 -> 3815 | I15: =G15-H15 -> 57 | J15: =I15*12 -> 684 | K15: 300 | L15: ='FEB 25'!O15 -> 0 | M15: =F15+J15+K15+L15 -> 2984 | N15: 2984 | O15: =M15-N15 -> 0 | Q15: ALLOTED WEF SEP 22. ADV 10000 RENT 2000
A16: 11 | B16: VACANT | C16: 1/1 | D16: 38443 | E16: 0 | F16: 0 | G16: 865 | H16: ='FEB 25'!G16 -> 859 | I16: =G16-H16 -> 6 | J16: =I16*12 -> 72 | K16: 0 | L16: ='FEB 25'!O16 -> 0 | M16: =F16+J16+K16+L16 -> 72 | N16: 0 | O16: =M16-N16 -> 72 | Q16: VACANT FROM DEC 24
A17: 12 | B17: VACANT | C17: 1/2 | D17: 38292 | F17: 0 | G17: 6883 | H17: ='FEB 25'!G17 -> 6844 | I17: =G17-H17 -> 39 | J17: =I17*12 -> 468 | K17: 0 | L17: ='FEB 25'!O17 -> 0 | M17: =F17+J17+K17+L17 -> 468 | N17: 0 | O17: =M17-N17 -> 468 | Q17: VACANT FROM FEB 25.
A18: 13 | B18: VACAMT | C18: 1/3 | D18: 38292 | E18: 500 | F18: 0 | G18: 5618 | H18: ='FEB 25'!G18 -> 5616 | I18: =G18-H18 -> 2 | J18: =I18*12 -> 24 | K18: 0 | L18: ='FEB 25'!O18 -> 0 | M18: =F18+J18+K18+L18 -> 24 | N18: 0 | O18: =M18-N18 -> 24 | Q18: VACANT FROM AUG 24
A19: 14 | B19: ANIL SHARMA | C19: 1/4 | D19: 38292 | E19: 500 | F19: 3000 | G19: 4101 | H19: ='FEB 25'!G19 -> 4063 | I19: =G19-H19 -> 38 | J19: =I19*12 -> 456 | K19: 400 | L19: ='FEB 25'!O19 -> 0 | M19: =F19+J19+K19+L19 -> 3856 | N19: 0 | O19: =M19-N19 -> 3856 | Q19: ADV 15K.19--5-24. RENT 3000
A20: 15 | B20: VACANT | C20: 1/5 | D20: 37469 | E20: 500 | F20: 0 | G20: 4245 | H20: ='FEB 25'!G20 -> 4244 | I20: =G20-H20 -> 1 | J20: =I20*12 -> 12 | K20: 0 | L20: ='FEB 25'!O20 -> 0 | M20: =F20+J20+K20+L20 -> 12 | N20: 0 | O20: =M20-N20 -> 12 | Q20: VACANT WEF NOV 2023
A21: 16 | B21: SHAILENDRA PANDEY | C21: 1/6 | D21: 37681 | E21: 500 | F21: 3000 | G21: 3488 | H21: ='FEB 25'!G21 -> 3439 | I21: =G21-H21 -> 49 | J21: =I21*12 -> 588 | K21: 400 | L21: ='FEB 25'!O21 -> 21682 | M21: =F21+J21+K21+L21 -> 25670 | N21: 0 | O21: =M21-N21 -> 25670 | Q21: RENT INCREASED WEF MAR 24 FROM 2300. ADV 10000
A22: 17 | B22: BIRENDAR YADAV | C22: 2/1 | D22: 38292 | E22: 500 | F22: 2800 | G22: 779 | H22: ='FEB 25'!G22 -> 747 | I22: =G22-H22 -> 32 | J22: =I22*12 -> 384 | K22: 400 | L22: ='FEB 25'!O22 -> 42440 | M22: =F22+J22+K22+L22 -> 46024 | N22: 0 | O22: =M22-N22 -> 46024 | Q22: RENT INCREASED WEF DEC 22 FROM 2200. ADV NIL
A23: 18 | B23: HARI SHANKER SHUKLA | C23: 2/2 | D23: 38292 | E23: 500 | F23: 3100 | G23: 993 | H23: 973 | I23: =G23-H23 -> 20 | J23: =I23*12 -> 240 | K23: 400 | L23: ='FEB 25'!O23 -> 14134 | M23: =F23+J23+K23+L23 -> 17874 | N23: 6000 | O23: =M23-N23 -> 11874 | Q23: RENT INCRESED WEF JUL 24 FROM 2700. ADV 10000
A24: 19 | B24: SHIV SHANKER PANDEY | C24: 2/3 | D24: 37681 | E24: 500 | F24: 2800 | G24: 5476 | H24: ='FEB 25'!G24 -> 5452 | I24: =G24-H24 -> 24 | J24: =I24*12 -> 288 | K24: 400 | L24: ='FEB 25'!O24 -> 0 | M24: =F24+J24+K24+L24 -> 3488 | N24: 3500 | O24: =M24-N24 -> -12 | Q24: REALLOTED WEF DEC 22. RENT 2800. ADV NIL
A25: 20 | B25: PRAKASH PANDEY | C25: 2/4 | D25: 37681 | E25: 0 | F25: 2800 | G25: 1082 | H25: ='FEB 25'!G25 -> 1022 | I25: =G25-H25 -> 60 | J25: =I25*12 -> 720 | K25: 400 | L25: ='FEB 25'!O25 -> 2660 | M25: =F25+J25+K25+L25 -> 6580 | N25: 0 | O25: =M25-N25 -> 6580 | Q25: ALLOTED FROM DEC 23. ADV NIL. RENT 2800
A26: 21 | B26: PAPPU | C26: 2/5 | D26: 37681 | E26: 500 | F26: 3000 | G26: 3310 | H26: ='FEB 25'!G26 -> 3267 | I26: =G26-H26 -> 43 | J26: =I26*12 -> 516 | K26: 400 | L26: ='FEB 25'!O26 -> 3456 | M26: =F26+J26+K26+L26 -> 7372 | N26: 7000 | O26: =M26-N26 -> 372 | Q26: ALLOTED WEF DEC 24. ADV 10K, RENT 3100
A27: 22 | B27: VACANT | C27: 2/6 | D27: 37681 | E27: 0 | F27: 0 | G27: 5070 | H27: ='FEB 25'!G27 -> 5070 | I27: =G27-H27 -> 0 | J27: =I27*12 -> 0 | K27: 0 | L27: ='FEB 25'!O27 -> 0 | M27: =F27+J27+K27+L27 -> 0 | N27: 0 | O27: =M27-N27 -> 0 | Q27: VACATED WEF OCT 24.
C28: TOTAL | E28: =SUM(E6:E27) -> 7000 | F28: =SUM(F6:F27) -> 36800 | I28: =SUM(I6:I27) -> 668 | J28: =SUM(J6:J27) -> 8016 | K28: =SUM(K6:K27) -> 5200 | L28: =SUM(L6:L27) -> 177898 | M28: =SUM(M6:M27) -> 227914 | N28: =SUM(N6:N27) -> 21912 | O28: =SUM(O6:O27) -> 206002

Sheet DEC 24
A1: SITA DEVI PANDEY HOUSING PROJECT
A2: 11/1B/1 GANPAT RAI KHEMKA LANE LILUAH HOWRAH(W. B.) 711204
A3: FOR THE MONTH OF - DEC 2024 | U3: 44
A4: SNO | B4: NAME | C4: ROOM | D4: DATE OF | E4: ELECTRIC | F4: MTLY | G4: ELECTRIC | K4: MISC | L4: B/F & | M4: TOTAL | N4: AMT | O4: B/F OR | P4: PAYMENT | Q4: REMARKS
C5: NO | D5: ALLOTMENT | E5: SECURITY | F5: RENT | G5: NEW | H5: PRE | I5: TOTAL | J5: COST | K5: RENT | L5: ADV | M5: AMT DUE | N5: PAID | O5: ADV | P5: DATE
A6: 1 | B6: SUNNY PRAJAPATI | C6: G/1 | D6: 38754 | E6: 0 | F6: 2200 | G6: 1415 | H6: ='NOV 24'!G6 -> 1402 | I6: =G6-H6 -> 13 | J6: =I6*12 -> 156 | K6: 300 | L6: ='NOV 24'!O6 -> 7404 | M6: =F6+J6+K6+L6 -> 10060 | N6: 0 | O6: =M6-N6 -> 10060 | Q6: ALLOTED WEF SEP 21. ADV 10000. RENT 2000
A7: 2 | B7: VACANT | C7: G/2 | D7: 37653 | E7: 0 | F7: 0 | G7: 655 | H7: ='NOV 24'!G7 -> 655 | I7: =G7-H7 -> 0 | J7: =I7*12 -> 0 | K7: 0 | L7: ='NOV 24'!O7 -> 0 | M7: 0 | N7: 0 | O7: =M7-N7 -> 0 | Q7: VACANT FM SEP 24
A8: 3 | B8: PANKAJ PATEL | C8: G/3 | D8: 37895 | E8: 0 | F8: 2200 | G8: 4445 | H8: ='NOV 24'!G8 -> 4444 | I8: =G8-H8 -> 1 | J8: =I8*12 -> 12 | K8: 300 | L8: ='NOV 24'!O8 -> 18502 | M8: =F8+J8+K8+L8 -> 21014 | N8: 3000 | O8: =M8-N8 -> 18014 | Q8: ALLOTED WEF JUL 21. ADV 5K, RENT 2200 FM JUL 24.
A9: 4 | B9: BADRI MANDAL | C9: G/4 | D9: 38292 | E9: 500 | F9: 2000 | G9: 4481 | H9: ='NOV 24'!G9 -> 4476 | I9: =G9-H9 -> 5 | J9: =I9*12 -> 60 | K9: 300 | L9: ='NOV 24'!O9 -> 10038 | M9: =F9+J9+K9+L9 -> 12398 | N9: 0 | O9: =M9-N9 -> 12398 | Q9: ALLOTED WEF 01 DEC 2022. RENT 2000. ADV 5000
A10: 5 | B10: VACANT | C10: G/5 | F10: 0 | G10: 4286 | H10: 4286 | I10: =G10-H10 -> 0 | J10: =I10*12 -> 0 | K10: 0 | L10: ='NOV 24'!O10 -> 0 | M10: =F10+J10+K10+L10 -> 0 | N10: 0 | O10: =M10-N10 -> 0 | Q10: VACANT FROM JUL 24
A11: 6 | B11: VIVEK MANDAL | C11: G/6 | D11: 37667 | E11: 500 | F11: 2000 | G11: 2008 | H11: ='NOV 24'!G11 -> 2005 | I11: =G11-H11 -> 3 | J11: =I11*12 -> 36 | K11: 300 | L11: ='NOV 24'!O11 -> 16692 | M11: =F11+J11+K11+L11 -> 19028 | N11: 0 | O11: =M11-N11 -> 19028 | Q11: ALLOTED WEF JUN 24. ADV 4000, RENT 2000
A12: 7 | B12: RAM P SHRESTHA | C12: G/7 | D12: 37773 | E12: 500 | F12: 2200 | G12: 4947 | H12: ='NOV 24'!G12 -> 4944 | I12: =G12-H12 -> 3 | J12: =I12*12 -> 36 | K12: 300 | L12: ='NOV 24'!O12 -> 200 | M12: =F12+J12+K12+L12 -> 2736 | N12: 0 | O12: =M12-N12 -> 2736 | Q12: ALLOTED WEF SEP 21. ADV 10000. RENT 2000
A13: 8 | B13: AJAY BAG | C13: G/8 | D13: 37469 | E13: 500 | F13: 1800 | G13: 3330 | H13: ='NOV 24'!G13 -> 3325 | I13: =G13-H13 -> 5 | J13: =I13*12 -> 60 | K13: 300 | L13: ='NOV 24'!O13 -> 10002 | M13: =F13+J13+K13+L13 -> 12162 | N13: 0 | O13: =M13-N13 -> 12162 | Q13: ALLOTED WEF MAR 22. ADV 10000. RENT 1800
A14: 9 | B14: VACANT | C14: G/9 | D14: 37347 | E14: 500 | F14: 0 | G14: 12861 | H14: ='NOV 24'!G14 -> 12861 | I14: =G14-H14 -> 0 | J14: =I14*12 -> 0 | K14: 0 | L14: ='NOV 24'!O14 -> 0 | M14: =F14+J14+K14+L14 -> 0 | O14: =M14-N14 -> 0 | Q14: VACATED WEF OCT 24.
A15: 10 | B15: PRAMOD MANDAL | C15: G/10 | D15: 37165 | E15: 500 | F15: 2000 | G15: 3789 | H15: ='NOV 24'!G15 -> 3778 | I15: =G15-H15 -> 11 | J15: =I15*12 -> 132 | K15: 300 | L15: ='NOV 24'!O15 -> 0 | M15: =F15+J15+K15+L15 -> 2432 | N15: 2432 | O15: =M15-N15 -> 0 | Q15: ALLOTED WEF SEP 22. ADV 10000 RENT 2000
A16: 11 | B16: NEW | C16: 1/1 | D16: 38443 | E16: 0 | F16: 2400 | G16: 859 | H16: ='NOV 24'!G16 -> 856 | I16: =G16-H16 -> 3 | J16: =I16*12 -> 36 | K16: 400 | L16: ='NOV 24'!O16 -> 12 | M16: =F16+J16+K16+L16 -> 2848 | N16: 2848 | O16: =M16-N16 -> 0 | Q16: VACATED. ALL DUES CLEAR
A17: 12 | B17: RAKESH AGARWAL | C17: 1/2 | D17: 38292 | F17: 3100 | G17: 6842 | H17: ='NOV 24'!G17 -> 6835 | I17: =G17-H17 -> 7 | J17: =I17*12 -> 84 | K17: 400 | L17: ='NOV 24'!O17 -> 9888 | M17: =F17+J17+K17+L17 -> 13472 | N17: 0 | O17: =M17-N17 -> 13472 | Q17: ALLOTED WEF JUL 24. ADV 10K. RENT 3100
A18: 13 | B18: VACAMT | C18: 1/3 | D18: 38292 | E18: 500 | F18: 0 | G18: 5616 | H18: ='NOV 24'!G18 -> 5616 | I18: =G18-H18 -> 0 | J18: =I18*12 -> 0 | K18: 0 | L18: ='NOV 24'!O18 -> 0 | M18: =F18+J18+K18+L18 -> 0 | N18: 0 | O18: =M18-N18 -> 0 | Q18: VACANT FROM AUG 24
A19: 14 | B19: ANIL SHARMA | C19: 1/4 | D19: 38292 | E19: 500 | F19: 3000 | G19: 4032 | H19: ='NOV 24'!G19 -> 4026 | I19: =G19-H19 -> 6 | J19: =I19*12 -> 72 | K19: 400 | L19: ='NOV 24'!O19 -> 0 | M19: =F19+J19+K19+L19 -> 3472 | N19: 3480 | O19: =M19-N19 -> -8 | Q19: ADV 15K.19--5-24. RENT 3000
A20: 15 | B20: VACANT | C20: 1/5 | D20: 37469 | E20: 500 | F20: 0 | G20: 4244 | H20: ='NOV 24'!G20 -> 4244 | I20: =G20-H20 -> 0 | J20: =I20*12 -> 0 | K20: 0 | L20: ='NOV 24'!O20 -> 0 | M20: =F20+J20+K20+L20 -> 0 | N20: 0 | O20: =M20-N20 -> 0 | Q20: VACANT WEF NOV 2023
A21: 16 | B21: SHAILENDRA PANDEY | C21: 1/6 | D21: 37681 | E21: 500 | F21: 3000 | G21: 3381 | H21: ='NOV 24'!G21 -> 3368 | I21: =G21-H21 -> 13 | J21: =I21*12 -> 156 | K21: 400 | L21: ='NOV 24'!O21 -> 20630 | M21: =F21+J21+K21+L21 -> 24186 | N21: 5000 | O21: =M21-N21 -> 19186 | Q21: RENT INCREASED WEF MAR 24 FROM 2300. ADV 10000
A22: 17 | B22: BIRENDAR YADAV | C22: 2/1 | D22: 38292 | E22: 500 | F22: 2800 | G22: 712 | H22: ='NOV 24'!G22 -> 702 | I22: =G22-H22 -> 10 | J22: =I22*12 -> 120 | K22: 400 | L22: ='NOV 24'!O22 -> 44300 | M22: =F22+J22+K22+L22 -> 47620 | N22: 7000 | O22: =M22-N22 -> 40620 | Q22: RENT INCREASED WEF DEC 22 FROM 2200. ADV NIL
A23: 18 | B23: HARI SHANKER SHUKLA | C23: 2/2 | D23: 38292 | E23: 500 | F23: 3100 | G23: 976 | H23: ='NOV 24'!G23 -> 976 | I23: =G23-H23 -> 0 | J23: =I23*12 -> 0 | K23: 400 | L23: ='NOV 24'!O23 -> 13634 | M23: =F23+J23+K23+L23 -> 17134 | N23: 0 | O23: =M23-N23 -> 17134 | Q23: RENT INCRESED WEF JUL 24 FROM 2700. ADV 10000
A24: 19 | B24: SHIV SHANKER PANDEY | C24: 2/3 | D24: 37681 | E24: 500 | F24: 2800 | G24: 5432 | H24: ='NOV 24'!G24 -> 5424 | I24: =G24-H24 -> 8 | J24: =I24*12 -> 96 | K24: 400 | L24: ='NOV 24'!O24 -> 0 | M24: =F24+J24+K24+L24 -> 3296 | N24: 3296 | O24: =M24-N24 -> 0 | Q24: REALLOTED WEF DEC 22. RENT 2800. ADV NIL
A25: 20 | B25: PRAKASH PANDEY | C25: 2/4 | D25: 37681 | E25: 0 | F25: 2800 | G25: 956 | H25: ='NOV 24'!G25 -> 940 | I25: =G25-H25 -> 16 | J25: =I25*12 -> 192 | K25: 400 | L25: ='NOV 24'!O25 -> 7076 | M25: =F25+J25+K25+L25 -> 10468 | N25: 5000 | O25: =M25-N25 -> 5468 | Q25: ALLOTED FROM DEC 23. ADV NIL. RENT 2800
A26: 21 | B26: VACANT | C26: 2/5 | D26: 37681 | E26: 500 | F26: 0 | G26: 3254 | H26: ='NOV 24'!G26 -> 3254 | I26: =G26-H26 -> 0 | J26: =I26*12 -> 0 | K26: 0 | L26: ='NOV 24'!O26 -> 0 | M26: =F26+J26+K26+L26 -> 0 | N26: 0 | O26: =M26-N26 -> 0 | Q26: VACATED WEF NOV 23.
A27: 22 | B27: VACANT | C27: 2/6 | D27: 37681 | E27: 0 | F27: 0 | G27: 5051 | H27: ='NOV 24'!G27 -> 5051 | I27: =G27-H27 -> 0 | J27: =I27*12 -> 0 | K27: 0 | L27: ='NOV 24'!O27 -> 0 | M27: =F27+J27+K27+L27 -> 0 | N27: 0 | O27: =M27-N27 -> 0 | Q27: VACATED WEF OCT 24.
C28: TOTAL | E28: =SUM(E6:E27) -> 7000 | F28: =SUM(F6:F27) -> 37400 | I28: =SUM(I6:I27) -> 104 | J28: =SUM(J6:J27) -> 1248 | K28: =SUM(K6:K27) -> 5300 | L28: =SUM(L6:L27) -> 158378 | M28: =SUM(M6:M27) -> 202326 | N28: =SUM(N6:N27) -> 32056 | O28: =SUM(O6:O27) -> 170270

Sheet FEB 25
A1: SITA DEVI PANDEY HOUSING PROJECT
A2: 11/1B/1 GANPAT RAI KHEMKA LANE LILUAH HOWRAH(W. B.) 711204
A3: FOR THE MONTH OF - JAN 2025 | U3: 44
A4: SNO | B4: NAME | C4: ROOM | D4: DATE OF | E4: ELECTRIC | F4: MTLY | G4: ELECTRIC | K4: MISC | L4: B/F & | M4: TOTAL | N4: AMT | O4: B/F OR | P4: PAYMENT | Q4: REMARKS
C5: NO | D5: ALLOTMENT | E5: SECURITY | F5: RENT | G5: NEW | H5: PRE | I5: TOTAL | J5: COST | K5: RENT | L5: ADV | M5: AMT DUE | N5: PAID | O5: ADV | P5: DATE
A6: 1 | B6: SUNNY PRAJAPATI | C6: G/1 | D6: 38754 | E6: 0 | F6: 2200 | G6: 1441 | H6: ='JAN 25'!G6 -> 1432 | I6: =G6-H6 -> 9 | J6: =I6*12 -> 108 | K6: 300 | L6: ='JAN 25'!O6 -> 12764 | M6: =F6+J6+K6+L6 -> 15372 | N6: 0 | O6: =M6-N6 -> 15372 | Q6: ALLOTED WEF SEP 21. ADV 10000. RENT 2000
A7: 2 | B7: VACANT | C7: G/2 | D7: 37653 | E7: 0 | F7: 0 | G7: 655 | H7: ='JAN 25'!G7 -> 655 | I7: =G7-H7 -> 0 | J7: =I7*12 -> 0 | K7: 0 | L7: ='JAN 25'!O7 -> 0 | M7: 0 | N7: 0 | O7: =M7-N7 -> 0 | Q7: VACANT FM SEP 24
A8: 3 | B8: PANKAJ PATEL | C8: G/3 | D8: 37895 | E8: 0 | F8: 2200 | G8: 4453 | H8: ='JAN 25'!G8 -> 4448 | I8: =G8-H8 -> 5 | J8: =I8*12 -> 60 | K8: 300 | L8: ='JAN 25'!O8 -> 17550 | M8: =F8+J8+K8+L8 -> 20110 | N8: 0 | O8: =M8-N8 -> 20110 | Q8: ALLOTED WEF JUL 21. ADV 5K, RENT 2200 FM JUL 24.
A9: 4 | B9: BADRI MANDAL | C9: G/4 | D9: 38292 | E9: 500 | F9: 2000 | G9: 4489 | H9: ='JAN 25'!G9 -> 4488 | I9: =G9-H9 -> 1 | J9: =I9*12 -> 12 | K9: 300 | L9: ='JAN 25'!O9 -> 9782 | M9: =F9+J9+K9+L9 -> 12094 | N9: 0 | O9: =M9-N9 -> 12094 | Q9: ALLOTED WEF 01 DEC 2022. RENT 2000. ADV 5000
A10: 5 | B10: VACANT | C10: G/5 | F10: 0 | G10: 4286 | H10: ='JAN 25'!G10 -> 4286 | I10: =G10-H10 -> 0 | J10: =I10*12 -> 0 | K10: 0 | L10: ='JAN 25'!O10 -> 0 | M10: =F10+J10+K10+L10 -> 0 | N10: 0 | O10: =M10-N10 -> 0 | Q10: VACANT FROM JUL 24
A11: 6 | B11: VIVEK MANDAL | C11: G/6 | D11: 37667 | E11: 500 | F11: 2000 | G11: 2047 | H11: ='JAN 25'!G11 -> 2016 | I11: =G11-H11 -> 31 | J11: =I11*12 -> 372 | K11: 300 | L11: ='JAN 25'!O11 -> 21424 | M11: =F11+J11+K11+L11 -> 24096 | N11: 0 | O11: =M11-N11 -> 24096 | Q11: ALLOTED WEF JUN 24. ADV 4000, RENT 2000
A12: 7 | B12: RAM P SHRESTHA | C12: G/7 | D12: 37773 | E12: 500 | F12: 2200 | G12: 4953 | H12: ='JAN 25'!G12 -> 4949 | I12: =G12-H12 -> 4 | J12: =I12*12 -> 48 | K12: 300 | L12: ='JAN 25'!O12 -> 2524 | M12: =F12+J12+K12+L12 -> 5072 | N12: 0 | O12: =M12-N12 -> 5072 | Q12: ALLOTED WEF SEP 21. ADV 10000. RENT 2000
A13: 8 | B13: AJAY BAG | C13: G/8 | D13: 37469 | E13: 500 | F13: 1800 | G13: 3365 | H13: ='JAN 25'!G13 -> 3338 | I13: =G13-H13 -> 27 | J13: =I13*12 -> 324 | K13: 300 | L13: ='JAN 25'!O13 -> 14358 | M13: =F13+J13+K13+L13 -> 16782 | N13: 0 | O13: =M13-N13 -> 16782 | Q13: ALLOTED WEF MAR 22. ADV 10000. RENT 1800
A14: 9 | B14: VACANT | C14: G/9 | D14: 37347 | E14: 500 | F14: 0 | G14: 12861 | H14: ='JAN 25'!G14 -> 12861 | I14: =G14-H14 -> 0 | J14: =I14*12 -> 0 | K14: 0 | L14: ='JAN 25'!O14 -> 0 | M14: =F14+J14+K14+L14 -> 0 | N14: 0 | O14: =M14-N14 -> 0 | Q14: VACATED WEF OCT 24.
A15: 10 | B15: PRAMOD MANDAL | C15: G/10 | D15: 37165 | E15: 500 | F15: 2000 | G15: 3815 | H15: ='JAN 25'!G15 -> 3800 | I15: =G15-H15 -> 15 | J15: =I15*12 -> 180 | K15: 300 | L15: ='JAN 25'!O15 -> 0 | M15: =F15+J15+K15+L15 -> 2480 | N15: 2480 | O15: =M15-N15 -> 0 | Q15: ALLOTED WEF SEP 22. ADV 10000 RENT 2000
A16: 11 | B16: VACANT | C16: 1/1 | D16: 38443 | E16: 0 | F16: 0 | G16: 859 | H16: ='JAN 25'!G16 -> 859 | I16: =G16-H16 -> 0 | J16: =I16*12 -> 0 | K16: 0 | L16: ='JAN 25'!O16 -> 0 | M16: =F16+J16+K16+L16 -> 0 | N16: 0 | O16: =M16-N16 -> 0 | Q16: VACANT FROM DEC 24
A17: 12 | B17: RAKESH AGARWAL | C17: 1/2 | D17: 38292 | F17: 3100 | G17: 6844 | H17: ='JAN 25'!G17 -> 6844 | I17: =G17-H17 -> 0 | J17: =I17*12 -> 0 | K17: 400 | L17: ='JAN 25'!O17 -> 16996 | M17: =F17+J17+K17+L17 -> 20496 | N17: 20496 | O17: =M17-N17 -> 0 | Q17: VACANT FROM FEB 25.
A18: 13 | B18: VACAMT | C18: 1/3 | D18: 38292 | E18: 500 | F18: 0 | G18: 5616 | H18: ='JAN 25'!G18 -> 5616 | I18: =G18-H18 -> 0 | J18: =I18*12 -> 0 | K18: 0 | L18: ='JAN 25'!O18 -> 0 | M18: =F18+J18+K18+L18 -> 0 | N18: 0 | O18: =M18-N18 -> 0 | Q18: VACANT FROM AUG 24
A19: 14 | B19: ANIL SHARMA | C19: 1/4 | D19: 38292 | E19: 500 | F19: 3000 | G19: 4063 | H19: ='JAN 25'!G19 -> 4039 | I19: =G19-H19 -> 24 | J19: =I19*12 -> 288 | K19: 400 | L19: ='JAN 25'!O19 -> -4 | M19: =F19+J19+K19+L19 -> 3684 | N19: 3684 | O19: =M19-N19 -> 0 | Q19: ADV 15K.19--5-24. RENT 3000
A20: 15 | B20: VACANT | C20: 1/5 | D20: 37469 | E20: 500 | F20: 0 | G20: 4244 | H20: ='JAN 25'!G20 -> 4244 | I20: =G20-H20 -> 0 | J20: =I20*12 -> 0 | K20: 0 | L20: ='JAN 25'!O20 -> 0 | M20: =F20+J20+K20+L20 -> 0 | N20: 0 | O20: =M20-N20 -> 0 | Q20: VACANT WEF NOV 2023
A21: 16 | B21: SHAILENDRA PANDEY | C21: 1/6 | D21: 37681 | E21: 500 | F21: 3000 | G21: 3439 | H21: ='JAN 25'!G21 -> 3416 | I21: =G21-H21 -> 23 | J21: =I21*12 -> 276 | K21: 400 | L21: ='JAN 25'!O21 -> 23006 | M21: =F21+J21+K21+L21 -> 26682 | N21: 5000 | O21: =M21-N21 -> 21682 | Q21: RENT INCREASED WEF MAR 24 FROM 2300. ADV 10000
A22: 17 | B22: BIRENDAR YADAV | C22: 2/1 | D22: 38292 | E22: 500 | F22: 2800 | G22: 747 | H22: ='JAN 25'!G22 -> 729 | I22: =G22-H22 -> 18 | J22: =I22*12 -> 216 | K22: 400 | L22: ='JAN 25'!O22 -> 44024 | M22: =F22+J22+K22+L22 -> 47440 | N22: 5000 | O22: =M22-N22 -> 42440 | Q22: RENT INCREASED WEF DEC 22 FROM 2200. ADV NIL
A23: 18 | B23: HARI SHANKER SHUKLA | C23: 2/2 | D23: 38292 | E23: 500 | F23: 3100 | G23: 976 | H23: ='JAN 25'!G23 -> 976 | I23: =G23-H23 -> 0 | J23: =I23*12 -> 0 | K23: 400 | L23: ='JAN 25'!O23 -> 20634 | M23: =F23+J23+K23+L23 -> 24134 | N23: 10000 | O23: =M23-N23 -> 14134 | Q23: RENT INCRESED WEF JUL 24 FROM 2700. ADV 10000
A24: 19 | B24: SHIV SHANKER PANDEY | C24: 2/3 | D24: 37681 | E24: 500 | F24: 2800 | G24: 5452 | H24: ='JAN 25'!G24 -> 5441 | I24: =G24-H24 -> 11 | J24: =I24*12 -> 132 | K24: 400 | L24: ='JAN 25'!O24 -> -2 | M24: =F24+J24+K24+L24 -> 3330 | N24: 3330 | O24: =M24-N24 -> 0 | Q24: REALLOTED WEF DEC 22. RENT 2800. ADV NIL
A25: 20 | B25: PRAKASH PANDEY | C25: 2/4 | D25: 37681 | E25: 0 | F25: 2800 | G25: 1022 | H25: ='JAN 25'!G25 -> 986 | I25: =G25-H25 -> 36 | J25: =I25*12 -> 432 | K25: 400 | L25: ='JAN 25'!O25 -> 4028 | M25: =F25+J25+K25+L25 -> 7660 | N25: 5000 | O25: =M25-N25 -> 2660 | Q25: ALLOTED FROM DEC 23. ADV NIL. RENT 2800
A26: 21 | B26: PAPPU | C26: 2/5 | D26: 37681 | E26: 500 | F26: 3000 | G26: 3267 | H26: ='JAN 25'!G26 -> 3257 | I26: =G26-H26 -> 10 | J26: =I26*12 -> 120 | K26: 400 | L26: ='JAN 25'!O26 -> -64 | M26: =F26+J26+K26+L26 -> 3456 | N26: 0 | O26: =M26-N26 -> 3456 | Q26: ALLOTED WEF DEC 24. ADV 10K, RENT 3100
A27: 22 | B27: VACANT | C27: 2/6 | D27: 37681 | E27: 0 | F27: 0 | G27: 5070 | H27: ='JAN 25'!G27 -> 5070 | I27: =G27-H27 -> 0 | J27: =I27*12 -> 0 | K27: 0 | L27: ='JAN 25'!O27 -> 0 | M27: =F27+J27+K27+L27 -> 0 | N27: 0 | O27: =M27-N27 -> 0 | Q27: VACATED WEF OCT 24.
C28: TOTAL | E28: =SUM(E6:E27) -> 7000 | F28: =SUM(F6:F27) -> 38000 | I28: =SUM(I6:I27) -> 214 | J28: =SUM(J6:J27) -> 2568 | K28: =SUM(K6:K27) -> 5300 | L28: =SUM(L6:L27) -> 187020 | M28: =SUM(M6:M27) -> 232888 | N28: =SUM(N6:N27) -> 54990 | O28: =SUM(O6:O27) -> 177898

Sheet JAN 25
A1: SITA DEVI PANDEY HOUSING PROJECT
A2: 11/1B/1 GANPAT RAI KHEMKA LANE LILUAH HOWRAH(W. B.) 711204
A3: FOR THE MONTH OF - JAN 2025 | U3: 44
A4: SNO | B4: NAME | C4: ROOM | D4: DATE OF | E4: ELECTRIC | F4: MTLY | G4: ELECTRIC | K4: MISC | L4: B/F & | M4: TOTAL | N4: AMT | O4: B/F OR | P4: PAYMENT | Q4: REMARKS
C5: NO | D5: ALLOTMENT | E5: SECURITY | F5: RENT | G5: NEW | H5: PRE | I5: TOTAL | J5: COST | K5: RENT | L5: ADV | M5: AMT DUE | N5: PAID | O5: ADV | P5: DATE
A6: 1 | B6: SUNNY PRAJAPATI | C6: G/1 | D6: 38754 | E6: 0 | F6: 2200 | G6: 1432 | H6: ='DEC 24'!G6 -> 1415 | I6: =G6-H6 -> 17 | J6: =I6*12 -> 204 | K6: 300 | L6: ='DEC 24'!O6 -> 10060 | M6: =F6+J6+K6+L6 -> 12764 | N6: 0 | O6: =M6-N6 -> 12764 | Q6: ALLOTED WEF SEP 21. ADV 10000. RENT 2000
A7: 2 | B7: VACANT | C7: G/2 | D7: 37653 | E7: 0 | F7: 0 | G7: 655 | H7: ='DEC 24'!G7 -> 655 | I7: =G7-H7 -> 0 | J7: =I7*12 -> 0 | K7: 0 | L7: ='DEC 24'!O7 -> 0 | M7: 0 | N7: 0 | O7: =M7-N7 -> 0 | Q7: VACANT FM SEP 24
A8: 3 | B8: PANKAJ PATEL | C8: G/3 | D8: 37895 | E8: 0 | F8: 2200 | G8: 4448 | H8: ='DEC 24'!G8 -> 4445 | I8: =G8-H8 -> 3 | J8: =I8*12 -> 36 | K8: 300 | L8: ='DEC 24'!O8 -> 18014 | M8: =F8+J8+K8+L8 -> 20550 | N8: 3000 | O8: =M8-N8 -> 17550 | Q8: ALLOTED WEF JUL 21. ADV 5K, RENT 2200 FM JUL 24.
A9: 4 | B9: BADRI MANDAL | C9: G/4 | D9: 38292 | E9: 500 | F9: 2000 | G9: 4488 | H9: ='DEC 24'!G9 -> 4481 | I9: =G9-H9 -> 7 | J9: =I9*12 -> 84 | K9: 300 | L9: ='DEC 24'!O9 -> 12398 | M9: =F9+J9+K9+L9 -> 14782 | N9: 5000 | O9: =M9-N9 -> 9782 | Q9: ALLOTED WEF 01 DEC 2022. RENT 2000. ADV 5000
A10: 5 | B10: VACANT | C10: G/5 | F10: 0 | G10: 4286 | H10: ='DEC 24'!G10 -> 4286 | I10: =G10-H10 -> 0 | J10: =I10*12 -> 0 | K10: 0 | L10: ='DEC 24'!O10 -> 0 | M10: =F10+J10+K10+L10 -> 0 | N10: 0 | O10: =M10-N10 -> 0 | Q10: VACANT FROM JUL 24
A11: 6 | B11: VIVEK MANDAL | C11: G/6 | D11: 37667 | E11: 500 | F11: 2000 | G11: 2016 | H11: ='DEC 24'!G11 -> 2008 | I11: =G11-H11 -> 8 | J11: =I11*12 -> 96 | K11: 300 | L11: ='DEC 24'!O11 -> 19028 | M11: =F11+J11+K11+L11 -> 21424 | N11: 0 | O11: =M11-N11 -> 21424 | Q11: ALLOTED WEF JUN 24. ADV 4000, RENT 2000
A12: 7 | B12: RAM P SHRESTHA | C12: G/7 | D12: 37773 | E12: 500 | F12: 2200 | G12: 4949 | H12: ='DEC 24'!G12 -> 4947 | I12: =G12-H12 -> 2 | J12: =I12*12 -> 24 | K12: 300 | L12: ='DEC 24'!O12 -> 2736 | M12: =F12+J12+K12+L12 -> 5260 | N12: 2736 | O12: =M12-N12 -> 2524 | Q12: ALLOTED WEF SEP 21. ADV 10000. RENT 2000
A13: 8 | B13: AJAY BAG | C13: G/8 | D13: 37469 | E13: 500 | F13: 1800 | G13: 3338 | H13: ='DEC 24'!G13 -> 3330 | I13: =G13-H13 -> 8 | J13: =I13*12 -> 96 | K13: 300 | L13: ='DEC 24'!O13 -> 12162 | M13: =F13+J13+K13+L13 -> 14358 | N13: 0 | O13: =M13-N13 -> 14358 | Q13: ALLOTED WEF MAR 22. ADV 10000. RENT 1800
A14: 9 | B14: VACANT | C14: G/9 | D14: 37347 | E14: 500 | F14: 0 | G14: 12861 | H14: ='DEC 24'!G14 -> 12861 | I14: =G14-H14 -> 0 | J14: =I14*12 -> 0 | K14: 0 | L14: ='DEC 24'!O14 -> 0 | M14: =F14+J14+K14+L14 -> 0 | O14: =M14-N14 -> 0 | Q14: VACATED WEF OCT 24.
A15: 10 | B15: PRAMOD MANDAL | C15: G/10 | D15: 37165 | E15: 500 | F15: 2000 | G15: 3800 | H15: ='DEC 24'!G15 -> 3789 | I15: =G15-H15 -> 11 | J15: =I15*12 -> 132 | K15: 300 | L15: ='DEC 24'!O15 -> 0 | M15: =F15+J15+K15+L15 -> 2432 | N15: 2432 | O15: =M15-N15 -> 0 | Q15: ALLOTED WEF SEP 22. ADV 10000 RENT 2000
A16: 11 | B16: VACANT | C16: 1/1 | D16: 38443 | E16: 0 | F16: 0 | G16: 859 | H16: ='DEC 24'!G16 -> 859 | I16: =G16-H16 -> 0 | J16: =I16*12 -> 0 | K16: 0 | L16: ='DEC 24'!O16 -> 0 | M16: =F16+J16+K16+L16 -> 0 | N16: 0 | O16: =M16-N16 -> 0 | Q16: VACANT FROM DEC 24
A17: 12 | B17: RAKESH AGARWAL | C17: 1/2 | D17: 38292 | F17: 3100 | G17: 6844 | H17: ='DEC 24'!G17 -> 6842 | I17: =G17-H17 -> 2 | J17: =I17*12 -> 24 | K17: 400 | L17: ='DEC 24'!O17 -> 13472 | M17: =F17+J17+K17+L17 -> 16996 | N17: 0 | O17: =M17-N17 -> 16996 | Q17: ALLOTED WEF JUL 24. ADV 10K. RENT 3100
A18: 13 | B18: VACAMT | C18: 1/3 | D18: 38292 | E18: 500 | F18: 0 | G18: 5616 | H18: ='DEC 24'!G18 -> 5616 | I18: =G18-H18 -> 0 | J18: =I18*12 -> 0 | K18: 0 | L18: ='DEC 24'!O18 -> 0 | M18: =F18+J18+K18+L18 -> 0 | N18: 0 | O18: =M18-N18 -> 0 | Q18: VACANT FROM AUG 24
A19: 14 | B19: ANIL SHARMA | C19: 1/4 | D19: 38292 | E19: 500 | F19: 3000 | G19: 4039 | H19: ='DEC 24'!G19 -> 4032 | I19: =G19-H19 -> 7 | J19: =I19*12 -> 84 | K19: 400 | L19: ='DEC 24'!O19 -> -8 | M19: =F19+J19+K19+L19 -> 3476 | N19: 3480 | O19: =M19-N19 -> -4 | Q19: ADV 15K.19--5-24. RENT 3000
A20: 15 | B20: VACANT | C20: 1/5 | D20: 37469 | E20: 500 | F20: 0 | G20: 4244 | H20: ='DEC 24'!G20 -> 4244 | I20: =G20-H20 -> 0 | J20: =I20*12 -> 0 | K20: 0 | L20: ='DEC 24'!O20 -> 0 | M20: =F20+J20+K20+L20 -> 0 | N20: 0 | O20: =M20-N20 -> 0 | Q20: VACANT WEF NOV 2023
A21: 16 | B21: SHAILENDRA PANDEY | C21: 1/6 | D21: 37681 | E21: 500 | F21: 3000 | G21: 3416 | H21: ='DEC 24'!G21 -> 3381 | I21: =G21-H21 -> 35 | J21: =I21*12 -> 420 | K21: 400 | L21: ='DEC 24'!O21 -> 19186 | M21: =F21+J21+K21+L21 -> 23006 | N21: 0 | O21: =M21-N21 -> 23006 | Q21: RENT INCREASED WEF MAR 24 FROM 2300. ADV 10000
A22: 17 | B22: BIRENDAR YADAV | C22: 2/1 | D22: 38292 | E22: 500 | F22: 2800 | G22: 729 | H22: ='DEC 24'!G22 -> 712 | I22: =G22-H22 -> 17 | J22: =I22*12 -> 204 | K22: 400 | L22: ='DEC 24'!O22 -> 40620 | M22: =F22+J22+K22+L22 -> 44024 | N22: 0 | O22: =M22-N22 -> 44024 | Q22: RENT INCREASED WEF DEC 22 FROM 2200. ADV NIL
A23: 18 | B23: HARI SHANKER SHUKLA | C23: 2/2 | D23: 38292 | E23: 500 | F23: 3100 | G23: 976 | H23: ='DEC 24'!G23 -> 976 | I23: =G23-H23 -> 0 | J23: =I23*12 -> 0 | K23: 400 | L23: ='DEC 24'!O23 -> 17134 | M23: =F23+J23+K23+L23 -> 20634 | N23: 0 | O23: =M23-N23 -> 20634 | Q23: RENT INCRESED WEF JUL 24 FROM 2700. ADV 10000
A24: 19 | B24: SHIV SHANKER PANDEY | C24: 2/3 | D24: 37681 | E24: 500 | F24: 2800 | G24: 5441 | H24: ='DEC 24'!G24 -> 5432 | I24: =G24-H24 -> 9 | J24: =I24*12 -> 108 | K24: 400 | L24: ='DEC 24'!O24 -> 0 | M24: =F24+J24+K24+L24 -> 3308 | N24: 3310 | O24: =M24-N24 -> -2 | Q24: REALLOTED WEF DEC 22. RENT 2800. ADV NIL
A25: 20 | B25: PRAKASH PANDEY | C25: 2/4 | D25: 37681 | E25: 0 | F25: 2800 | G25: 986 | H25: ='DEC 24'!G25 -> 956 | I25: =G25-H25 -> 30 | J25: =I25*12 -> 360 | K25: 400 | L25: ='DEC 24'!O25 -> 5468 | M25: =F25+J25+K25+L25 -> 9028 | N25: 5000 | O25: =M25-N25 -> 4028 | Q25: ALLOTED FROM DEC 23. ADV NIL. RENT 2800
A26: 21 | B26: PAPPU | C26: 2/5 | D26: 37681 | E26: 500 | F26: 3000 | G26: 3257 | H26: ='DEC 24'!G26 -> 3254 | I26: =G26-H26 -> 3 | J26: =I26*12 -> 36 | K26: 400 | L26: ='DEC 24'!O26 -> 0 | M26: =F26+J26+K26+L26 -> 3436 | N26: 3500 | O26: =M26-N26 -> -64 | Q26: ALLOTED WEF DEC 24. ADV 10K, RENT 3100
A27: 22 | B27: VACANT | C27: 2/6 | D27: 37681 | E27: 0 | F27: 0 | G27: 5070 | H27: ='DEC 24'!G27 -> 5051 | I27: =G27-H27 -> 19 | J27: =I27*12 -> 228 | K27: 0 | L27: ='DEC 24'!O27 -> 0 | M27: =F27+J27+K27+L27 -> 228 | N27: 228 | O27: =M27-N27 -> 0 | Q27: VACATED WEF OCT 24.
C28: TOTAL | E28: =SUM(E6:E27) -> 7000 | F28: =SUM(F6:F27) -> 38000 | I28: =SUM(I6:I27) -> 178 | J28: =SUM(J6:J27) -> 2136 | K28: =SUM(K6:K27) -> 5300 | L28: =SUM(L6:L27) -> 170270 | M28: =SUM(M6:M27) -> 215706 | N28: =SUM(N6:N27) -> 28686 | O28: =SUM(O6:O27) -> 187020

Sheet NOV 24
A1: SITA DEVI PANDEY HOUSING PROJECT
A2: 11/1B/1 GANPAT RAI KHEMKA LANE LILUAH HOWRAH(W. B.) 711204
A3: FOR THE MONTH OF - NOV 2024 | U3: 44
A4: SNO | B4: NAME | C4: ROOM | D4: DATE OF | E4: ELECTRIC | F4: MTLY | G4: ELECTRIC | K4: MISC | L4: B/F & | M4: TOTAL | N4: AMT | O4: B/F OR | P4: PAYMENT | Q4: REMARKS
C5: NO | D5: ALLOTMENT | E5: SECURITY | F5: RENT | G5: NEW | H5: PRE | I5: TOTAL | J5: COST | K5: RENT | L5: ADV | M5: AMT DUE | N5: PAID | O5: ADV | P5: DATE
A6: 1 | B6: SUNNY PRAJAPATI | C6: G/1 | D6: 38754 | E6: 0 | F6: 2200 | G6: 1402 | H6: ='OCT 24'!G6 -> 1382 | I6: =G6-H6 -> 20 | J6: =I6*12 -> 240 | K6: 300 | L6: ='OCT 24'!O6 -> 4664 | M6: =F6+J6+K6+L6 -> 7404 | N6: 0 | O6: =M6-N6 -> 7404 | Q6: ALLOTED WEF SEP 21. ADV 10000. RENT 2000
A7: 2 | B7: VACANT | C7: G/2 | D7: 37653 | E7: 0 | F7: 0 | G7: 655 | H7: ='OCT 24'!G7 -> 655 | I7: =G7-H7 -> 0 | J7: =I7*12 -> 0 | K7: 0 | L7: ='OCT 24'!O7 -> 0 | M7: 0 | N7: 0 | O7: =M7-N7 -> 0 | Q7: VACANT FM SEP 24
A8: 3 | B8: PANKAJ PATEL | C8: G/3 | D8: 37895 | E8: 0 | F8: 2200 | G8: 4444 | H8: ='OCT 24'!G8 -> 4441 | I8: =G8-H8 -> 3 | J8: =I8*12 -> 36 | K8: 300 | L8: ='OCT 24'!O8 -> 15966 | M8: =F8+J8+K8+L8 -> 18502 | N8: 0 | O8: =M8-N8 -> 18502 | Q8: ALLOTED WEF JUL 21. ADV 5K, RENT 2200 FM JUL 24.
A9: 4 | B9: BADRI MANDAL | C9: G/4 | D9: 38292 | E9: 500 | F9: 2000 | G9: 4476 | H9: ='OCT 24'!G9 -> 4452 | I9: =G9-H9 -> 24 | J9: =I9*12 -> 288 | K9: 300 | L9: ='OCT 24'!O9 -> 12450 | M9: =F9+J9+K9+L9 -> 15038 | N9: 5000 | O9: =M9-N9 -> 10038 | Q9: ALLOTED WEF 01 DEC 2022. RENT 2000. ADV 5000
A10: 5 | B10: VACANT | C10: G/5 | F10: 0 | G10: 4279 | H10: ='OCT 24'!G10 -> 4279 | I10: =G10-H10 -> 0 | J10: =I10*12 -> 0 | K10: 0 | L10: ='OCT 24'!O10 -> 0 | M10: =F10+J10+K10+L10 -> 0 | N10: 0 | O10: =M10-N10 -> 0 | Q10: VACANT FROM JUL 24
A11: 6 | B11: VIVEK MANDAL | C11: G/6 | D11: 37667 | E11: 500 | F11: 2000 | G11: 2005 | H11: ='OCT 24'!G11 -> 1967 | I11: =G11-H11 -> 38 | J11: =I11*12 -> 456 | K11: 300 | L11: ='OCT 24'!O11 -> 13936 | M11: =F11+J11+K11+L11 -> 16692 | N11: 0 | O11: =M11-N11 -> 16692 | Q11: ALLOTED WEF JUN 24. ADV 4000, RENT 2000
A12: 7 | B12: RAM P SHRESTHA | C12: G/7 | D12: 37773 | E12: 500 | F12: 2200 | G12: 4944 | H12: ='OCT 24'!G12 -> 4940 | I12: =G12-H12 -> 4 | J12: =I12*12 -> 48 | K12: 300 | L12: ='OCT 24'!O12 -> 0 | M12: =F12+J12+K12+L12 -> 2548 | N12: 2348 | O12: =M12-N12 -> 200 | Q12: ALLOTED WEF SEP 21. ADV 10000. RENT 2000
A13: 8 | B13: AJAY BAG | C13: G/8 | D13: 37469 | E13: 500 | F13: 1800 | G13: 3325 | H13: ='OCT 24'!G13 -> 3289 | I13: =G13-H13 -> 36 | J13: =I13*12 -> 432 | K13: 300 | L13: ='OCT 24'!O13 -> 7470 | M13: =F13+J13+K13+L13 -> 10002 | N13: 0 | O13: =M13-N13 -> 10002 | Q13: ALLOTED WEF MAR 22. ADV 10000. RENT 1800
A14: 9 | B14: VACANT | C14: G/9 | D14: 37347 | E14: 500 | F14: 0 | G14: 12861 | H14: ='OCT 24'!G14 -> 12861 | I14: =G14-H14 -> 0 | J14: =I14*12 -> 0 | K14: 0 | L14: ='OCT 24'!O14 -> 0 | M14: =F14+J14+K14+L14 -> 0 | N14: 0 | O14: =M14-N14 -> 0 | Q14: VACATED WEF OCT 24.
A15: 10 | B15: PRAMOD MANDAL | C15: G/10 | D15: 37165 | E15: 500 | F15: 2000 | G15: 3778 | H15: ='OCT 24'!G15 -> 3741 | I15: =G15-H15 -> 37 | J15: =I15*12 -> 444 | K15: 300 | L15: ='OCT 24'!O15 -> 0 | M15: =F15+J15+K15+L15 -> 2744 | N15: 2744 | O15: =M15-N15 -> 0 | Q15: ALLOTED WEF SEP 22. ADV 10000 RENT 2000
A16: 11 | B16: NEW | C16: 1/1 | D16: 38443 | E16: 0 | F16: 2400 | G16: 856 | H16: ='OCT 24'!G16 -> 853 | I16: =G16-H16 -> 3 | J16: =I16*12 -> 36 | K16: 400 | L16: ='OCT 24'!O16 -> 1156 | M16: =F16+J16+K16+L16 -> 3992 | N16: 3980 | O16: =M16-N16 -> 12 | Q16: ALLOTED WEF 23 OCT 24. ADV 5K. RENT 2400.
A17: 12 | B17: RAKESH AGARWAL | C17: 1/2 | D17: 38292 | F17: 3100 | G17: 6835 | H17: ='OCT 24'!G17 -> 6813 | I17: =G17-H17 -> 22 | J17: =I17*12 -> 264 | K17: 400 | L17: ='OCT 24'!O17 -> 6124 | M17: =F17+J17+K17+L17 -> 9888 | N17: 0 | O17: =M17-N17 -> 9888 | Q17: ALLOTED WEF JUL 24. ADV 10K. RENT 3100
A18: 13 | B18: VACAMT | C18: 1/3 | D18: 38292 | E18: 500 | F18: 0 | G18: 5616 | H18: ='OCT 24'!G18 -> 5616 | I18: =G18-H18 -> 0 | J18: =I18*12 -> 0 | K18: 0 | L18: ='OCT 24'!O18 -> 0 | M18: =F18+J18+K18+L18 -> 0 | N18: 0 | O18: =M18-N18 -> 0 | Q18: VACANT FROM AUG 24
A19: 14 | B19: ANIL SHARMA | C19: 1/4 | D19: 38292 | E19: 500 | F19: 3000 | G19: 4026 | H19: ='OCT 24'!G19 -> 3998 | I19: =G19-H19 -> 28 | J19: =I19*12 -> 336 | K19: 400 | L19: ='OCT 24'!O19 -> 0 | M19: =F19+J19+K19+L19 -> 3736 | N19: 3736 | O19: =M19-N19 -> 0 | Q19: ADV 15K.19--5-24. RENT 3000
A20: 15 | B20: VACANT | C20: 1/5 | D20: 37469 | E20: 500 | F20: 0 | G20: 4244 | H20: ='OCT 24'!G20 -> 4244 | I20: =G20-H20 -> 0 | J20: =I20*12 -> 0 | K20: 0 | L20: ='OCT 24'!O20 -> 0 | M20: =F20+J20+K20+L20 -> 0 | N20: 0 | O20: =M20-N20 -> 0 | Q20: VACANT WEF NOV 2023
A21: 16 | B21: SHAILENDRA PANDEY | C21: 1/6 | D21: 37681 | E21: 500 | F21: 3000 | G21: 3368 | H21: ='OCT 24'!G21 -> 3333 | I21: =G21-H21 -> 35 | J21: =I21*12 -> 420 | K21: 400 | L21: ='OCT 24'!O21 -> 21810 | M21: =F21+J21+K21+L21 -> 25630 | N21: 5000 | O21: =M21-N21 -> 20630 | Q21: RENT INCREASED WEF MAR 24 FROM 2300. ADV 10000
A22: 17 | B22: BIRENDAR YADAV | C22: 2/1 | D22: 38292 | E22: 500 | F22: 2800 | G22: 702 | H22: ='OCT 24'!G22 -> 676 | I22: =G22-H22 -> 26 | J22: =I22*12 -> 312 | K22: 400 | L22: ='OCT 24'!O22 -> 40788 | M22: =F22+J22+K22+L22 -> 44300 | N22: 0 | O22: =M22-N22 -> 44300 | Q22: RENT INCREASED WEF DEC 22 FROM 2200. ADV NIL
A23: 18 | B23: HARI SHANKER SHUKLA | C23: 2/2 | D23: 38292 | E23: 500 | F23: 3100 | G23: 976 | H23: ='OCT 24'!G23 -> 976 | I23: =G23-H23 -> 0 | J23: =I23*12 -> 0 | K23: 400 | L23: ='OCT 24'!O23 -> 10134 | M23: =F23+J23+K23+L23 -> 13634 | N23: 0 | O23: =M23-N23 -> 13634 | Q23: RENT INCRESED WEF JUL 24 FROM 2700. ADV 10000
A24: 19 | B24: SHIV SHANKER PANDEY | C24: 2/3 | D24: 37681 | E24: 500 | F24: 2800 | G24: 5424 | H24: ='OCT 24'!G24 -> 5409 | I24: =G24-H24 -> 15 | J24: =I24*12 -> 180 | K24: 400 | L24: ='OCT 24'!O24 -> -40 | M24: =F24+J24+K24+L24 -> 3340 | N24: 3340 | O24: =M24-N24 -> 0 | Q24: REALLOTED WEF DEC 22. RENT 2800. ADV NIL
A25: 20 | B25: PRAKASH PANDEY | C25: 2/4 | D25: 37681 | E25: 0 | F25: 2800 | G25: 940 | H25: ='OCT 24'!G25 -> 899 | I25: =G25-H25 -> 41 | J25: =I25*12 -> 492 | K25: 400 | L25: ='OCT 24'!O25 -> 11384 | M25: =F25+J25+K25+L25 -> 15076 | N25: 8000 | O25: =M25-N25 -> 7076 | Q25: ALLOTED FROM DEC 23. ADV NIL. RENT 2800
A26: 21 | B26: VACANT | C26: 2/5 | D26: 37681 | E26: 500 | F26: 0 | G26: 3254 | H26: ='OCT 24'!G26 -> 3254 | I26: =G26-H26 -> 0 | J26: =I26*12 -> 0 | K26: 0 | L26: ='OCT 24'!O26 -> 0 | M26: =F26+J26+K26+L26 -> 0 | N26: 0 | O26: =M26-N26 -> 0 | Q26: VACATED WEF NOV 23.
A27: 22 | B27: VACANT | C27: 2/6 | D27: 37681 | E27: 0 | F27: 0 | G27: 5051 | H27: ='OCT 24'!G27 -> 5051 | I27: =G27-H27 -> 0 | J27: =I27*12 -> 0 | K27: 0 | L27: 0 | M27: =F27+J27+K27+L27 -> 0 | N27: 0 | O27: =M27-N27 -> 0 | Q27: VACATED WEF OCT 24.
C28: TOTAL | E28: =SUM(E6:E27) -> 7000 | F28: =SUM(F6:F27) -> 37400 | I28: =SUM(I6:I27) -> 332 | J28: =SUM(J6:J27) -> 3984 | K28: =SUM(K6:K27) -> 5300 | L28: =SUM(L6:L27) -> 145842 | M28: =SUM(M6:M27) -> 192526 | N28: =SUM(N6:N27) -> 34148 | O28: =SUM(O6:O27) -> 158378

Sheet OCT 24
A1: SITA DEVI PANDEY HOUSING PROJECT
A2: 11/1B/1 GANPAT RAI KHEMKA LANE LILUAH HOWRAH(W. B.) 711204
A3: FOR THE MONTH OF - OCT 2024 | U3: 44
A4: SNO | B4: NAME | C4: ROOM | D4: DATE OF | E4: ELECTRIC | F4: MTLY | G4: ELECTRIC | K4: MISC | L4: B/F & | M4: TOTAL | N4: AMT | O4: B/F OR | P4: PAYMENT | Q4: REMARKS
C5: NO | D5: ALLOTMENT | E5: SECURITY | F5: RENT | G5: NEW | H5: PRE | I5: TOTAL | J5: COST | K5: RENT | L5: ADV | M5: AMT DUE | N5: PAID | O5: ADV | P5: DATE
A6: 1 | B6: SUNNY PRAJAPATI | C6: G/1 | D6: 38754 | E6: 0 | F6: 2200 | G6: 1382 | H6: ='SEP 24'!G6 -> 1345 | I6: =G6-H6 -> 37 | J6: =I6*12 -> 444 | K6: 300 | L6: ='SEP 24'!O6 -> 17720 | M6: =F6+J6+K6+L6 -> 20664 | N6: 16000 | O6: =M6-N6 -> 4664 | Q6: ALLOTED WEF SEP 21. ADV 10000. RENT 2000
A7: 2 | B7: VACANT | C7: G/2 | D7: 37653 | E7: 0 | F7: 2000 | G7: 655 | H7: 655 | I7: =G7-H7 -> 0 | J7: =I7*12 -> 0 | K7: 0 | L7: ='SEP 24'!O7 -> 0 | M7: 0 | N7: 0 | O7: =M7-N7 -> 0 | Q7: ALLLTED WEF SEP 23. ADV 5K RENT 2000. VACANT FM SEP 24
A8: 3 | B8: PANKAJ PATEL | C8: G/3 | D8: 37895 | E8: 0 | F8: 2200 | G8: 4441 | H8: ='SEP 24'!G8 -> 4417 | I8: =G8-H8 -> 24 | J8: =I8*12 -> 288 | K8: 300 | L8: ='SEP 24'!O8 -> 18178 | M8: =F8+J8+K8+L8 -> 20966 | N8: 5000 | O8: =M8-N8 -> 15966 | Q8: ALLOTED WEF JUL 21. ADV 5K, RENT 2200 FM JUL 24.
A9: 4 | B9: BADRI MANDAL | C9: G/4 | D9: 38292 | E9: 500 | F9: 2000 | G9: 4452 | H9: ='SEP 24'!G9 -> 4417 | I9: =G9-H9 -> 35 | J9: =I9*12 -> 420 | K9: 300 | L9: ='SEP 24'!O9 -> 9730 | M9: =F9+J9+K9+L9 -> 12450 | N9: 0 | O9: =M9-N9 -> 12450 | Q9: ALLOTED WEF 01 DEC 2022. RENT 2000. ADV 5000
A10: 5 | B10: VACANT | C10: G/5 | F10: 0 | G10: 4279 | H10: ='SEP 24'!G10 -> 4279 | I10: =G10-H10 -> 0 | J10: =I10*12 -> 0 | K10: 0 | L10: ='SEP 24'!O10 -> 0 | M10: =F10+J10+K10+L10 -> 0 | N10: 0 | O10: =M10-N10 -> 0 | Q10: VACANT FROM JUL 24
A11: 6 | B11: VIVEK MANDAL | C11: G/6 | D11: 37667 | E11: 500 | F11: 2000 | G11: 1967 | H11: ='SEP 24'!G11 -> 1919 | I11: =G11-H11 -> 48 | J11: =I11*12 -> 576 | K11: 300 | L11: ='SEP 24'!O11 -> 11060 | M11: =F11+J11+K11+L11 -> 13936 | N11: 0 | O11: =M11-N11 -> 13936 | Q11: ALLOTED WEF JUN 24. ADV 4000, RENT 2000
A12: 7 | B12: RAM P SHRESTHA | C12: G/7 | D12: 37773 | E12: 500 | F12: 2000 | G12: 4940 | H12: ='SEP 24'!G12 -> 4935 | I12: =G12-H12 -> 5 | J12: =I12*12 -> 60 | K12: 300 | L12: ='SEP 24'!O12 -> 2672 | M12: =F12+J12+K12+L12 -> 5032 | N12: 5032 | O12: =M12-N12 -> 0 | Q12: ALLOTED WEF SEP 21. ADV 10000. RENT 2000
A13: 8 | B13: AJAY BAG | C13: G/8 | D13: 37469 | E13: 500 | F13: 1800 | G13: 3289 | H13: ='SEP 24'!G13 -> 3232 | I13: =G13-H13 -> 57 | J13: =I13*12 -> 684 | K13: 300 | L13: ='SEP 24'!O13 -> 19686 | M13: =F13+J13+K13+L13 -> 22470 | N13: 15000 | O13: =M13-N13 -> 7470 | Q13: ALLOTED WEF MAR 22. ADV 10000. RENT 1800
A14: 9 | B14: PRAMOD MANDAL | C14: G/9 | D14: 37347 | E14: 500 | F14: 2100 | G14: 12861 | H14: ='SEP 24'!G14 -> 12861 | I14: =G14-H14 -> 0 | J14: =I14*12 -> 0 | K14: 300 | L14: ='SEP 24'!O14 -> 3240 | M14: =F14+J14+K14+L14 -> 5640 | N14: 5640 | O14: =M14-N14 -> 0 | Q14: VACATED WEF OCT 24. 4360 RETURNED.
A15: 10 | B15: PRAMOD MANDAL | C15: G/10 | D15: 37165 | E15: 500 | F15: 2000 | G15: 3741 | H15: ='SEP 24'!G15 -> 3673 | I15: =G15-H15 -> 68 | J15: =I15*12 -> 816 | K15: 300 | L15: ='SEP 24'!O15 -> 0 | M15: =F15+J15+K15+L15 -> 3116 | N15: 3116 | O15: =M15-N15 -> 0 | Q15: ALLOTED WEF SEP 22. ADV 10000 RENT 2000
A16: 11 | B16: NEW | C16: 1/1 | D16: 38443 | E16: 0 | F16: 1000 | G16: 853 | H16: ='SEP 24'!G16 -> 840 | I16: =G16-H16 -> 13 | J16: =I16*12 -> 156 | K16: 0 | L16: ='SEP 24'!O16 -> 0 | M16: =F16+J16+K16+L16 -> 1156 | N16: 0 | O16: =M16-N16 -> 1156 | Q16: ALLOTED WEF 23 OCT 24. ADV 5K. RENT 2400.
A17: 12 | B17: RAKESH AGARWAL | C17: 1/2 | D17: 38292 | F17: 3100 | G17: 6813 | H17: ='SEP 24'!G17 -> 6775 | I17: =G17-H17 -> 38 | J17: =I17*12 -> 456 | K17: 400 | L17: ='SEP 24'!O17 -> 2168 | M17: =F17+J17+K17+L17 -> 6124 | N17: 0 | O17: =M17-N17 -> 6124 | Q17: ALLOTED WEF JUL 24. ADV 10K. RENT 3100
A18: 13 | B18: VACAMT | C18: 1/3 | D18: 38292 | E18: 500 | F18: 0 | G18: 5616 | H18: ='SEP 24'!G18 -> 5616 | I18: =G18-H18 -> 0 | J18: =I18*12 -> 0 | K18: 0 | L18: ='SEP 24'!O18 -> 0 | M18: =F18+J18+K18+L18 -> 0 | N18: 0 | O18: =M18-N18 -> 0 | Q18: VACANT FROM AUT 24
A19: 14 | B19: ANIL SHARMA | C19: 1/4 | D19: 38292 | E19: 500 | F19: 3000 | G19: 3998 | H19: ='SEP 24'!G19 -> 3952 | I19: =G19-H19 -> 46 | J19: =I19*12 -> 552 | K19: 400 | L19: ='SEP 24'!O19 -> 0 | M19: =F19+J19+K19+L19 -> 3952 | N19: 3952 | O19: =M19-N19 -> 0 | Q19: ADV 15K.19--5-24. RENT 3000
A20: 15 | B20: VACANT | C20: 1/5 | D20: 37469 | E20: 500 | F20: 0 | G20: 4244 | H20: ='SEP 24'!G20 -> 4244 | I20: =G20-H20 -> 0 | J20: =I20*12 -> 0 | K20: 0 | L20: ='SEP 24'!O20 -> 0 | M20: =F20+J20+K20+L20 -> 0 | N20: 0 | O20: =M20-N20 -> 0 | Q20: VACANT WEF NOV 2023
A21: 16 | B21: SHAILENDRA PANDEY | C21: 1/6 | D21: 37681 | E21: 500 | F21: 3000 | G21: 3333 | H21: ='SEP 24'!G21 -> 3272 | I21: =G21-H21 -> 61 | J21: =I21*12 -> 732 | K21: 400 | L21: ='SEP 24'!O21 -> 22678 | M21: =F21+J21+K21+L21 -> 26810 | N21: 5000 | O21: =M21-N21 -> 21810 | Q21: RENT INCREASED WEF MAR 24 FROM 2300. ADV 10000
A22: 17 | B22: BIRENDAR YADAV | C22: 2/1 | D22: 38292 | E22: 500 | F22: 2800 | G22: 676 | H22: ='SEP 24'!G22 -> 641 | I22: =G22-H22 -> 35 | J22: =I22*12 -> 420 | K22: 400 | L22: ='SEP 24'!O22 -> 42168 | M22: =F22+J22+K22+L22 -> 45788 | N22: 5000 | O22: =M22-N22 -> 40788 | Q22: RENT INCREASED WEF DEC 22 FROM 2200. ADV NIL
A23: 18 | B23: HARI SHANKER SHUKLA | C23: 2/2 | D23: 38292 | E23: 500 | F23: 3100 | G23: 976 | H23: ='SEP 24'!G23 -> 924 | I23: =G23-H23 -> 52 | J23: =I23*12 -> 624 | K23: 400 | L23: ='SEP 24'!O23 -> 6010 | M23: =F23+J23+K23+L23 -> 10134 | N23: 0 | O23: =M23-N23 -> 10134 | Q23: RENT INCRESED WEF JUL 24 FROM 2700. ADV 10000
A24: 19 | B24: SHIV SHANKER PANDEY | C24: 2/3 | D24: 37681 | E24: 500 | F24: 2800 | G24: 5409 | H24: ='SEP 24'!G24 -> 5382 | I24: =G24-H24 -> 27 | J24: =I24*12 -> 324 | K24: 400 | L24: ='SEP 24'!O24 -> -48 | M24: =F24+J24+K24+L24 -> 3476 | N24: 3516 | O24: =M24-N24 -> -40 | Q24: REALLOTED WEF DEC 22. RENT 2800. ADV NIL
A25: 20 | B25: PRAKASH PANDEY | C25: 2/4 | D25: 37681 | E25: 0 | F25: 2800 | G25: 899 | H25: ='SEP 24'!G25 -> 834 | I25: =G25-H25 -> 65 | J25: =I25*12 -> 780 | K25: 400 | L25: ='SEP 24'!O25 -> 7404 | M25: =F25+J25+K25+L25 -> 11384 | N25: 0 | O25: =M25-N25 -> 11384 | Q25: ALLOTED FROM DEC 23. ADV NIL. RENT 2800
A26: 21 | B26: VACANT | C26: 2/5 | D26: 37681 | E26: 500 | F26: 0 | G26: 3254 | H26: ='SEP 24'!G26 -> 3254 | I26: =G26-H26 -> 0 | J26: =I26*12 -> 0 | K26: 0 | L26: ='SEP 24'!O26 -> 0 | M26: =F26+J26+K26+L26 -> 0 | N26: 0 | O26: =M26-N26 -> 0 | Q26: VACATED WEF NOV 23.
A27: 22 | B27: SUNIL MONDAL | C27: 2/6 | D27: 37681 | E27: 0 | F27: 3600 | G27: 5051 | H27: ='SEP 24'!G27 -> 4977 | I27: =G27-H27 -> 74 | J27: =I27*12 -> 888 | K27: 400 | L27: ='SEP 24'!O27 -> 57662 | M27: =F27+J27+K27+L27 -> 62550 | N27: 0 | O27: =M27-N27 -> 62550 | Q27: VACATED WEF OCT 24. ADV 10K. DUE 62550
C28: TOTAL | E28: =SUM(E6:E27) -> 7000 | F28: =SUM(F6:F27) -> 43500 | I28: =SUM(I6:I27) -> 685 | J28: =SUM(J6:J27) -> 8220 | K28: =SUM(K6:K27) -> 5600 | L28: =SUM(L6:L27) -> 220328 | M28: =SUM(M6:M27) -> 275648 | N28: =SUM(N6:N27) -> 67256 | O28: =SUM(O6:O27) -> 208392

Sheet SEP 24
A1: SITA DEVI PANDEY HOUSING PROJECT
A2: 11/1B/1 GANPAT RAI KHEMKA LANE LILUAH HOWRAH(W. B.) 711204
A3: FOR THE MONTH OF - SEP 2024 | U3: 44
A4: SNO | B4: NAME | C4: ROOM | D4: DATE OF | E4: ELECTRIC | F4: MTLY | G4: ELECTRIC | K4: MISC | L4: B/F & | M4: TOTAL | N4: AMT | O4: B/F OR | P4: PAYMENT | Q4: REMARKS
C5: NO | D5: ALLOTMENT | E5: SECURITY | F5: RENT | G5: NEW | H5: PRE | I5: TOTAL | J5: COST | K5: RENT | L5: ADV | M5: AMT DUE | N5: PAID | O5: ADV | P5: DATE
A6: 1 | B6: SUNNY PRAJAPATI | C6: G/1 | D6: 38754 | E6: 0 | F6: 2200 | G6: 1345 | H6: ='AUG 24'!G6 -> 1291 | I6: =G6-H6 -> 54 | J6: =I6*12 -> 648 | K6: 300 | L6: ='AUG 24'!O6 -> 14572 | M6: =F6+J6+K6+L6 -> 17720 | N6: 0 | O6: =M6-N6 -> 17720 | Q6: RENT INCREASED WEF SEP 24. FM 2000. ADV 10000.
A7: 2 | B7: VACANT | C7: G/2 | D7: 37653 | E7: 0 | F7: 2000 | G7: 656 | H7: 656 | I7: =G7-H7 -> 0 | J7: =I7*12 -> 0 | K7: 0 | L7: ='AUG 24'!O7 -> 0 | M7: 0 | N7: 0 | O7: =M7-N7 -> 0 | Q7: ALLLTED WEF SEP 23. ADV 5K RENT 2000. VACANT FM SEP 24
A8: 3 | B8: PANKAJ PATEL | C8: G/3 | D8: 37895 | E8: 0 | F8: 2200 | G8: 4417 | H8: ='AUG 24'!G8 -> 4391 | I8: =G8-H8 -> 26 | J8: =I8*12 -> 312 | K8: 300 | L8: ='AUG 24'!O8 -> 15366 | M8: =F8+J8+K8+L8 -> 18178 | N8: 0 | O8: =M8-N8 -> 18178 | Q8: ALLOTED WEF JUL 21. ADV 5K, RENT 2200 FM JUL 24.
A9: 4 | B9: BADRI MANDAL | C9: G/4 | D9: 38292 | E9: 500 | F9: 2000 | G9: 4417 | H9: ='AUG 24'!G9 -> 4359 | I9: =G9-H9 -> 58 | J9: =I9*12 -> 696 | K9: 300 | L9: ='AUG 24'!O9 -> 10734 | M9: =F9+J9+K9+L9 -> 13730 | N9: 4000 | O9: =M9-N9 -> 9730 | Q9: ALLOTED WEF 01 DEC 2022. RENT 2000. ADV 5000
A10: 5 | B10: VACANT | C10: G/5 | F10: 0 | G10: 4279 | H10: 4279 | I10: =G10-H10 -> 0 | J10: =I10*12 -> 0 | K10: 0 | L10: ='AUG 24'!O10 -> 0 | M10: =F10+J10+K10+L10 -> 0 | N10: 0 | O10: =M10-N10 -> 0 | Q10: VACANT FROM JUL 24
A11: 6 | B11: VIVEK MANDAL | C11: G/6 | D11: 37667 | E11: 500 | F11: 2000 | G11: 1919 | H11: ='AUG 24'!G11 -> 1861 | I11: =G11-H11 -> 58 | J11: =I11*12 -> 696 | K11: 300 | L11: ='AUG 24'!O11 -> 8064 | M11: =F11+J11+K11+L11 -> 11060 | N11: 0 | O11: =M11-N11 -> 11060 | Q11: ALLOTED WEF JUN 24. ADV 4000, RENT 2000
A12: 7 | B12: RAM P SHRESTHA | C12: G/7 | D12: 37773 | E12: 500 | F12: 2000 | G12: 4935 | H12: ='AUG 24'!G12 -> 4904 | I12: =G12-H12 -> 31 | J12: =I12*12 -> 372 | K12: 300 | L12: ='AUG 24'!O12 -> 0 | M12: =F12+J12+K12+L12 -> 2672 | N12: 0 | O12: =M12-N12 -> 2672 | Q12: ALLOTED WEF SEP 21. ADV 10000. RENT 2000
A13: 8 | B13: AJAY BAG | C13: G/8 | D13: 37469 | E13: 500 | F13: 1800 | G13: 3232 | H13: ='AUG 24'!G13 -> 3130 | I13: =G13-H13 -> 102 | J13: =I13*12 -> 1224 | K13: 300 | L13: ='AUG 24'!O13 -> 16362 | M13: =F13+J13+K13+L13 -> 19686 | N13: 0 | O13: =M13-N13 -> 19686 | Q13: ALLOTED WEF MAR 22. ADV 10000. RENT 1800
A14: 9 | B14: PRAMOD MANDAL | C14: G/9 | D14: 37347 | E14: 500 | F14: 2100 | G14: 12861 | H14: ='AUG 24'!G14 -> 12791 | I14: =G14-H14 -> 70 | J14: =I14*12 -> 840 | K14: 300 | L14: ='AUG 24'!O14 -> 0 | M14: =F14+J14+K14+L14 -> 3240 | N14: 0 | O14: =M14-N14 -> 3240 | Q14: ALLOTED WEF SEP 22. ADV 10000 RENT 2100 SHIFTJUL 23
A15: 10 | B15: PRAMOD MANDAL | C15: G/10 | D15: 37165 | E15: 500 | F15: 2000 | G15: 3673 | H15: ='AUG 24'!G15 -> 3575 | I15: =G15-H15 -> 98 | J15: =I15*12 -> 1176 | K15: 300 | L15: ='AUG 24'!O15 -> 0 | M15: =F15+J15+K15+L15 -> 3476 | N15: 3476 | O15: =M15-N15 -> 0 | Q15: ALLOTED WEF SEP 22. ADV 10000 RENT 2000
A16: 11 | B16: RAKESH AGARWAL | C16: 1/1 | D16: 38443 | E16: 0 | F16: 2100 | G16: 840 | H16: ='AUG 24'!G16 -> 839 | I16: =G16-H16 -> 1 | J16: =I16*12 -> 12 | K16: 400 | L16: ='AUG 24'!O16 -> 5156 | M16: =F16+J16+K16+L16 -> 7668 | N16: 7668 | O16: =M16-N16 -> 0 | Q16: VACATED WEF SEP 24, 332 RETURNED
A17: 12 | B17: RAKESH AGARWAL | C17: 1/2 | D17: 38292 | F17: 3100 | G17: 6775 | H17: ='AUG 24'!G17 -> 6713 | I17: =G17-H17 -> 62 | J17: =I17*12 -> 744 | K17: 400 | L17: ='AUG 24'!O17 -> -2076 | M17: =F17+J17+K17+L17 -> 2168 | N17: 0 | O17: =M17-N17 -> 2168 | Q17: ALLOTED WEF JUL 24. ADV 10K. RENT 3100
A18: 13 | B18: VACAMT | C18: 1/3 | D18: 38292 | E18: 500 | F18: 0 | G18: 5616 | H18: ='AUG 24'!G18 -> 5616 | I18: =G18-H18 -> 0 | J18: =I18*12 -> 0 | K18: 0 | L18: ='AUG 24'!O18 -> 0 | M18: =F18+J18+K18+L18 -> 0 | N18: 0 | O18: =M18-N18 -> 0 | Q18: VACANT FROM AUT 24
A19: 14 | B19: ANIL SHARMA | C19: 1/4 | D19: 38292 | E19: 500 | F19: 3000 | G19: 3952 | H19: ='AUG 24'!G19 -> 3894 | I19: =G19-H19 -> 58 | J19: =I19*12 -> 696 | K19: 400 | L19: ='AUG 24'!O19 -> -12 | M19: =F19+J19+K19+L19 -> 4084 | N19: 4084 | O19: =M19-N19 -> 0 | Q19: ADV 15K.19--5-24. RENT 3000
A20: 15 | B20: VACANT | C20: 1/5 | D20: 37469 | E20: 500 | F20: 0 | G20: 4244 | H20: ='AUG 24'!G20 -> 4244 | I20: =G20-H20 -> 0 | J20: =I20*12 -> 0 | K20: 0 | L20: ='AUG 24'!O20 -> 0 | M20: =F20+J20+K20+L20 -> 0 | N20: 0 | O20: =M20-N20 -> 0 | Q20: VACANT WEF NOV 2023
A21: 16 | B21: SHAILENDRA PANDEY | C21: 1/6 | D21: 37681 | E21: 500 | F21: 3000 | G21: 3272 | H21: ='AUG 24'!G21 -> 3206 | I21: =G21-H21 -> 66 | J21: =I21*12 -> 792 | K21: 400 | L21: ='AUG 24'!O21 -> 38486 | M21: =F21+J21+K21+L21 -> 42678 | N21: 20000 | O21: =M21-N21 -> 22678 | Q21: RENT INCREASED WEF MAR 24 FROM 2300. ADV 10000
A22: 17 | B22: BIRENDAR YADAV | C22: 2/1 | D22: 38292 | E22: 500 | F22: 2800 | G22: 641 | H22: ='AUG 24'!G22 -> 593 | I22: =G22-H22 -> 48 | J22: =I22*12 -> 576 | K22: 400 | L22: ='AUG 24'!O22 -> 38392 | M22: =F22+J22+K22+L22 -> 42168 | N22: 0 | O22: =M22-N22 -> 42168 | Q22: RENT INCREASED WEF DEC 22 FROM 2200. ADV NIL
A23: 18 | B23: HARI SHANKER SHUKLA | C23: 2/2 | D23: 38292 | E23: 500 | F23: 3100 | G23: 924 | H23: ='AUG 24'!G23 -> 919 | I23: =G23-H23 -> 5 | J23: =I23*12 -> 60 | K23: 400 | L23: ='AUG 24'!O23 -> 12450 | M23: =F23+J23+K23+L23 -> 16010 | N23: 10000 | O23: =M23-N23 -> 6010 | Q23: RENT INCRESED WEF JUL 24 FROM 2700. ADV 10000
A24: 19 | B24: SHIV SHANKER PANDEY | C24: 2/3 | D24: 37681 | E24: 500 | F24: 2800 | G24: 5382 | H24: ='AUG 24'!G24 -> 5366 | I24: =G24-H24 -> 16 | J24: =I24*12 -> 192 | K24: 400 | L24: ='AUG 24'!O24 -> 3560 | M24: =F24+J24+K24+L24 -> 6952 | N24: 7000 | O24: =M24-N24 -> -48 | Q24: REALLOTED WEF DEC 22. RENT 2800. ADV NIL
A25: 20 | B25: PRAKASH PANDEY | C25: 2/4 | D25: 37681 | E25: 0 | F25: 2800 | G25: 834 | H25: ='AUG 24'!G25 -> 810 | I25: =G25-H25 -> 24 | J25: =I25*12 -> 288 | K25: 400 | L25: ='AUG 24'!O25 -> 8916 | M25: =F25+J25+K25+L25 -> 12404 | N25: 5000 | O25: =M25-N25 -> 7404 | Q25: ALLOTED FROM DEC 23. ADV NIL. RENT 2800
A26: 21 | B26: VACANT | C26: 2/5 | D26: 37681 | E26: 500 | F26: 0 | G26: 3254 | H26: ='AUG 24'!G26 -> 3254 | I26: =G26-H26 -> 0 | J26: =I26*12 -> 0 | K26: 0 | L26: ='AUG 24'!O26 -> 0 | M26: =F26+J26+K26+L26 -> 0 | N26: 0 | O26: =M26-N26 -> 0 | Q26: VACATED WEF NOV 23.
A27: 22 | B27: SUNIL MONDAL | C27: 2/6 | D27: 37681 | E27: 0 | F27: 3600 | G27: 4977 | H27: ='AUG 24'!G27 -> 4850 | I27: =G27-H27 -> 127 | J27: =I27*12 -> 1524 | K27: 400 | L27: ='AUG 24'!O27 -> 52138 | M27: =F27+J27+K27+L27 -> 57662 | N27: 0 | O27: =M27-N27 -> 57662 | Q27: REALLOTED WEF DEC 23. LAST RENT 3300. ADV 10K
C28: TOTAL | E28: =SUM(E6:E27) -> 7000 | F28: =SUM(F6:F27) -> 44600 | I28: =SUM(I6:I27) -> 904 | J28: =SUM(J6:J27) -> 10848 | K28: =SUM(K6:K27) -> 6000 | L28: =SUM(L6:L27) -> 222108 | M28: =SUM(M6:M27) -> 281556 | N28: =SUM(N6:N27) -> 61228 | O28: =SUM(O6:O27) -> 220328

Sheet AUG 24
A1: SITA DEVI PANDEY HOUSING PROJECT
A2: 11/1B/1 GANPAT RAI KHEMKA LANE LILUAH HOWRAH(W. B.) 711204
A3: FOR THE MONTH OF - AUG 2024 | U3: 44
A4: SNO | B4: NAME | C4: ROOM | D4: DATE OF | E4: ELECTRIC | F4: MTLY | G4: ELECTRIC | K4: MISC | L4: B/F & | M4: TOTAL | N4: AMT | O4: B/F OR | P4: PAYMENT | Q4: REMARKS
C5: NO | D5: ALLOTMENT | E5: SECURITY | F5: RENT | G5: NEW | H5: PRE | I5: TOTAL | J5: COST | K5: RENT | L5: ADV | M5: AMT DUE | N5: PAID | O5: ADV | P5: DATE
A6: 1 | B6: SUNNY PRAJAPATI | C6: G/1 | D6: 38754 | E6: 0 | F6: 2000 | G6: 1291 | H6: ='JUL 24'!G6 -> 1242 | I6: =G6-H6 -> 49 | J6: =I6*12 -> 588 | K6: 300 | L6: ='JUL 24'!O6 -> 11684 | M6: =F6+J6+K6+L6 -> 14572 | N6: 0 | O6: =M6-N6 -> 14572 | Q6: ALLOTED WEF SEP 21. ADV 10000. RENT 2000
A7: 2 | B7: MISHRA JI | C7: G/2 | D7: 37653 | E7: 0 | F7: 2000 | G7: 653 | H7: ='JUL 24'!G7 -> 582 | I7: =G7-H7 -> 71 | J7: =I7*12 -> 852 | K7: 300 | L7: ='JUL 24'!O7 -> 4812 | M7: =F7+J7+K7+L7 -> 7964 | N7: 7964 | O7: =M7-N7 -> 0 | Q7: VACATED FROM SEP 24. ALL CLEAR
A8: 3 | B8: PANKAJ PATEL | C8: G/3 | D8: 37895 | E8: 0 | F8: 2200 | G8: 4391 | H8: ='JUL 24'!G8 -> 4370 | I8: =G8-H8 -> 21 | J8: =I8*12 -> 252 | K8: 300 | L8: ='JUL 24'!O8 -> 15614 | M8: =F8+J8+K8+L8 -> 18366 | N8: 3000 | O8: =M8-N8 -> 15366 | Q8: ALLOTED WEF JUL 21. ADV 5K, RENT 2200 FM JUL 24.
A9: 4 | B9: BADRI MANDAL | C9: G/4 | D9: 38292 | E9: 500 | F9: 2000 | G9: 4359 | H9: ='JUL 24'!G9 -> 4318 | I9: =G9-H9 -> 41 | J9: =I9*12 -> 492 | K9: 300 | L9: ='JUL 24'!O9 -> 11942 | M9: =F9+J9+K9+L9 -> 14734 | N9: 4000 | O9: =M9-N9 -> 10734 | Q9: ALLOTED WEF 01 DEC 2022. RENT 2000. ADV 5000
A10: 5 | B10: VACANT | C10: G/5 | F10: 0 | G10: 4276 | H10: 4276 | I10: =G10-H10 -> 0 | J10: =I10*12 -> 0 | K10: 0 | L10: ='JUL 24'!O10 -> 0 | M10: =F10+J10+K10+L10 -> 0 | N10: 0 | O10: =M10-N10 -> 0 | Q10: VACANT FROM JUL 24
A11: 6 | B11: BADRI MANDAL | C11: G/6 | D11: 37667 | E11: 500 | F11: 2000 | G11: 1861 | H11: ='JUL 24'!G11 -> 1838 | I11: =G11-H11 -> 23 | J11: =I11*12 -> 276 | K11: 300 | L11: ='JUL 24'!O11 -> 5488 | M11: =F11+J11+K11+L11 -> 8064 | N11: 0 | O11: =M11-N11 -> 8064 | Q11: ALLOTED WEF JUN 24. ADV 4000, RENT 2000
A12: 7 | B12: RAM P SHRESTHA | C12: G/7 | D12: 37773 | E12: 500 | F12: 2000 | G12: 4904 | H12: ='JUL 24'!G12 -> 4875 | I12: =G12-H12 -> 29 | J12: =I12*12 -> 348 | K12: 300 | L12: ='JUL 24'!O12 -> 2596 | M12: =F12+J12+K12+L12 -> 5244 | N12: 5244 | O12: =M12-N12 -> 0 | Q12: ALLOTED WEF SEP 21. ADV 10000. RENT 2000
A13: 8 | B13: AJAY BAG | C13: G/8 | D13: 37469 | E13: 500 | F13: 1800 | G13: 3130 | H13: ='JUL 24'!G13 -> 3055 | I13: =G13-H13 -> 75 | J13: =I13*12 -> 900 | K13: 300 | L13: ='JUL 24'!O13 -> 13362 | M13: =F13+J13+K13+L13 -> 16362 | N13: 0 | O13: =M13-N13 -> 16362 | Q13: ALLOTED WEF MAR 22. ADV 10000. RENT 1800
A14: 9 | B14: PRAMOD MANDAL | C14: G/9 | D14: 37347 | E14: 500 | F14: 2100 | G14: 12791 | H14: ='JUL 24'!G14 -> 12709 | I14: =G14-H14 -> 82 | J14: =I14*12 -> 984 | K14: 300 | L14: ='JUL 24'!O14 -> 4200 | M14: =F14+J14+K14+L14 -> 7584 | N14: 7584 | O14: =M14-N14 -> 0 | Q14: ALLOTED WEF SEP 22. ADV 10000 RENT 2100 SHIFTJUL 23
A15: 10 | B15: PRAMOD MANDAL | C15: G/10 | D15: 37165 | E15: 500 | F15: 2000 | G15: 3575 | H15: ='JUL 24'!G15 -> 3377 | I15: =G15-H15 -> 198 | J15: =I15*12 -> 2376 | K15: 300 | L15: ='JUL 24'!O15 -> 0 | M15: =F15+J15+K15+L15 -> 4676 | N15: 4676 | O15: =M15-N15 -> 0 | Q15: ALLOTED WEF SEP 22. ADV 10000 RENT 2000
A16: 11 | B16: RAKESH AGARWAL | C16: 1/1 | D16: 38443 | E16: 0 | F16: 2100 | G16: 839 | H16: ='JUL 24'!G16 -> 826 | I16: =G16-H16 -> 13 | J16: =I16*12 -> 156 | K16: 400 | L16: ='JUL 24'!O16 -> 2500 | M16: =F16+J16+K16+L16 -> 5156 | N16: 0 | O16: =M16-N16 -> 5156 | Q16: ALLOTED WEF JUL 24. ADV 8K. RENT 2100
A17: 12 | B17: RAKESH AGARWAL | C17: 1/2 | D17: 38292 | F17: 3100 | G17: 6713 | H17: ='JUL 24'!G17 -> 6665 | I17: =G17-H17 -> 48 | J17: =I17*12 -> 576 | K17: 400 | L17: ='JUL 24'!O17 -> 3848 | M17: =F17+J17+K17+L17 -> 7924 | N17: 10000 | O17: =M17-N17 -> -2076 | Q17: ALLOTED WEF JUL 24. ADV 10K. RENT 3100
A18: 13 | B18: VACAMT | C18: 1/3 | D18: 38292 | E18: 500 | F18: 0 | G18: 5616 | H18: ='JUL 24'!G18 -> 5616 | I18: =G18-H18 -> 0 | J18: =I18*12 -> 0 | K18: 0 | L18: 0 | M18: =F18+J18+K18+L18 -> 0 | N18: 0 | O18: =M18-N18 -> 0 | Q18: VACANT FROM AUT 24
A19: 14 | B19: ANIL SHARMA | C19: 1/4 | D19: 38292 | E19: 500 | F19: 3000 | G19: 3894 | H19: ='JUL 24'!G19 -> 3845 | I19: =G19-H19 -> 49 | J19: =I19*12 -> 588 | K19: 400 | L19: ='JUL 24'!O19 -> 0 | M19: =F19+J19+K19+L19 -> 3988 | N19: 4000 | O19: =M19-N19 -> -12 | Q19: ADV 15K.19--5-24. RENT 3000
A20: 15 | B20: VACANT | C20: 1/5 | D20: 37469 | E20: 500 | F20: 0 | G20: 4244 | H20: ='JUL 24'!G20 -> 4244 | I20: =G20-H20 -> 0 | J20: =I20*12 -> 0 | K20: 0 | L20: ='JUL 24'!O20 -> 0 | M20: =F20+J20+K20+L20 -> 0 | N20: 0 | O20: =M20-N20 -> 0 | Q20: VACANT WEF NOV 2023
A21: 16 | B21: SHAILENDRA PANDEY | C21: 1/6 | D21: 37681 | E21: 500 | F21: 3000 | G21: 3206 | H21: ='JUL 24'!G21 -> 3147 | I21: =G21-H21 -> 59 | J21: =I21*12 -> 708 | K21: 400 | L21: ='JUL 24'!O21 -> 34378 | M21: =F21+J21+K21+L21 -> 38486 | N21: 0 | O21: =M21-N21 -> 38486 | Q21: RENT INCREASED WEF MAR 24 FROM 2300. ADV 10000
A22: 17 | B22: BIRENDAR YADAV | C22: 2/1 | D22: 38292 | E22: 500 | F22: 2800 | G22: 593 | H22: ='JUL 24'!G22 -> 556 | I22: =G22-H22 -> 37 | J22: =I22*12 -> 444 | K22: 400 | L22: ='JUL 24'!O22 -> 44748 | M22: =F22+J22+K22+L22 -> 48392 | N22: 10000 | O22: =M22-N22 -> 38392 | Q22: RENT INCREASED WEF DEC 22 FROM 2200. ADV NIL
A23: 18 | B23: HARI SHANKER SHUKLA | C23: 2/2 | D23: 38292 | E23: 500 | F23: 3100 | G23: 919 | H23: ='JUL 24'!G23 -> 870 | I23: =G23-H23 -> 49 | J23: =I23*12 -> 588 | K23: 400 | L23: ='JUL 24'!O23 -> 8362 | M23: =F23+J23+K23+L23 -> 12450 | N23: 0 | O23: =M23-N23 -> 12450 | Q23: RENT INCRESED WEF JUL 24 FROM 2700. ADV 10000
A24: 19 | B24: SHIV SHANKER PANDEY | C24: 2/3 | D24: 37681 | E24: 500 | F24: 2800 | G24: 5366 | H24: ='JUL 24'!G24 -> 5336 | I24: =G24-H24 -> 30 | J24: =I24*12 -> 360 | K24: 400 | L24: ='JUL 24'!O24 -> 0 | M24: =F24+J24+K24+L24 -> 3560 | N24: 0 | O24: =M24-N24 -> 3560 | Q24: REALLOTED WEF DEC 22. RENT 2800. ADV NIL
A25: 20 | B25: PRAKASH PANDEY | C25: 2/4 | D25: 37681 | E25: 0 | F25: 2800 | G25: 810 | H25: ='JUL 24'!G25 -> 800 | I25: =G25-H25 -> 10 | J25: =I25*12 -> 120 | K25: 400 | L25: ='JUL 24'!O25 -> 10596 | M25: =F25+J25+K25+L25 -> 13916 | N25: 5000 | O25: =M25-N25 -> 8916 | Q25: ALLOTED FROM DEC 23. ADV NIL. RENT 2800
A26: 21 | B26: VACANT | C26: 2/5 | D26: 37681 | E26: 500 | F26: 0 | G26: 3254 | H26: ='JUL 24'!G26 -> 3254 | I26: =G26-H26 -> 0 | J26: =I26*12 -> 0 | K26: 0 | L26: ='JUL 24'!O26 -> 0 | M26: =F26+J26+K26+L26 -> 0 | N26: 0 | O26: =M26-N26 -> 0 | Q26: VACATED WEF NOV 23.
A27: 22 | B27: SUNIL MONDAL | C27: 2/6 | D27: 37681 | E27: 0 | F27: 3600 | G27: 4850 | H27: ='JUL 24'!G27 -> 4712 | I27: =G27-H27 -> 138 | J27: =I27*12 -> 1656 | K27: 400 | L27: ='JUL 24'!O27 -> 61482 | M27: =F27+J27+K27+L27 -> 67138 | N27: 15000 | O27: =M27-N27 -> 52138 | Q27: REALLOTED WEF DEC 23. LAST RENT 3300. ADV 10K
C28: TOTAL | E28: =SUM(E6:E27) -> 7000 | F28: =SUM(F6:F27) -> 44400 | I28: =SUM(I6:I27) -> 1022 | J28: =SUM(J6:J27) -> 12264 | K28: =SUM(K6:K27) -> 6300 | L28: =SUM(L6:L27) -> 235612 | M28: =SUM(M6:M27) -> 298576 | N28: =SUM(N6:N27) -> 76468 | O28: =SUM(O6:O27) -> 222108

Sheet JUL 24
A1: SITA DEVI PANDEY HOUSING PROJECT
A2: 11/1B/1 GANPAT RAI KHEMKA LANE LILUAH HOWRAH(W. B.) 711204
A3: FOR THE MONTH OF - JUL 2024 | U3: 44
A4: SNO | B4: NAME | C4: ROOM | D4: DATE OF | E4: ELECTRIC | F4: MTLY | G4: ELECTRIC | K4: MISC | L4: B/F & | M4: TOTAL | N4: AMT | O4: B/F OR | P4: PAYMENT | Q4: REMARKS
C5: NO | D5: ALLOTMENT | E5: SECURITY | F5: RENT | G5: NEW | H5: PRE | I5: TOTAL | J5: COST | K5: RENT | L5: ADV | M5: AMT DUE | N5: PAID | O5: ADV | P5: DATE
A6: 1 | B6: SUNNY PRAJAPATI | C6: G/1 | D6: 38754 | E6: 0 | F6: 2000 | G6: 1242 | H6: ='JUN 24 '!G6 -> 1208 | I6: =G6-H6 -> 34 | J6: =I6*12 -> 408 | K6: 300 | L6: ='JUN 24 '!O6 -> 8976 | M6: =F6+J6+K6+L6 -> 11684 | N6: 0 | O6: =M6-N6 -> 11684 | Q6: ALLOTED WEF SEP 21. ADV 10000. RENT 2000
A7: 2 | B7: MISHRA JI | C7: G/2 | D7: 37653 | E7: 0 | F7: 2000 | G7: 582 | H7: ='JUN 24 '!G7 -> 534 | I7: =G7-H7 -> 48 | J7: =I7*12 -> 576 | K7: 300 | L7: ='JUN 24 '!O7 -> 1936 | M7: =F7+J7+K7+L7 -> 4812 | N7: 0 | O7: =M7-N7 -> 4812 | Q7: ALLLTED WEF SEP 23. ADV 5K RENT 2000.
A8: 3 | B8: PANKAJ PATEL | C8: G/3 | D8: 37895 | E8: 0 | F8: 2000 | G8: 4370 | H8: ='JUN 24 '!G8 -> 4346 | I8: =G8-H8 -> 24 | J8: =I8*12 -> 288 | K8: 300 | L8: ='JUN 24 '!O8 -> 19026 | M8: =F8+J8+K8+L8 -> 21614 | N8: 6000 | O8: =M8-N8 -> 15614 | Q8: ALLOTED WEF JUL 21. ADV 5K, RENT 2000.
A9: 4 | B9: BADRI MANDAL | C9: G/4 | D9: 38292 | E9: 500 | F9: 2000 | G9: 4318 | H9: ='JUN 24 '!G9 -> 4278 | I9: =G9-H9 -> 40 | J9: =I9*12 -> 480 | K9: 300 | L9: ='JUN 24 '!O9 -> 9162 | M9: =F9+J9+K9+L9 -> 11942 | N9: 0 | O9: =M9-N9 -> 11942 | Q9: ALLOTED WEF 01 DEC 2022. RENT 2000. ADV 5000
A10: 5 | B10: VACANT | C10: G/5 | F10: 0 | G10: 4275 | H10: ='JUN 24 '!G10 -> 4245 | I10: =G10-H10 -> 30 | J10: =I10*12 -> 360 | K10: 0 | L10: ='JUN 24 '!O10 -> 0 | M10: =F10+J10+K10+L10 -> 360 | N10: 360 | O10: =M10-N10 -> 0 | Q10: ALLOTED WEF SEP 23. ADV 5K. RENT 2K
A11: 6 | B11: BADRI MANDAL | C11: G/6 | D11: 37667 | E11: 500 | F11: 2000 | G11: 1838 | H11: ='JUN 24 '!G11 -> 1803 | I11: =G11-H11 -> 35 | J11: =I11*12 -> 420 | K11: 300 | L11: ='JUN 24 '!O11 -> 2768 | M11: =F11+J11+K11+L11 -> 5488 | N11: 0 | O11: =M11-N11 -> 5488 | Q11: ALLOTED WEF JUN 24. ADV 4000, RENT 2000
A12: 7 | B12: RAM P SHRESTHA | C12: G/7 | D12: 37773 | E12: 500 | F12: 2000 | G12: 4875 | H12: ='JUN 24 '!G12 -> 4850 | I12: =G12-H12 -> 25 | J12: =I12*12 -> 300 | K12: 300 | L12: ='JUN 24 '!O12 -> -4 | M12: =F12+J12+K12+L12 -> 2596 | N12: 0 | O12: =M12-N12 -> 2596 | Q12: ALLOTED WEF SEP 21. ADV 10000. RENT 2000
A13: 8 | B13: AJAY BAG | C13: G/8 | D13: 37469 | E13: 500 | F13: 1800 | G13: 3055 | H13: ='JUN 24 '!G13 -> 3012 | I13: =G13-H13 -> 43 | J13: =I13*12 -> 516 | K13: 300 | L13: ='JUN 24 '!O13 -> 10746 | M13: =F13+J13+K13+L13 -> 13362 | N13: 0 | O13: =M13-N13 -> 13362 | Q13: ALLOTED WEF MAR 22. ADV 10000. RENT 1800
A14: 9 | B14: PRAMOD MANDAL | C14: G/9 | D14: 37347 | E14: 500 | F14: 2100 | G14: 12709 | H14: ='JUN 24 '!G14 -> 12665 | I14: =G14-H14 -> 44 | J14: =I14*12 -> 528 | K14: 300 | L14: ='JUN 24 '!O14 -> 1272 | M14: =F14+J14+K14+L14 -> 4200 | N14: 0 | O14: =M14-N14 -> 4200 | Q14: ALLOTED WEF SEP 22. ADV 10000 RENT 2100 SHIFTJUL 23
A15: 10 | B15: PRAMOD MANDAL | C15: G/10 | D15: 37165 | E15: 500 | F15: 2000 | G15: 3377 | H15: ='JUN 24 '!G15 -> 3308 | I15: =G15-H15 -> 69 | J15: =I15*12 -> 828 | K15: 300 | L15: ='JUN 24 '!O15 -> 0 | M15: =F15+J15+K15+L15 -> 3128 | N15: 3128 | O15: =M15-N15 -> 0 | Q15: ALLOTED WEF SEP 22. ADV 10000 RENT 2000
A16: 11 | B16: RAKESH AGARWAL | C16: 1/1 | D16: 38443 | E16: 0 | F16: 2100 | G16: 826 | H16: ='JUN 24 '!G16 -> 826 | I16: =G16-H16 -> 0 | J16: =I16*12 -> 0 | K16: 400 | L16: ='JUN 24 '!O16 -> 0 | M16: =F16+J16+K16+L16 -> 2500 | N16: 0 | O16: =M16-N16 -> 2500 | Q16: ALLOTED WEF JUL 24. ADV 10K. RENT 2100
A17: 12 | B17: RAKESH AGARWAL | C17: 1/2 | D17: 38292 | F17: 3100 | G17: 6665 | H17: ='JUN 24 '!G17 -> 6636 | I17: =G17-H17 -> 29 | J17: =I17*12 -> 348 | K17: 400 | L17: ='JUN 24 '!O17 -> 0 | M17: =F17+J17+K17+L17 -> 3848 | N17: 0 | O17: =M17-N17 -> 3848 | Q17: ALLOTED WEF JUL 24. ADV 10K. RENT 3100
A18: 13 | B18: AJAY DUBEY | C18: 1/3 | D18: 38292 | E18: 500 | F18: 3100 | G18: 5616 | H18: ='JUN 24 '!G18 -> 5545 | I18: =G18-H18 -> 71 | J18: =I18*12 -> 852 | K18: 400 | L18: ='JUN 24 '!O18 -> 19610 | M18: =F18+J18+K18+L18 -> 23962 | N18: 15000 | O18: =M18-N18 -> 8962 | Q18: RENT INCREASED WEF JUL 21 FROM 2600, ADV 15000
A19: 14 | B19: ANIL SHARMA | C19: 1/4 | D19: 38292 | E19: 500 | F19: 3000 | G19: 3845 | H19: ='JUN 24 '!G19 -> 3799 | I19: =G19-H19 -> 46 | J19: =I19*12 -> 552 | K19: 400 | L19: ='JUN 24 '!O19 -> -22 | M19: =F19+J19+K19+L19 -> 3930 | N19: 3930 | O19: =M19-N19 -> 0 | Q19: ADV 15K.19--5-24. RENT 3000
A20: 15 | B20: VACANT | C20: 1/5 | D20: 37469 | E20: 500 | F20: 0 | G20: 4244 | H20: ='JUN 24 '!G20 -> 4239 | I20: =G20-H20 -> 5 | J20: =I20*12 -> 60 | K20: 0 | L20: ='JUN 24 '!O20 -> 0 | M20: =F20+J20+K20+L20 -> 60 | N20: 60 | O20: =M20-N20 -> 0 | Q20: VACANT WEF NOV 2023
A21: 16 | B21: SHAILENDRA PANDEY | C21: 1/6 | D21: 37681 | E21: 500 | F21: 3000 | G21: 3147 | H21: ='JUN 24 '!G21 -> 3095 | I21: =G21-H21 -> 52 | J21: =I21*12 -> 624 | K21: 400 | L21: ='JUN 24 '!O21 -> 30354 | M21: =F21+J21+K21+L21 -> 34378 | N21: 0 | O21: =M21-N21 -> 34378 | Q21: RENT INCREASED WEF MAR 21 FROM 2300. ADV 10000
A22: 17 | B22: BIRENDAR YADAV | C22: 2/1 | D22: 38292 | E22: 500 | F22: 2800 | G22: 556 | H22: ='JUN 24 '!G22 -> 514 | I22: =G22-H22 -> 42 | J22: =I22*12 -> 504 | K22: 400 | L22: ='JUN 24 '!O22 -> 41044 | M22: =F22+J22+K22+L22 -> 44748 | N22: 0 | O22: =M22-N22 -> 44748 | Q22: RENT INCREASED WEF DEC 22 FROM 2200. ADV NIL
A23: 18 | B23: HARI SHANKER SHUKLA | C23: 2/2 | D23: 38292 | E23: 500 | F23: 2700 | G23: 870 | H23: ='JUN 24 '!G23 -> 852 | I23: =G23-H23 -> 18 | J23: =I23*12 -> 216 | K23: 400 | L23: ='JUN 24 '!O23 -> 15046 | M23: =F23+J23+K23+L23 -> 18362 | N23: 10000 | O23: =M23-N23 -> 8362 | Q23: RENT INCRESED WEF JUL 21 FROM 2200. ADV 10000
A24: 19 | B24: SHIV SHANKER PANDEY | C24: 2/3 | D24: 37681 | E24: 500 | F24: 2800 | G24: 5336 | H24: ='JUN 24 '!G24 -> 5307 | I24: =G24-H24 -> 29 | J24: =I24*12 -> 348 | K24: 400 | L24: -6 | M24: =F24+J24+K24+L24 -> 3542 | N24: 3542 | O24: =M24-N24 -> 0 | Q24: REALLOTED WEF DEC 22. RENT 2800. ADV NIL
A25: 20 | B25: PRAKASH PANDEY | C25: 2/4 | D25: 37681 | E25: 0 | F25: 2800 | G25: 800 | H25: ='JUN 24 '!G25 -> 769 | I25: =G25-H25 -> 31 | J25: =I25*12 -> 372 | K25: 400 | L25: ='JUN 24 '!O25 -> 7024 | M25: =F25+J25+K25+L25 -> 10596 | N25: 0 | O25: =M25-N25 -> 10596 | Q25: ALLOTED FROM DEC 23. ADV NIL. RENT 2800
A26: 21 | B26: VACANT | C26: 2/5 | D26: 37681 | E26: 500 | F26: 0 | G26: 3254 | H26: ='JUN 24 '!G26 -> 3254 | I26: =G26-H26 -> 0 | J26: =I26*12 -> 0 | K26: 0 | L26: ='JUN 24 '!O26 -> 0 | M26: =F26+J26+K26+L26 -> 0 | N26: 0 | O26: =M26-N26 -> 0 | Q26: VACATED WEF NOV 23.
A27: 22 | B27: SUNIL MONDAL | C27: 2/6 | D27: 37681 | E27: 0 | F27: 3600 | G27: 4712 | H27: ='JUN 24 '!G27 -> 4616 | I27: =G27-H27 -> 96 | J27: =I27*12 -> 1152 | K27: 400 | L27: ='JUN 24 '!O27 -> 56330 | M27: =F27+J27+K27+L27 -> 61482 | N27: 0 | O27: =M27-N27 -> 61482 | Q27: REALLOTED WEF DEC 23. LAST RENT 3300. ADV 10K
C28: TOTAL | E28: =SUM(E6:E27) -> 7000 | F28: =SUM(F6:F27) -> 46900 | I28: =SUM(I6:I27) -> 811 | J28: =SUM(J6:J27) -> 9732 | K28: =SUM(K6:K27) -> 6700 | L28: =SUM(L6:L27) -> 223262 | M28: =SUM(M6:M27) -> 286594 | N28: =SUM(N6:N27) -> 42020 | O28: =SUM(O6:O27) -> 244574

Sheet JUN 24 
A1: SITA DEVI PANDEY HOUSING PROJECT
A2: 11/1B/1 GANPAT RAI KHEMKA LANE LILUAH HOWRAH(W. B.) 711204
A3: FOR THE MONTH OF - JUN 2024 | U3: 44
A4: SNO | B4: NAME | C4: ROOM | D4: DATE OF | E4: ELECTRIC | F4: MTLY | G4: ELECTRIC | K4: MISC | L4: B/F & | M4: TOTAL | N4: AMT | O4: B/F OR | P4: PAYMENT | Q4: REMARKS
C5: NO | D5: ALLOTMENT | E5: SECURITY | F5: RENT | G5: NEW | H5: PRE | I5: TOTAL | J5: COST | K5: RENT | L5: ADV | M5: AMT DUE | N5: PAID | O5: ADV | P5: DATE
A6: 1 | B6: SUNNY PRAJAPATI | C6: G/1 | D6: 38754 | E6: 0 | F6: 2000 | G6: 1208 | H6: ='MAY 24'!G6 -> 1173 | I6: =G6-H6 -> 35 | J6: =I6*12 -> 420 | K6: 300 | L6: ='MAY 24'!O6 -> 6256 | M6: =F6+J6+K6+L6 -> 8976 | N6: 0 | O6: =M6-N6 -> 8976 | Q6: ALLOTED WEF SEP 21. ADV 10000. RENT 2000
A7: 2 | B7: MISHRA JI | C7: G/2 | D7: 37653 | E7: 0 | F7: 2000 | G7: 534 | H7: ='MAY 24'!G7 -> 471 | I7: =G7-H7 -> 63 | J7: =I7*12 -> 756 | K7: 300 | L7: ='MAY 24'!O7 -> 1880 | M7: =F7+J7+K7+L7 -> 4936 | N7: 3000 | O7: =M7-N7 -> 1936 | Q7: ALLLTED WEF SEP 23. ADV 5K RENT 2000.
A8: 3 | B8: PANKAJ PATEL | C8: G/3 | D8: 37895 | E8: 0 | F8: 2000 | G8: 4346 | H8: ='MAY 24'!G8 -> 4336 | I8: =G8-H8 -> 10 | J8: =I8*12 -> 120 | K8: 300 | L8: ='MAY 24'!O8 -> 16606 | M8: =F8+J8+K8+L8 -> 19026 | N8: 0 | O8: =M8-N8 -> 19026 | Q8: ALLOTED WEF JUL 21. ADV 5K, RENT 2000.
A9: 4 | B9: BADRI MANDAL | C9: G/4 | D9: 38292 | E9: 500 | F9: 2000 | G9: 4278 | H9: ='MAY 24'!G9 -> 4231 | I9: =G9-H9 -> 47 | J9: =I9*12 -> 564 | K9: 300 | L9: ='MAY 24'!O9 -> 11298 | M9: =F9+J9+K9+L9 -> 14162 | N9: 5000 | O9: =M9-N9 -> 9162 | Q9: ALLOTED WEF 01 DEC 2022. RENT 2000. ADV 5000
A10: 5 | B10: NEW | C10: G/5 | F10: 2000 | G10: 4245 | H10: ='MAY 24'!G10 -> 4181 | I10: =G10-H10 -> 64 | J10: =I10*12 -> 768 | K10: 300 | L10: ='MAY 24'!O10 -> 470 | M10: =F10+J10+K10+L10 -> 3538 | N10: 3538 | O10: =M10-N10 -> 0 | Q10: VACATED WEF JUL 2024.
A11: 6 | B11: BADRI MANDAL | C11: G/6 | D11: 37667 | E11: 500 | F11: 2000 | G11: 1803 | H11: ='MAY 24'!G11 -> 1764 | I11: =G11-H11 -> 39 | J11: =I11*12 -> 468 | K11: 300 | L11: ='MAY 24'!O11 -> 0 | M11: =F11+J11+K11+L11 -> 2768 | N11: 0 | O11: =M11-N11 -> 2768 | Q11: ALLOTED WEF JUN 24. ADV 4000, RENT 2000
A12: 7 | B12: RAM P SHRESTHA | C12: G/7 | D12: 37773 | E12: 500 | F12: 2000 | G12: 4850 | H12: ='MAY 24'!G12 -> 4817 | I12: =G12-H12 -> 33 | J12: =I12*12 -> 396 | K12: 300 | L12: ='MAY 24'!O12 -> 0 | M12: =F12+J12+K12+L12 -> 2696 | N12: 2700 | O12: =M12-N12 -> -4 | Q12: ALLOTED WEF SEP 21. ADV 10000. RENT 2000
A13: 8 | B13: AJAY BAG | C13: G/8 | D13: 37469 | E13: 500 | F13: 1800 | G13: 3012 | H13: ='MAY 24'!G13 -> 2939 | I13: =G13-H13 -> 73 | J13: =I13*12 -> 876 | K13: 300 | L13: ='MAY 24'!O13 -> 7770 | M13: =F13+J13+K13+L13 -> 10746 | N13: 0 | O13: =M13-N13 -> 10746 | Q13: ALLOTED WEF MAR 22. ADV 10000. RENT 1800
A14: 9 | B14: PRAMOD MANDAL | C14: G/9 | D14: 37347 | E14: 500 | F14: 2100 | G14: 12665 | H14: ='MAY 24'!G14 -> 12621 | I14: =G14-H14 -> 44 | J14: =I14*12 -> 528 | K14: 300 | L14: ='MAY 24'!O14 -> 4344 | M14: =F14+J14+K14+L14 -> 7272 | N14: 6000 | O14: =M14-N14 -> 1272 | Q14: ALLOTED WEF SEP 22. ADV 10000 RENT 2100 SHIFTJUL 23
A15: 10 | B15: PRAMOD MANDAL | C15: G/10 | D15: 37165 | E15: 500 | F15: 2000 | G15: 3308 | H15: ='MAY 24'!G15 -> 3298 | I15: =G15-H15 -> 10 | J15: =I15*12 -> 120 | K15: 300 | L15: ='MAY 24'!O15 -> 3300 | M15: =F15+J15+K15+L15 -> 5720 | N15: 5720 | O15: =M15-N15 -> 0 | Q15: ALLOTED WEF SEP 22. ADV 10000 RENT 2000
A16: 11 | B16: SONU PRAJAPATI | C16: 1/1 | D16: 38443 | E16: 0 | F16: 2200 | G16: 826 | H16: ='MAY 24'!G16 -> 789 | I16: =G16-H16 -> 37 | J16: =I16*12 -> 444 | K16: 400 | L16: ='MAY 24'!O16 -> 17438 | M16: =F16+J16+K16+L16 -> 20482 | N16: 20482 | O16: =M16-N16 -> 0 | Q16: VACATED WEF JUN 24. 10K DUE
A17: 12 | B17: GOPAL SINGH | C17: 1/2 | D17: 38292 | F17: 3300 | G17: 6636 | H17: ='MAY 24'!G17 -> 6562 | I17: =G17-H17 -> 74 | J17: =I17*12 -> 888 | K17: 400 | L17: ='MAY 24'!O17 -> 1794 | M17: =F17+J17+K17+L17 -> 6382 | N17: 6382 | O17: =M17-N17 -> 0 | Q17: VACATED WEF JUN. ALL DUES CLEAR
A18: 13 | B18: AJAY DUBEY | C18: 1/3 | D18: 38292 | E18: 500 | F18: 3100 | G18: 5545 | H18: ='MAY 24'!G18 -> 5436 | I18: =G18-H18 -> 109 | J18: =I18*12 -> 1308 | K18: 400 | L18: ='MAY 24'!O18 -> 14802 | M18: =F18+J18+K18+L18 -> 19610 | N18: 0 | O18: =M18-N18 -> 19610 | Q18: RENT INCREASED WEF JUL 21 FROM 2600, ADV 15000
A19: 14 | B19: ANIL SHARMA | C19: 1/4 | D19: 38292 | E19: 500 | F19: 3000 | G19: 3799 | H19: ='MAY 24'!G19 -> 3746 | I19: =G19-H19 -> 53 | J19: =I19*12 -> 636 | K19: 400 | L19: ='MAY 24'!O19 -> -8 | M19: =F19+J19+K19+L19 -> 4028 | N19: 4050 | O19: =M19-N19 -> -22 | Q19: ADV 15K.19--5-24. RENT 3000
A20: 15 | B20: VACANT | C20: 1/5 | D20: 37469 | E20: 500 | F20: 0 | G20: 4239 | H20: ='MAY 24'!G20 -> 4232 | I20: =G20-H20 -> 7 | J20: =I20*12 -> 84 | K20: 0 | L20: ='MAY 24'!O20 -> 0 | M20: =F20+J20+K20+L20 -> 84 | N20: 84 | O20: =M20-N20 -> 0 | Q20: VACANT WEF NOV 2023
A21: 16 | B21: SHAILENDRA PANDEY | C21: 1/6 | D21: 37681 | E21: 500 | F21: 3000 | G21: 3095 | H21: ='MAY 24'!G21 -> 3020 | I21: =G21-H21 -> 75 | J21: =I21*12 -> 900 | K21: 400 | L21: ='MAY 24'!O21 -> 31054 | M21: =F21+J21+K21+L21 -> 35354 | N21: 5000 | O21: =M21-N21 -> 30354 | Q21: RENT INCREASED WEF MAR 21 FROM 2300. ADV 10000
A22: 17 | B22: BIRENDAR YADAV | C22: 2/1 | D22: 38292 | E22: 500 | F22: 2800 | G22: 514 | H22: ='MAY 24'!G22 -> 466 | I22: =G22-H22 -> 48 | J22: =I22*12 -> 576 | K22: 400 | L22: ='MAY 24'!O22 -> 42268 | M22: =F22+J22+K22+L22 -> 46044 | N22: 5000 | O22: =M22-N22 -> 41044 | Q22: RENT INCREASED WEF DEC 22 FROM 2200. ADV NIL
A23: 18 | B23: HARI SHANKER SHUKLA | C23: 2/2 | D23: 38292 | E23: 500 | F23: 2700 | G23: 852 | H23: ='MAY 24'!G23 -> 851 | I23: =G23-H23 -> 1 | J23: =I23*12 -> 12 | K23: 400 | L23: ='MAY 24'!O23 -> 11934 | M23: =F23+J23+K23+L23 -> 15046 | N23: 0 | O23: =M23-N23 -> 15046 | Q23: RENT INCRESED WEF JUL 21 FROM 2200. ADV 10000
A24: 19 | B24: SHIV SHANKER PANDEY | C24: 2/3 | D24: 37681 | E24: 500 | F24: 2800 | G24: 5307 | H24: ='MAY 24'!G24 -> 5270 | I24: =G24-H24 -> 37 | J24: =I24*12 -> 444 | K24: 400 | L24: ='MAY 24'!O24 -> 10 | M24: =F24+J24+K24+L24 -> 3654 | N24: 3660 | O24: =M24-N24 -> -6 | Q24: REALLOTED WEF DEC 22. RENT 2800. ADV NIL
A25: 20 | B25: PRAKASH PANDEY | C25: 2/4 | D25: 37681 | E25: 0 | F25: 2800 | G25: 769 | H25: ='MAY 24'!G25 -> 704 | I25: =G25-H25 -> 65 | J25: =I25*12 -> 780 | K25: 400 | L25: ='MAY 24'!O25 -> 11344 | M25: =F25+J25+K25+L25 -> 15324 | N25: 8300 | O25: =M25-N25 -> 7024 | Q25: ALLOTED FROM DEC 23. ADV NIL. RENT 2800
A26: 21 | B26: VACANT | C26: 2/5 | D26: 37681 | E26: 500 | F26: 0 | G26: 3254 | H26: ='MAY 24'!G26 -> 3254 | I26: =G26-H26 -> 0 | J26: =I26*12 -> 0 | K26: 0 | L26: ='MAY 24'!O26 -> 0 | M26: =F26+J26+K26+L26 -> 0 | N26: 0 | O26: =M26-N26 -> 0 | Q26: VACATED WEF NOV 23.
A27: 22 | B27: SUNIL MONDAL | C27: 2/6 | D27: 37681 | E27: 0 | F27: 3600 | G27: 4616 | H27: ='MAY 24'!G27 -> 4476 | I27: =G27-H27 -> 140 | J27: =I27*12 -> 1680 | K27: 400 | L27: ='MAY 24'!O27 -> 50650 | M27: =F27+J27+K27+L27 -> 56330 | N27: 0 | O27: =M27-N27 -> 56330 | Q27: REALLOTED WEF DEC 23. LAST RENT 3300. ADV 10K
C28: TOTAL | E28: =SUM(E6:E27) -> 7000 | F28: =SUM(F6:F27) -> 49200 | I28: =SUM(I6:I27) -> 1064 | J28: =SUM(J6:J27) -> 12768 | K28: =SUM(K6:K27) -> 7000 | L28: =SUM(L6:L27) -> 233210 | M28: =SUM(M6:M27) -> 302178 | N28: =SUM(N6:N27) -> 78916 | O28: =SUM(O6:O27) -> 223262

Sheet MAY 24
A1: SITA DEVI PANDEY HOUSING PROJECT
A2: 11/1B/1 GANPAT RAI KHEMKA LANE LILUAH HOWRAH(W. B.) 711204
A3: FOR THE MONTH OF - MAY 2024 | U3: 44
A4: SNO | B4: NAME | C4: ROOM | D4: DATE OF | E4: ELECTRIC | F4: MTLY | G4: ELECTRIC | K4: MISC | L4: B/F & | M4: TOTAL | N4: AMT | O4: B/F OR | P4: PAYMENT | Q4: REMARKS
C5: NO | D5: ALLOTMENT | E5: SECURITY | F5: RENT | G5: NEW | H5: PRE | I5: TOTAL | J5: COST | K5: RENT | L5: ADV | M5: AMT DUE | N5: PAID | O5: ADV | P5: DATE
A6: 1 | B6: SUNNY PRAJAPATI | C6: G/1 | D6: 38754 | E6: 0 | F6: 2000 | G6: 1173 | H6: ='APR 24'!G6 -> 1150 | I6: =G6-H6 -> 23 | J6: =I6*12 -> 276 | K6: 300 | L6: ='APR 24'!O6 -> 3680 | M6: =F6+J6+K6+L6 -> 6256 | N6: 0 | O6: =M6-N6 -> 6256 | Q6: ALLOTED WEF SEP 21. ADV 10000. RENT 2000
A7: 2 | B7: MISHRA JI | C7: G/2 | D7: 37653 | E7: 0 | F7: 2000 | G7: 471 | H7: ='APR 24'!G7 -> 417 | I7: =G7-H7 -> 54 | J7: =I7*12 -> 648 | K7: 300 | L7: ='APR 24'!O7 -> 1932 | M7: =F7+J7+K7+L7 -> 4880 | N7: 3000 | O7: =M7-N7 -> 1880 | Q7: ALLLTED WEF SEP 23. ADV 5K RENT 2000.
A8: 3 | B8: PANKAJ PATEL | C8: G/3 | D8: 37895 | E8: 0 | F8: 2000 | G8: 4336 | H8: ='APR 24'!G8 -> 4308 | I8: =G8-H8 -> 28 | J8: =I8*12 -> 336 | K8: 300 | L8: ='APR 24'!O8 -> 16970 | M8: =F8+J8+K8+L8 -> 19606 | N8: 3000 | O8: =M8-N8 -> 16606 | Q8: ALLOTED WEF JUL 21. ADV 5K, RENT 2000.
A9: 4 | B9: BADRI MANDAL | C9: G/4 | D9: 38292 | E9: 500 | F9: 2000 | G9: 4231 | H9: ='APR 24'!G9 -> 4197 | I9: =G9-H9 -> 34 | J9: =I9*12 -> 408 | K9: 300 | L9: ='APR 24'!O9 -> 8590 | M9: =F9+J9+K9+L9 -> 11298 | N9: 0 | O9: =M9-N9 -> 11298 | Q9: ALLOTED WEF 01 DEC 2022. RENT 2000. ADV 5000
A10: 5 | B10: NEW | C10: G/5 | F10: 2000 | G10: 4181 | H10: ='APR 24'!G10 -> 4125 | I10: =G10-H10 -> 56 | J10: =I10*12 -> 672 | K10: 300 | L10: ='APR 24'!O10 -> 498 | M10: =F10+J10+K10+L10 -> 3470 | N10: 3000 | O10: =M10-N10 -> 470 | Q10: ALLOTED WEF SEP 23. ADV 5K. RENT 2K
A11: 6 | B11: NEW FROM JUN 24 | C11: G/6 | D11: 37667 | E11: 500 | F11: 0 | G11: 1764 | H11: ='APR 24'!G11 -> 1750 | I11: =G11-H11 -> 14 | J11: =I11*12 -> 168 | K11: 0 | L11: ='APR 24'!O11 -> 0 | M11: =F11+J11+K11+L11 -> 168 | N11: 168 | O11: =M11-N11 -> 0 | Q11: ALLOTED WEF JUN 24. ADV 4000, RENT 2000
A12: 7 | B12: RAM P SHRESTHA | C12: G/7 | D12: 37773 | E12: 500 | F12: 2000 | G12: 4817 | H12: ='APR 24'!G12 -> 4791 | I12: =G12-H12 -> 26 | J12: =I12*12 -> 312 | K12: 300 | L12: ='APR 24'!O12 -> 3524 | M12: =F12+J12+K12+L12 -> 6136 | N12: 6136 | O12: =M12-N12 -> 0 | Q12: ALLOTED WEF SEP 21. ADV 10000. RENT 2000
A13: 8 | B13: AJAY BAG | C13: G/8 | D13: 37469 | E13: 500 | F13: 1800 | G13: 2939 | H13: ='APR 24'!G13 -> 2871 | I13: =G13-H13 -> 68 | J13: =I13*12 -> 816 | K13: 300 | L13: ='APR 24'!O13 -> 4854 | M13: =F13+J13+K13+L13 -> 7770 | N13: 0 | O13: =M13-N13 -> 7770 | Q13: ALLOTED WEF MAR 22. ADV 10000. RENT 1800
A14: 9 | B14: PRAMOD MANDAL | C14: G/9 | D14: 37347 | E14: 500 | F14: 2100 | G14: 12621 | H14: ='APR 24'!G14 -> 12585 | I14: =G14-H14 -> 36 | J14: =I14*12 -> 432 | K14: 300 | L14: ='APR 24'!O14 -> 1512 | M14: =F14+J14+K14+L14 -> 4344 | N14: 0 | O14: =M14-N14 -> 4344 | Q14: ALLOTED WEF SEP 22. ADV 10000 RENT 2100 SHIFTJUL 23
A15: 10 | B15: PRAMOD MANDAL | C15: G/10 | D15: 37165 | E15: 500 | F15: 2000 | G15: 3298 | H15: ='APR 24'!G15 -> 3220 | I15: =G15-H15 -> 78 | J15: =I15*12 -> 936 | K15: 300 | L15: ='APR 24'!O15 -> 3380 | M15: =F15+J15+K15+L15 -> 6616 | N15: 3316 | O15: =M15-N15 -> 3300 | Q15: ALLOTED WEF SEP 22. ADV 10000 RENT 2000
A16: 11 | B16: SONU PRAJAPATI | C16: 1/1 | D16: 38443 | E16: 0 | F16: 2200 | G16: 789 | H16: ='APR 24'!G16 -> 729 | I16: =G16-H16 -> 60 | J16: =I16*12 -> 720 | K16: 400 | L16: ='APR 24'!O16 -> 24118 | M16: =F16+J16+K16+L16 -> 27438 | N16: 10000 | O16: =M16-N16 -> 17438 | Q16: ALLOTED WEF APR 22. ADV 10K. RENT 2200
A17: 12 | B17: GOPAL SINGH | C17: 1/2 | D17: 38292 | F17: 3300 | G17: 6562 | H17: ='APR 24'!G17 -> 6493 | I17: =G17-H17 -> 69 | J17: =I17*12 -> 828 | K17: 400 | L17: ='APR 24'!O17 -> -2734 | M17: =F17+J17+K17+L17 -> 1794 | N17: 0 | O17: =M17-N17 -> 1794 | Q17: ALLOTED WEF DEC 23. ADV 8000. LAST RENT 2800
A18: 13 | B18: AJAY DUBEY | C18: 1/3 | D18: 38292 | E18: 500 | F18: 3100 | G18: 5436 | H18: ='APR 24'!G18 -> 5341 | I18: =G18-H18 -> 95 | J18: =I18*12 -> 1140 | K18: 400 | L18: ='APR 24'!O18 -> 10162 | M18: =F18+J18+K18+L18 -> 14802 | N18: 0 | O18: =M18-N18 -> 14802 | Q18: RENT INCREASED WEF JUL 21 FROM 2600, ADV 15000
A19: 14 | B19: ANIL SHARMA | C19: 1/4 | D19: 38292 | E19: 500 | F19: 1000 | G19: 3746 | H19: ='APR 24'!G19 -> 3730 | I19: =G19-H19 -> 16 | J19: =I19*12 -> 192 | K19: 0 | L19: ='APR 24'!O19 -> 0 | M19: =F19+J19+K19+L19 -> 1192 | N19: 1200 | O19: =M19-N19 -> -8 | Q19: ADV 15K.19--5-24. RENT 3000
A20: 15 | B20: VACANT | C20: 1/5 | D20: 37469 | E20: 500 | F20: 0 | G20: 4232 | H20: ='APR 24'!G20 -> 4232 | I20: =G20-H20 -> 0 | J20: =I20*12 -> 0 | K20: 0 | L20: ='APR 24'!O20 -> 0 | M20: =F20+J20+K20+L20 -> 0 | N20: 0 | O20: =M20-N20 -> 0 | Q20: VACANT WEF NOV 2023
A21: 16 | B21: SHAILENDRA PANDEY | C21: 1/6 | D21: 37681 | E21: 500 | F21: 3000 | G21: 3020 | H21: ='APR 24'!G21 -> 2947 | I21: =G21-H21 -> 73 | J21: =I21*12 -> 876 | K21: 400 | L21: ='APR 24'!O21 -> 26778 | M21: =F21+J21+K21+L21 -> 31054 | N21: 0 | O21: =M21-N21 -> 31054 | Q21: RENT INCREASED WEF MAR 21 FROM 2300. ADV 10000
A22: 17 | B22: BIRENDAR YADAV | C22: 2/1 | D22: 38292 | E22: 500 | F22: 2800 | G22: 466 | H22: ='APR 24'!G22 -> 424 | I22: =G22-H22 -> 42 | J22: =I22*12 -> 504 | K22: 400 | L22: ='APR 24'!O22 -> 43564 | M22: =F22+J22+K22+L22 -> 47268 | N22: 5000 | O22: =M22-N22 -> 42268 | Q22: RENT INCREASED WEF DEC 22 FROM 2200. ADV NIL
A23: 18 | B23: HARI SHANKER SHUKLA | C23: 2/2 | D23: 38292 | E23: 500 | F23: 2700 | G23: 851 | H23: ='APR 24'!G23 -> 843 | I23: =G23-H23 -> 8 | J23: =I23*12 -> 96 | K23: 400 | L23: ='APR 24'!O23 -> 8738 | M23: =F23+J23+K23+L23 -> 11934 | N23: 0 | O23: =M23-N23 -> 11934 | Q23: RENT INCRESED WEF JUL 21 FROM 2200. ADV 10000
A24: 19 | B24: SHIV SHANKER PANDEY | C24: 2/3 | D24: 37681 | E24: 500 | F24: 2800 | G24: 5270 | H24: ='APR 24'!G24 -> 5243 | I24: =G24-H24 -> 27 | J24: =I24*12 -> 324 | K24: 400 | L24: ='APR 24'!O24 -> -2 | M24: =F24+J24+K24+L24 -> 3522 | N24: 3512 | O24: =M24-N24 -> 10 | Q24: REALLOTED WEF DEC 22. RENT 2800. ADV NIL
A25: 20 | B25: PRAKASH PANDEY | C25: 2/4 | D25: 37681 | E25: 0 | F25: 2800 | G25: 704 | H25: ='APR 24'!G25 -> 634 | I25: =G25-H25 -> 70 | J25: =I25*12 -> 840 | K25: 400 | L25: ='APR 24'!O25 -> 7304 | M25: =F25+J25+K25+L25 -> 11344 | N25: 0 | O25: =M25-N25 -> 11344 | Q25: ALLOTED FROM DEC 23. ADV NIL. RENT 2800
A26: 21 | B26: VACANT | C26: 2/5 | D26: 37681 | E26: 500 | F26: 0 | G26: 3254 | H26: ='APR 24'!G26 -> 3254 | I26: =G26-H26 -> 0 | J26: =I26*12 -> 0 | K26: 0 | L26: ='APR 24'!O26 -> 0 | M26: =F26+J26+K26+L26 -> 0 | N26: 0 | O26: =M26-N26 -> 0 | Q26: VACATED WEF NOV 23.
A27: 22 | B27: SUNIL MONDAL | C27: 2/6 | D27: 37681 | E27: 0 | F27: 3600 | G27: 4476 | H27: ='APR 24'!G27 -> 4335 | I27: =G27-H27 -> 141 | J27: =I27*12 -> 1692 | K27: 400 | L27: ='APR 24'!O27 -> 64958 | M27: =F27+J27+K27+L27 -> 70650 | N27: 20000 | O27: =M27-N27 -> 50650 | Q27: REALLOTED WEF DEC 23. LAST RENT 3300. ADV 10K
C28: TOTAL | E28: =SUM(E6:E27) -> 7000 | F28: =SUM(F6:F27) -> 45200 | I28: =SUM(I6:I27) -> 1018 | J28: =SUM(J6:J27) -> 12216 | K28: =SUM(K6:K27) -> 6300 | L28: =SUM(L6:L27) -> 227826 | M28: =SUM(M6:M27) -> 291542 | N28: =SUM(N6:N27) -> 58332 | O28: =SUM(O6:O27) -> 233210

Sheet APR 24
A1: SITA DEVI PANDEY HOUSING PROJECT
A2: 11/1B/1 GANPAT RAI KHEMKA LANE LILUAH HOWRAH(W. B.) 711204
A3: FOR THE MONTH OF - APR 2024 | U3: 44
A4: SNO | B4: NAME | C4: ROOM | D4: DATE OF | E4: ELECTRIC | F4: MONTHLY | G4: ELECTRIC | K4: MISC | L4: B/F & | M4: TOTAL | N4: AMT | O4: B/F OR | P4: PAYMENT | Q4: REMARKS
C5: NO | D5: ALLOTMENT | E5: SECURITY | F5: RENT | G5: NEW | H5: PREV | I5: T UNIT | J5: AMOUNT | K5: RENT | L5: ADV | M5: AMT DUE | N5: PAID | O5: ADV | P5: DATE
A6: 1 | B6: SUNNY PRAJAPATI | C6: G/1 | D6: 38754 | E6: 0 | F6: 2000 | G6: 1150 | H6: ='MAR 24'!G6 -> 1110 | I6: =G6-H6 -> 40 | J6: =I6*12 -> 480 | K6: 1200 | L6: ='MAR 24'!O6 -> 0 | M6: =F6+J6+K6+L6 -> 3680 | N6: 0 | O6: =M6-N6 -> 3680 | Q6: ALLOTED WEF SEP 21. ADV 10000. RENT 2000
A7: 2 | B7: MISHRA JI | C7: G/2 | D7: 37653 | E7: 0 | F7: 2000 | G7: 417 | H7: ='MAR 24'!G7 -> 356 | I7: =G7-H7 -> 61 | J7: =I7*12 -> 732 | K7: 1200 | L7: ='MAR 24'!O7 -> 1000 | M7: =F7+J7+K7+L7 -> 4932 | N7: 3000 | O7: =M7-N7 -> 1932 | Q7: ALLLTED WEF SEP 23. ADV 5K RENT 2000.
A8: 3 | B8: PANKAJ PATEL | C8: G/3 | D8: 37895 | E8: 0 | F8: 2000 | G8: 4308 | H8: ='MAR 24'!G8 -> 4303 | I8: =G8-H8 -> 5 | J8: =I8*12 -> 60 | K8: 1200 | L8: ='MAR 24'!O8 -> 18710 | M8: =F8+J8+K8+L8 -> 21970 | N8: 5000 | O8: =M8-N8 -> 16970 | Q8: ALLOTED WEF JUL 21. ADV 5K, RENT 2000.
A9: 4 | B9: BADRI MANDAL | C9: G/4 | D9: 38292 | E9: 500 | F9: 2000 | G9: 4197 | H9: ='MAR 24'!G9 -> 4161 | I9: =G9-H9 -> 36 | J9: =I9*12 -> 432 | K9: 1200 | L9: ='MAR 24'!O9 -> 4958 | M9: =F9+J9+K9+L9 -> 8590 | N9: 0 | O9: =M9-N9 -> 8590 | Q9: ALLOTED WEF 15 DEC 2022. RENT 2000. ADV 5000
A10: 5 | B10: NEW | C10: G/5 | F10: 2000 | G10: 4125 | H10: ='MAR 24'!G10 -> 4067 | I10: =G10-H10 -> 58 | J10: =I10*12 -> 696 | K10: 1200 | L10: ='MAR 24'!O10 -> 32 | M10: =F10+J10+K10+L10 -> 3928 | N10: 3430 | O10: =M10-N10 -> 498 | Q10: ALLOTED WEF SEP 23. ADV 5K. RENT 2K
A11: 6 | B11: VACANT | C11: G/6 | D11: 37667 | E11: 500 | F11: 0 | G11: 1750 | H11: ='MAR 24'!G11 -> 1728 | I11: =G11-H11 -> 22 | J11: =I11*12 -> 264 | K11: 0 | L11: ='MAR 24'!O11 -> 0 | M11: =F11+J11+K11+L11 -> 264 | N11: 264 | O11: =M11-N11 -> 0 | Q11: VACANT FROM JAN 24
A12: 7 | B12: RAM P SHRESTHA | C12: G/7 | D12: 37773 | E12: 500 | F12: 2000 | G12: 4791 | H12: ='MAR 24'!G12 -> 4764 | I12: =G12-H12 -> 27 | J12: =I12*12 -> 324 | K12: 1200 | L12: ='MAR 24'!O12 -> 0 | M12: =F12+J12+K12+L12 -> 3524 | N12: 0 | O12: =M12-N12 -> 3524 | Q12: ALLOTED WEF SEP 21. ADV 10000. RENT 2000
A13: 8 | B13: AJAY BAG | C13: G/8 | D13: 37469 | E13: 500 | F13: 1800 | G13: 2871 | H13: ='MAR 24'!G13 -> 2816 | I13: =G13-H13 -> 55 | J13: =I13*12 -> 660 | K13: 1200 | L13: ='MAR 24'!O13 -> 11194 | M13: =F13+J13+K13+L13 -> 14854 | N13: 10000 | O13: =M13-N13 -> 4854 | Q13: ALLOTED WEF MAR 22. ADV 10000. RENT 1800
A14: 9 | B14: PRAMOD MANDAL | C14: G/9 | D14: 37347 | E14: 500 | F14: 2100 | G14: 12585 | H14: ='MAR 24'!G14 -> 12548 | I14: =G14-H14 -> 37 | J14: =I14*12 -> 444 | K14: 1200 | L14: ='MAR 24'!O14 -> 2768 | M14: =F14+J14+K14+L14 -> 6512 | N14: 5000 | O14: =M14-N14 -> 1512 | Q14: ALLOTED WEF SEP 22. ADV 10000 RENT 2100 SHIFTJUL 23
A15: 10 | B15: PRAMOD MANDAL | C15: G/10 | D15: 37165 | E15: 500 | F15: 2000 | G15: 3220 | H15: ='MAR 24'!G15 -> 3205 | I15: =G15-H15 -> 15 | J15: =I15*12 -> 180 | K15: 1200 | L15: ='MAR 24'!O15 -> 0 | M15: =F15+J15+K15+L15 -> 3380 | N15: 0 | O15: =M15-N15 -> 3380 | Q15: ALLOTED WEF SEP 22. ADV 10000 RENT 2000
A16: 11 | B16: SONU PRAJAPATI | C16: 1/1 | D16: 38443 | E16: 0 | F16: 2200 | G16: 729 | H16: ='MAR 24'!G16 -> 677 | I16: =G16-H16 -> 52 | J16: =I16*12 -> 624 | K16: 1300 | L16: ='MAR 24'!O16 -> 19994 | M16: =F16+J16+K16+L16 -> 24118 | N16: 0 | O16: =M16-N16 -> 24118 | Q16: ALLOTED WEF APR 22. ADV 10K. RENT 2200
A17: 12 | B17: GOPAL SINGH | C17: 1/2 | D17: 38292 | F17: 3300 | G17: 6493 | H17: ='MAR 24'!G17 -> 6426 | I17: =G17-H17 -> 67 | J17: =I17*12 -> 804 | K17: 1300 | L17: ='MAR 24'!O17 -> 21862 | M17: =F17+J17+K17+L17 -> 27266 | N17: 30000 | O17: =M17-N17 -> -2734 | Q17: ALLOTED WEF DEC 23. ADV 8K. LAST RENT 2800
A18: 13 | B18: AJAY DUBEY | C18: 1/3 | D18: 38292 | E18: 500 | F18: 3100 | G18: 5341 | H18: ='MAR 24'!G18 -> 5275 | I18: =G18-H18 -> 66 | J18: =I18*12 -> 792 | K18: 1300 | L18: ='MAR 24'!O18 -> 44970 | M18: =F18+J18+K18+L18 -> 50162 | N18: 40000 | O18: =M18-N18 -> 10162 | Q18: RENT INCREASED WEF JUL 21 FROM 2600, ADV 15000
A19: 14 | B19: VACANT | C19: 1/4 | D19: 38292 | E19: 500 | F19: 0 | G19: 3730 | H19: ='MAR 24'!G19 -> 3730 | I19: =G19-H19 -> 0 | J19: =I19*12 -> 0 | K19: 0 | L19: ='MAR 24'!O19 -> 0 | M19: =F19+J19+K19+L19 -> 0 | N19: 0 | O19: =M19-N19 -> 0 | Q19: VACATED WEF MAR 24.
A20: 15 | B20: VACANT | C20: 1/5 | D20: 37469 | E20: 500 | F20: 0 | G20: 4232 | H20: ='MAR 24'!G20 -> 4232 | I20: =G20-H20 -> 0 | J20: =I20*12 -> 0 | K20: 0 | L20: ='MAR 24'!O20 -> 0 | M20: =F20+J20+K20+L20 -> 0 | N20: 0 | O20: =M20-N20 -> 0 | Q20: VACANT WEF NOV 2023
A21: 16 | B21: SHAILENDRA PANDEY | C21: 1/6 | D21: 37681 | E21: 500 | F21: 3000 | G21: 2947 | H21: ='MAR 24'!G21 -> 2882 | I21: =G21-H21 -> 65 | J21: =I21*12 -> 780 | K21: 1300 | L21: ='MAR 24'!O21 -> 21698 | M21: =F21+J21+K21+L21 -> 26778 | N21: 0 | O21: =M21-N21 -> 26778 | Q21: RENT INCREASED WEF MAR 21 FROM 2300. ADV 10000
A22: 17 | B22: BIRENDAR YADAV | C22: 2/1 | D22: 38292 | E22: 500 | F22: 2800 | G22: 424 | H22: ='MAR 24'!G22 -> 400 | I22: =G22-H22 -> 24 | J22: =I22*12 -> 288 | K22: 1300 | L22: ='MAR 24'!O22 -> 39176 | M22: =F22+J22+K22+L22 -> 43564 | N22: 0 | O22: =M22-N22 -> 43564 | Q22: RENT INCREASED WEF DEC 22 FROM 2200. ADV NIL
A23: 18 | B23: HARI SHANKER SHUKLA | C23: 2/2 | D23: 38292 | E23: 500 | F23: 2700 | G23: 843 | H23: ='MAR 24'!G23 -> 802 | I23: =G23-H23 -> 41 | J23: =I23*12 -> 492 | K23: 1300 | L23: ='MAR 24'!O23 -> 4246 | M23: =F23+J23+K23+L23 -> 8738 | N23: 0 | O23: =M23-N23 -> 8738 | Q23: RENT INCRESED WEF JUL 21 FROM 2200. ADV 10000
A24: 19 | B24: SHIV SHANKER PANDEY | C24: 2/3 | D24: 37681 | E24: 500 | F24: 2800 | G24: 5243 | H24: ='MAR 24'!G24 -> 5214 | I24: =G24-H24 -> 29 | J24: =I24*12 -> 348 | K24: 300 | L24: ='MAR 24'!O24 -> 0 | M24: =F24+J24+K24+L24 -> 3448 | N24: 3450 | O24: =M24-N24 -> -2 | Q24: REALLOTED WEF DEC 22. RENT 2800. ADV NIL
A25: 20 | B25: PRAKASH PANDEY | C25: 2/4 | D25: 37681 | E25: 0 | F25: 2800 | G25: 634 | H25: ='MAR 24'!G25 -> 625 | I25: =G25-H25 -> 9 | J25: =I25*12 -> 108 | K25: 1300 | L25: ='MAR 24'!O25 -> 8096 | M25: =F25+J25+K25+L25 -> 12304 | N25: 5000 | O25: =M25-N25 -> 7304 | Q25: TEMPORARY FOR 1 MTH
A26: 21 | B26: VACANT | C26: 2/5 | D26: 37681 | E26: 500 | F26: 0 | G26: 3254 | H26: ='MAR 24'!G26 -> 3254 | I26: =G26-H26 -> 0 | J26: =I26*12 -> 0 | K26: 0 | L26: ='MAR 24'!O26 -> 0 | M26: =F26+J26+K26+L26 -> 0 | N26: 0 | O26: =M26-N26 -> 0 | Q26: VACATED WEF NOV 23.
A27: 22 | B27: SUNIL MONDAL | C27: 2/6 | D27: 37681 | E27: 0 | F27: 3600 | G27: 4335 | H27: ='MAR 24'!G27 -> 4209 | I27: =G27-H27 -> 126 | J27: =I27*12 -> 1512 | K27: 1300 | L27: ='MAR 24'!O27 -> 58546 | M27: =F27+J27+K27+L27 -> 64958 | N27: 0 | O27: =M27-N27 -> 64958 | Q27: REALLOTED WEF DEC 23. LAST RENT 3300. ADV 10K
C28: TOTAL | E28: =SUM(E6:E27) -> 7000 | F28: =SUM(F6:F27) -> 44200 | I28: =SUM(I6:I27) -> 835 | J28: =SUM(J6:J27) -> 10020 | K28: =SUM(K6:K27) -> 21500 | L28: =SUM(L6:L27) -> 257250 | M28: =SUM(M6:M27) -> 332970 | N28: =SUM(N6:N27) -> 105144 | O28: =SUM(O6:O27) -> 227826

Sheet MAR 24
A1: SITA DEVI PANDEY HOUSING PROJECT
A2: 11/1B/1 GANPAT RAI KHEMKA LANE LILUAH HOWRAH(W. B.) 711204
A3: FOR THE MONTH OF - MAR 2024 | U3: 44
A4: SNO | B4: NAME | C4: ROOM | D4: DATE OF | E4: ELECTRIC | F4: MONTHLY | G4: ELECTRIC | K4: MISC | L4: B/F & | M4: TOTAL | N4: AMT | O4: B/F OR | P4: PAYMENT | Q4: REMARKS
C5: NO | D5: ALLOTMENT | E5: SECURITY | F5: RENT | G5: NEW | H5: PREV | I5: T UNIT | J5: AMOUNT | K5: RENT | L5: ADV | M5: AMT DUE | N5: PAID | O5: ADV | P5: DATE
A6: 1 | B6: SUNNY PRAJAPATI | C6: G/1 | D6: 38754 | E6: 0 | F6: 2000 | G6: 1110 | H6: ='FEB 24'!G6 -> 1092 | I6: =G6-H6 -> 18 | J6: =I6*12 -> 216 | K6: 200 | L6: ='FEB 24'!O6 -> 0 | M6: =F6+J6+K6+L6 -> 2416 | N6: 2416 | O6: =M6-N6 -> 0 | Q6: ALLOTED WEF SEP 21. ADV 10000. RENT 2000
A7: 2 | B7: MISHRA JI | C7: G/2 | D7: 37653 | E7: 0 | F7: 2000 | G7: 356 | H7: ='FEB 24'!G7 -> 347 | I7: =G7-H7 -> 9 | J7: =I7*12 -> 108 | K7: 200 | L7: ='FEB 24'!O7 -> 1050 | M7: =F7+J7+K7+L7 -> 3358 | N7: 2358 | O7: =M7-N7 -> 1000 | Q7: ALLLTED WEF SEP 23. ADV 5K RENT 2000.
A8: 3 | B8: PANKAJ PATEL | C8: G/3 | D8: 37895 | E8: 0 | F8: 2000 | G8: 4303 | H8: ='FEB 24'!G8 -> 4287 | I8: =G8-H8 -> 16 | J8: =I8*12 -> 192 | K8: 200 | L8: ='FEB 24'!O8 -> 16318 | M8: =F8+J8+K8+L8 -> 18710 | N8: 0 | O8: =M8-N8 -> 18710 | Q8: ALLOTED WEF JUL 21. ADV 5K, RENT 2000.
A9: 4 | B9: BADRI MANDAL | C9: G/4 | D9: 38292 | E9: 500 | F9: 2000 | G9: 4161 | H9: ='FEB 24'!G9 -> 4138 | I9: =G9-H9 -> 23 | J9: =I9*12 -> 276 | K9: 200 | L9: ='FEB 24'!O9 -> 2482 | M9: =F9+J9+K9+L9 -> 4958 | N9: 0 | O9: =M9-N9 -> 4958 | Q9: ALLOTED WEF 15 DEC 2022. RENT 2000. ADV 5000
A10: 5 | B10: NEW | C10: G/5 | F10: 2000 | G10: 4067 | H10: ='FEB 24'!G10 -> 4040 | I10: =G10-H10 -> 27 | J10: =I10*12 -> 324 | K10: 200 | L10: ='FEB 24'!O10 -> -42 | M10: =F10+J10+K10+L10 -> 2482 | N10: 2450 | O10: =M10-N10 -> 32 | Q10: ALLOTED WEF SEP 23. ADV 5K. RENT 2K
A11: 6 | B11: VACANT | C11: G/6 | D11: 37667 | E11: 500 | F11: 0 | G11: 1728 | H11: ='FEB 24'!G11 -> 1728 | I11: =G11-H11 -> 0 | J11: =I11*12 -> 0 | K11: 0 | L11: ='FEB 24'!O11 -> 0 | M11: =F11+J11+K11+L11 -> 0 | N11: 0 | O11: =M11-N11 -> 0 | Q11: VACANT FROM JAN 24
A12: 7 | B12: RAM P SHRESTHA | C12: G/7 | D12: 37773 | E12: 500 | F12: 2000 | G12: 4764 | H12: ='FEB 24'!G12 -> 4753 | I12: =G12-H12 -> 11 | J12: =I12*12 -> 132 | K12: 200 | L12: ='FEB 24'!O12 -> 0 | M12: =F12+J12+K12+L12 -> 2332 | N12: 2332 | O12: =M12-N12 -> 0 | Q12: ALLOTED WEF SEP 21. ADV 10000. RENT 2000
A13: 8 | B13: AJAY BAG | C13: G/8 | D13: 37469 | E13: 500 | F13: 1800 | G13: 2816 | H13: ='FEB 24'!G13 -> 2793 | I13: =G13-H13 -> 23 | J13: =I13*12 -> 276 | K13: 200 | L13: ='FEB 24'!O13 -> 8918 | M13: =F13+J13+K13+L13 -> 11194 | N13: 0 | O13: =M13-N13 -> 11194 | Q13: ALLOTED WEF MAR 22. ADV 10000. RENT 1800
A14: 9 | B14: PRAMOD MANDAL | C14: G/9 | D14: 37347 | E14: 500 | F14: 2100 | G14: 12548 | H14: ='FEB 24'!G14 -> 12509 | I14: =G14-H14 -> 39 | J14: =I14*12 -> 468 | K14: 200 | L14: ='FEB 24'!O14 -> 0 | M14: =F14+J14+K14+L14 -> 2768 | N14: 0 | O14: =M14-N14 -> 2768 | Q14: ALLOTED WEF SEP 22. ADV 10000 RENT 2100 SHIFTJUL 23
A15: 10 | B15: PRAMOD MANDAL | C15: G/10 | D15: 37165 | E15: 500 | F15: 2000 | G15: 3205 | H15: ='FEB 24'!G15 -> 3185 | I15: =G15-H15 -> 20 | J15: =I15*12 -> 240 | K15: 200 | L15: ='FEB 24'!O15 -> 0 | M15: =F15+J15+K15+L15 -> 2440 | N15: 2440 | O15: =M15-N15 -> 0 | Q15: ALLOTED WEF SEP 22. ADV 10000 RENT 2000
A16: 11 | B16: SONU PRAJAPATI | C16: 1/1 | D16: 38443 | E16: 0 | F16: 2200 | G16: 677 | H16: ='FEB 24'!G16 -> 604 | I16: =G16-H16 -> 73 | J16: =I16*12 -> 876 | K16: 300 | L16: ='FEB 24'!O16 -> 26618 | M16: =F16+J16+K16+L16 -> 29994 | N16: 10000 | O16: =M16-N16 -> 19994 | Q16: ALLOTED WEF APR 22. ADV 10K. RENT 2200
A17: 12 | B17: GOPAL SINGH | C17: 1/2 | D17: 38292 | F17: 3300 | G17: 6426 | H17: ='FEB 24'!G17 -> 6373 | I17: =G17-H17 -> 53 | J17: =I17*12 -> 636 | K17: 300 | L17: ='FEB 24'!O17 -> 17626 | M17: =F17+J17+K17+L17 -> 21862 | N17: 0 | O17: =M17-N17 -> 21862 | Q17: ALLOTED WEF DEC 23. ADV 8000. LAST RENT 2800
A18: 13 | B18: AJAY DUBEY | C18: 1/3 | D18: 38292 | E18: 500 | F18: 3100 | G18: 5275 | H18: ='FEB 24'!G18 -> 5213 | I18: =G18-H18 -> 62 | J18: =I18*12 -> 744 | K18: 300 | L18: ='FEB 24'!O18 -> 40826 | M18: =F18+J18+K18+L18 -> 44970 | N18: 0 | O18: =M18-N18 -> 44970 | Q18: RENT INCREASED WEF JUL 21 FROM 2600, ADV 15000
A19: 14 | B19: VACANT | C19: 1/4 | D19: 38292 | E19: 500 | F19: 0 | G19: 3730 | H19: ='FEB 24'!G19 -> 3730 | I19: =G19-H19 -> 0 | J19: =I19*12 -> 0 | K19: 0 | L19: ='FEB 24'!O19 -> 0 | M19: =F19+J19+K19+L19 -> 0 | N19: 0 | O19: =M19-N19 -> 0 | Q19: VACATED WEF MAR 24.
A20: 15 | B20: VACANT | C20: 1/5 | D20: 37469 | E20: 500 | F20: 0 | G20: 4232 | H20: ='FEB 24'!G20 -> 4232 | I20: =G20-H20 -> 0 | J20: =I20*12 -> 0 | K20: 0 | L20: ='FEB 24'!O20 -> 0 | M20: =F20+J20+K20+L20 -> 0 | N20: 0 | O20: =M20-N20 -> 0 | Q20: VACANT WEF NOV 2023
A21: 16 | B21: SHAILENDRA PANDEY | C21: 1/6 | D21: 37681 | E21: 500 | F21: 3000 | G21: 2882 | H21: ='FEB 24'!G21 -> 2839 | I21: =G21-H21 -> 43 | J21: =I21*12 -> 516 | K21: 300 | L21: ='FEB 24'!O21 -> 22882 | M21: =F21+J21+K21+L21 -> 26698 | N21: 5000 | O21: =M21-N21 -> 21698 | Q21: RENT INCREASED WEF MAR 21 FROM 2300. ADV 10000
A22: 17 | B22: BIRENDAR YADAV | C22: 2/1 | D22: 38292 | E22: 500 | F22: 2800 | G22: 400 | H22: ='FEB 24'!G22 -> 365 | I22: =G22-H22 -> 35 | J22: =I22*12 -> 420 | K22: 300 | L22: ='FEB 24'!O22 -> 35656 | M22: =F22+J22+K22+L22 -> 39176 | N22: 0 | O22: =M22-N22 -> 39176 | Q22: RENT INCREASED WEF DEC 22 FROM 2200. ADV NIL
A23: 18 | B23: HARI SHANKER SHUKLA | C23: 2/2 | D23: 38292 | E23: 500 | F23: 2700 | G23: 802 | H23: ='FEB 24'!G23 -> 801 | I23: =G23-H23 -> 1 | J23: =I23*12 -> 12 | K23: 300 | L23: ='FEB 24'!O23 -> 15234 | M23: =F23+J23+K23+L23 -> 18246 | N23: 14000 | O23: =M23-N23 -> 4246 | Q23: RENT INCRESED WEF JUL 21 FROM 2200. ADV 10000
A24: 19 | B24: SHIV SHANKER PANDEY | C24: 2/3 | D24: 37681 | E24: 500 | F24: 2800 | G24: 5214 | H24: ='FEB 24'!G24 -> 5186 | I24: =G24-H24 -> 28 | J24: =I24*12 -> 336 | K24: 300 | L24: ='FEB 24'!O24 -> 0 | M24: =F24+J24+K24+L24 -> 3436 | N24: 3436 | O24: =M24-N24 -> 0 | Q24: REALLOTED WEF DEC 22. RENT 2800. ADV NIL
A25: 20 | B25: PRAKASH PANDEY | C25: 2/4 | D25: 37681 | E25: 0 | F25: 2800 | G25: 625 | H25: ='FEB 24'!G25 -> 608 | I25: =G25-H25 -> 17 | J25: =I25*12 -> 204 | K25: 300 | L25: ='FEB 24'!O25 -> 4792 | M25: =F25+J25+K25+L25 -> 8096 | N25: 0 | O25: =M25-N25 -> 8096 | Q25: TEMPORARY FOR 1 MTH
A26: 21 | B26: VACANT | C26: 2/5 | D26: 37681 | E26: 500 | F26: 0 | G26: 3254 | H26: ='FEB 24'!G26 -> 3254 | I26: =G26-H26 -> 0 | J26: =I26*12 -> 0 | K26: 0 | L26: ='FEB 24'!O26 -> 0 | M26: =F26+J26+K26+L26 -> 0 | N26: 0 | O26: =M26-N26 -> 0 | Q26: VACATED WEF NOV 23.
A27: 22 | B27: SUNIL MONDAL | C27: 2/6 | D27: 37681 | E27: 0 | F27: 3600 | G27: 4209 | H27: ='FEB 24'!G27 -> 4127 | I27: =G27-H27 -> 82 | J27: =I27*12 -> 984 | K27: 300 | L27: ='FEB 24'!O27 -> 53662 | M27: =F27+J27+K27+L27 -> 58546 | N27: 0 | O27: =M27-N27 -> 58546 | Q27: REALLOTED WEF DEC 23. LAST RENT 3300. ADV 10K
C28: TOTAL | E28: =SUM(E6:E27) -> 7000 | F28: =SUM(F6:F27) -> 44200 | I28: =SUM(I6:I27) -> 580 | J28: =SUM(J6:J27) -> 6960 | K28: =SUM(K6:K27) -> 4500 | L28: =SUM(L6:L27) -> 246022 | M28: =SUM(M6:M27) -> 301682 | N28: =SUM(N6:N27) -> 44432 | O28: =SUM(O6:O27) -> 257250

Sheet FEB 24
A1: SITA DEVI PANDEY HOUSING PROJECT
A2: 11/1B/1 GANPAT RAI KHEMKA LANE LILUAH HOWRAH(W. B.) 711204
A3: FOR THE MONTH OF - FEB 2024 | U3: 44
A4: SNO | B4: NAME | C4: ROOM | D4: DATE OF | E4: ELECTRIC | F4: MONTHLY | G4: ELECTRIC | K4: MISC | L4: B/F & | M4: TOTAL | N4: AMT | O4: B/F OR | P4: PAYMENT | Q4: REMARKS
C5: NO | D5: ALLOTMENT | E5: SECURITY | F5: RENT | G5: NEW | H5: PREV | I5: T UNIT | J5: AMOUNT | K5: RENT | L5: ADV | M5: AMT DUE | N5: PAID | O5: ADV | P5: DATE
A6: 1 | B6: SUNNY PRAJAPATI | C6: G/1 | D6: 38754 | E6: 0 | F6: 2000 | G6: 1092 | H6: ='JAN 24'!G6 -> 1083 | I6: =G6-H6 -> 9 | J6: =I6*12 -> 108 | K6: 300 | L6: ='JAN 24'!O6 -> 0 | M6: =F6+J6+K6+L6 -> 2408 | N6: 2408 | O6: =M6-N6 -> 0 | Q6: ALLOTED WEF SEP 21. ADV 10000. RENT 2000
A7: 2 | B7: MISHRA JI | C7: G/2 | D7: 37653 | E7: 0 | F7: 2000 | G7: 347 | H7: ='JAN 24'!G7 -> 333 | I7: =G7-H7 -> 14 | J7: =I7*12 -> 168 | K7: 300 | L7: ='JAN 24'!O7 -> 582 | M7: =F7+J7+K7+L7 -> 3050 | N7: 2000 | O7: =M7-N7 -> 1050 | Q7: ALLLTED WEF SEP 23. ADV 5K RENT 2000.
A8: 3 | B8: PANKAJ PATEL | C8: G/3 | D8: 37895 | E8: 0 | F8: 2000 | G8: 4287 | H8: ='JAN 24'!G8 -> 4286 | I8: =G8-H8 -> 1 | J8: =I8*12 -> 12 | K8: 300 | L8: ='JAN 24'!O8 -> 14006 | M8: =F8+J8+K8+L8 -> 16318 | N8: 0 | O8: =M8-N8 -> 16318 | Q8: ALLOTED WEF JUL 21. ADV 5K, RENT 2000.
A9: 4 | B9: BADRI MANDAL | C9: G/4 | D9: 38292 | E9: 500 | F9: 2000 | G9: 4138 | H9: 4128 | I9: =G9-H9 -> 10 | J9: =I9*12 -> 120 | K9: 300 | L9: ='JAN 24'!O9 -> 62 | M9: =F9+J9+K9+L9 -> 2482 | N9: 0 | O9: =M9-N9 -> 2482 | Q9: ALLOTED WEF 15 DEC 2022. RENT 2000. ADV 5000
A10: 5 | B10: NEW | C10: G/5 | F10: 2000 | G10: 4040 | H10: ='JAN 24'!G10 -> 4035 | I10: =G10-H10 -> 5 | J10: =I10*12 -> 60 | K10: 300 | L10: ='JAN 24'!O10 -> 48 | M10: =F10+J10+K10+L10 -> 2408 | N10: 2450 | O10: =M10-N10 -> -42 | Q10: ALLOTED WEF SEP 23. ADV 5K. RENT 2K
A11: 6 | B11: BLANK | C11: G/6 | D11: 37667 | E11: 500 | F11: 0 | G11: 1728 | H11: ='JAN 24'!G11 -> 1728 | I11: =G11-H11 -> 0 | J11: =I11*12 -> 0 | K11: 0 | L11: ='JAN 24'!O11 -> 0 | M11: 0 | N11: 0 | O11: =M11-N11 -> 0 | Q11: VACANTWEF JAN 24
A12: 7 | B12: RAM P SHRESTHA | C12: G/7 | D12: 37773 | E12: 500 | F12: 2000 | G12: 4753 | H12: ='JAN 24'!G12 -> 4750 | I12: =G12-H12 -> 3 | J12: =I12*12 -> 36 | K12: 300 | L12: ='JAN 24'!O12 -> 2272 | M12: =F12+J12+K12+L12 -> 4608 | N12: 4608 | O12: =M12-N12 -> 0 | Q12: ALLOTED WEF SEP 21. ADV 10000. RENT 2000
A13: 8 | B13: AJAY BAG | C13: G/8 | D13: 37469 | E13: 500 | F13: 1800 | G13: 2793 | H13: ='JAN 24'!G13 -> 2788 | I13: =G13-H13 -> 5 | J13: =I13*12 -> 60 | K13: 300 | L13: ='JAN 24'!O13 -> 6758 | M13: =F13+J13+K13+L13 -> 8918 | N13: 0 | O13: =M13-N13 -> 8918 | Q13: ALLOTED WEF MAR 22. ADV 10000. RENT 1800
A14: 9 | B14: PRAMOD MANDAL | C14: G/9 | D14: 37347 | E14: 500 | F14: 2100 | G14: 12509 | H14: ='JAN 24'!G14 -> 12492 | I14: =G14-H14 -> 17 | J14: =I14*12 -> 204 | K14: 300 | L14: ='JAN 24'!O14 -> 0 | M14: =F14+J14+K14+L14 -> 2604 | N14: 2604 | O14: =M14-N14 -> 0 | Q14: ALLOTED WEF SEP 22. ADV 10000 RENT 2100 SHIFTJUL 23
A15: 10 | B15: PRAMOD MANDAL | C15: G/10 | D15: 37165 | E15: 500 | F15: 2000 | G15: 3185 | H15: ='JAN 24'!G15 -> 3177 | I15: =G15-H15 -> 8 | J15: =I15*12 -> 96 | K15: 300 | L15: ='JAN 24'!O15 -> -2 | M15: =F15+J15+K15+L15 -> 2394 | N15: 2394 | O15: =M15-N15 -> 0 | Q15: ALLOTED WEF SEP 22. ADV 10000 RENT 2000
A16: 11 | B16: SONU PRAJAPATI | C16: 1/1 | D16: 38443 | E16: 0 | F16: 2200 | G16: 604 | H16: ='JAN 24'!G16 -> 572 | I16: =G16-H16 -> 32 | J16: =I16*12 -> 384 | K16: 300 | L16: ='JAN 24'!O16 -> 23734 | M16: =F16+J16+K16+L16 -> 26618 | N16: 0 | O16: =M16-N16 -> 26618 | Q16: ALLOTED WEF APR 22. ADV 10K. RENT 2200
A17: 12 | B17: GOPAL SINGH | C17: 1/2 | D17: 38292 | F17: 3300 | G17: 6373 | H17: ='JAN 24'!G17 -> 6322 | I17: =G17-H17 -> 51 | J17: =I17*12 -> 612 | K17: 300 | L17: ='JAN 24'!O17 -> 23414 | M17: =F17+J17+K17+L17 -> 27626 | N17: 10000 | O17: =M17-N17 -> 17626 | Q17: ALLOTED WEF DEC 23. ADV 8000. LAST RENT 2800
A18: 13 | B18: AJAY DUBEY | C18: 1/3 | D18: 38292 | E18: 500 | F18: 3100 | G18: 5213 | H18: ='JAN 24'!G18 -> 5178 | I18: =G18-H18 -> 35 | J18: =I18*12 -> 420 | K18: 300 | L18: ='JAN 24'!O18 -> 37006 | M18: =F18+J18+K18+L18 -> 40826 | N18: 0 | O18: =M18-N18 -> 40826 | Q18: RENT INCREASED WEF JUL 21 FROM 2600, ADV 15000
A19: 14 | B19: AMLESH RAM | C19: 1/4 | D19: 38292 | E19: 500 | F19: 3000 | G19: 3730 | H19: ='JAN 24'!G19 -> 3730 | I19: =G19-H19 -> 0 | J19: =I19*12 -> 0 | K19: 300 | L19: ='JAN 24'!O19 -> 6780 | M19: =F19+J19+K19+L19 -> 10080 | N19: 10080 | O19: =M19-N19 -> 0 | Q19: VACATED WEF MAR 24. ALL DUES CLEAR
A20: 15 | B20: VACANT | C20: 1/5 | D20: 37469 | E20: 500 | F20: 0 | G20: 4232 | H20: ='JAN 24'!G20 -> 4232 | I20: =G20-H20 -> 0 | J20: =I20*12 -> 0 | K20: 0 | L20: 0 | M20: =F20+J20+K20+L20 -> 0 | N20: 0 | O20: =M20-N20 -> 0 | Q20: VACANT WEF NOV 2023
A21: 16 | B21: SHAILENDRA PANDEY | C21: 1/6 | D21: 37681 | E21: 500 | F21: 3000 | G21: 2839 | H21: ='JAN 24'!G21 -> 2815 | I21: =G21-H21 -> 24 | J21: =I21*12 -> 288 | K21: 300 | L21: ='JAN 24'!O21 -> 19294 | M21: =F21+J21+K21+L21 -> 22882 | N21: 0 | O21: =M21-N21 -> 22882 | Q21: RENT INCREASED WEF MAR 21 FROM 2300. ADV 10000
A22: 17 | B22: BIRENDAR YADAV | C22: 2/1 | D22: 38292 | E22: 500 | F22: 2800 | G22: 365 | H22: ='JAN 24'!G22 -> 345 | I22: =G22-H22 -> 20 | J22: =I22*12 -> 240 | K22: 300 | L22: ='JAN 24'!O22 -> 37316 | M22: =F22+J22+K22+L22 -> 40656 | N22: 5000 | O22: =M22-N22 -> 35656 | Q22: RENT INCREASED WEF DEC 22 FROM 2200. ADV NIL
A23: 18 | B23: HARI SHANKER SHUKLA | C23: 2/2 | D23: 38292 | E23: 500 | F23: 2700 | G23: 801 | H23: ='JAN 24'!G23 -> 800 | I23: =G23-H23 -> 1 | J23: =I23*12 -> 12 | K23: 300 | L23: ='JAN 24'!O23 -> 12222 | M23: =F23+J23+K23+L23 -> 15234 | N23: 0 | O23: =M23-N23 -> 15234 | Q23: RENT INCRESED WEF JUL 21 FROM 2200. ADV 10000
A24: 19 | B24: SHIV SHANKER PANDEY | C24: 2/3 | D24: 37681 | E24: 500 | F24: 2800 | G24: 5186 | H24: ='JAN 24'!G24 -> 5170 | I24: =G24-H24 -> 16 | J24: =I24*12 -> 192 | K24: 300 | L24: ='JAN 24'!O24 -> 0 | M24: =F24+J24+K24+L24 -> 3292 | N24: 3292 | O24: =M24-N24 -> 0 | Q24: REALLOTED WEF DEC 22. RENT 2800. ADV NIL
A25: 20 | B25: FUA TEMPORARY | C25: 2/4 | D25: 37681 | E25: 0 | F25: 2800 | G25: 608 | H25: ='JAN 24'!G25 -> 589 | I25: =G25-H25 -> 19 | J25: =I25*12 -> 228 | K25: 300 | L25: ='JAN 24'!O25 -> 6464 | M25: =F25+J25+K25+L25 -> 9792 | N25: 5000 | O25: =M25-N25 -> 4792 | Q25: TEMPORARY FOR 1 MTH
A26: 21 | B26: VACANT | C26: 2/5 | D26: 37681 | E26: 500 | F26: 0 | G26: 3254 | H26: ='JAN 24'!G26 -> 3254 | I26: =G26-H26 -> 0 | J26: =I26*12 -> 0 | K26: 0 | L26: 0 | M26: =F26+J26+K26+L26 -> 0 | N26: 0 | O26: =M26-N26 -> 0 | Q26: VACATED WEF NOV 23. ALL DUES CLEAR
A27: 22 | B27: SUNIL MONDAL | C27: 2/6 | D27: 37681 | E27: 0 | F27: 3600 | G27: 4127 | H27: ='JAN 24'!G27 -> 4075 | I27: =G27-H27 -> 52 | J27: =I27*12 -> 624 | K27: 300 | L27: ='JAN 24'!O27 -> 49138 | M27: =F27+J27+K27+L27 -> 53662 | N27: 0 | O27: =M27-N27 -> 53662 | Q27: REALLOTED WEF DEC 23. LAST RENT 3300. ADV 10K
C28: TOTAL | E28: =SUM(E6:E27) -> 7000 | F28: =SUM(F6:F27) -> 47200 | I28: =SUM(I6:I27) -> 322 | J28: =SUM(J6:J27) -> 3864 | K28: =SUM(K6:K27) -> 5700 | L28: =SUM(L6:L27) -> 239094 | M28: =SUM(M6:M27) -> 295858 | N28: =SUM(N6:N27) -> 49836 | O28: =SUM(O6:O27) -> 246022

Sheet JAN 24
A1: SITA DEVI PANDEY HOUSING PROJECT
A2: 11/1B/1 GANPAT RAI KHEMKA LANE LILUAH HOWRAH(W. B.) 711204
A3: FOR THE MONTH OF - JAN 2024 | U3: 44
A4: SNO | B4: NAME | C4: ROOM | D4: DATE OF | E4: ELECTRIC | F4: MONTHLY | G4: ELECTRIC | K4: MISC | L4: B/F & | M4: TOTAL | N4: AMT | O4: B/F OR | P4: PAYMENT | Q4: REMARKS
C5: NO | D5: ALLOTMENT | E5: SECURITY | F5: RENT | G5: NEW | H5: PREV | I5: T UNIT | J5: AMOUNT | K5: RENT | L5: ADV | M5: AMT DUE | N5: PAID | O5: ADV | P5: DATE
A6: 1 | B6: SUNNY PRAJAPATI | C6: G/1 | D6: 38754 | E6: 0 | F6: 2000 | G6: 1083 | H6: ='DEC 23'!G6 -> 1078 | I6: =G6-H6 -> 5 | J6: =I6*12 -> 60 | K6: 200 | L6: ='DEC 23'!O6 -> 0 | M6: =F6+J6+K6+L6 -> 2260 | N6: 2260 | O6: =M6-N6 -> 0 | Q6: ALLOTED WEF SEP 21. ADV 10000. RENT 2000
A7: 2 | B7: NEW | C7: G/2 | D7: 37653 | E7: 0 | F7: 2000 | G7: 333 | H7: ='DEC 23'!G7 -> 327 | I7: =G7-H7 -> 6 | J7: =I7*12 -> 72 | K7: 200 | L7: ='DEC 23'!O7 -> 310 | M7: =F7+J7+K7+L7 -> 2582 | N7: 2000 | O7: =M7-N7 -> 582 | Q7: ALLLTED WEF SEP 23. ADV 5K RENT 2000.
A8: 3 | B8: PANKAJ PATEL | C8: G/3 | D8: 37895 | E8: 0 | F8: 2000 | G8: 4286 | H8: ='DEC 23'!G8 -> 4284 | I8: =G8-H8 -> 2 | J8: =I8*12 -> 24 | K8: 200 | L8: ='DEC 23'!O8 -> 14782 | M8: =F8+J8+K8+L8 -> 17006 | N8: 3000 | O8: =M8-N8 -> 14006 | Q8: ALLOTED WEF JUL 21. ADV 5K, RENT 2000.
A9: 4 | B9: BADRI MANDAL | C9: G/4 | D9: 38292 | E9: 500 | F9: 2000 | G9: 14128 | H9: ='DEC 23'!G9 -> 14125 | I9: =G9-H9 -> 3 | J9: =I9*12 -> 36 | K9: 200 | L9: ='DEC 23'!O9 -> 7126 | M9: =F9+J9+K9+L9 -> 9362 | N9: 9300 | O9: =M9-N9 -> 62 | Q9: ALLOTED WEF 15 DEC 2022. RENT 2000. ADV 5000
A10: 5 | B10: NEW | C10: G/5 | F10: 2000 | G10: 4035 | H10: ='DEC 23'!G10 -> 4031 | I10: =G10-H10 -> 4 | J10: =I10*12 -> 48 | K10: 200 | L10: ='DEC 23'!O10 -> 0 | M10: =F10+J10+K10+L10 -> 2248 | N10: 2200 | O10: =M10-N10 -> 48 | Q10: ALLOTED WEF SEP 23. ADV 5K. RENT 2K
A11: 6 | B11: BC PATEL | C11: G/6 | D11: 37667 | E11: 500 | F11: 2000 | G11: 1728 | H11: ='DEC 23'!G11 -> 1725 | I11: =G11-H11 -> 3 | J11: =I11*12 -> 36 | K11: 200 | L11: ='DEC 23'!O11 -> 2260 | M11: =F11+J11+K11+L11 -> 4496 | N11: 4496 | O11: =M11-N11 -> 0 | Q11: VACANT WEF 29-02-2024. ALL DUES CLEAR
A12: 7 | B12: RAM P SHRESTHA | C12: G/7 | D12: 37773 | E12: 500 | F12: 2000 | G12: 4750 | H12: ='DEC 23'!G12 -> 4744 | I12: =G12-H12 -> 6 | J12: =I12*12 -> 72 | K12: 200 | L12: ='DEC 23'!O12 -> 0 | M12: =F12+J12+K12+L12 -> 2272 | N12: 0 | O12: =M12-N12 -> 2272 | Q12: ALLOTED WEF SEP 21. ADV 10000. RENT 2000
A13: 8 | B13: AJAY BAG | C13: G/8 | D13: 37469 | E13: 500 | F13: 1800 | G13: 2788 | H13: ='DEC 23'!G13 -> 2781 | I13: =G13-H13 -> 7 | J13: =I13*12 -> 84 | K13: 200 | L13: ='DEC 23'!O13 -> 12674 | M13: =F13+J13+K13+L13 -> 14758 | N13: 8000 | O13: =M13-N13 -> 6758 | Q13: ALLOTED WEF MAR 22. ADV 10000. RENT 1800
A14: 9 | B14: PRAMOD MANDAL | C14: G/9 | D14: 37347 | E14: 500 | F14: 2100 | G14: 12492 | H14: ='DEC 23'!G14 -> 12487 | I14: =G14-H14 -> 5 | J14: =I14*12 -> 60 | K14: 200 | L14: ='DEC 23'!O14 -> -56 | M14: =F14+J14+K14+L14 -> 2304 | N14: 2304 | O14: =M14-N14 -> 0 | Q14: ALLOTED WEF SEP 22. ADV 10000 RENT 2100 SHIFTJUL 23
A15: 10 | B15: PRAMOD MANDAL | C15: G/10 | D15: 37165 | E15: 500 | F15: 2000 | G15: 3177 | H15: ='DEC 23'!G15 -> 3171 | I15: =G15-H15 -> 6 | J15: =I15*12 -> 72 | K15: 200 | L15: ='DEC 23'!O15 -> -4 | M15: =F15+J15+K15+L15 -> 2268 | N15: 2270 | O15: =M15-N15 -> -2 | Q15: ALLOTED WEF SEP 22. ADV 10000 RENT 2000
A16: 11 | B16: SONU PRAJAPATI | C16: 1/1 | D16: 38443 | E16: 0 | F16: 2200 | G16: 572 | H16: ='DEC 23'!G16 -> 567 | I16: =G16-H16 -> 5 | J16: =I16*12 -> 60 | K16: 500 | L16: ='DEC 23'!O16 -> 20974 | M16: =F16+J16+K16+L16 -> 23734 | N16: 0 | O16: =M16-N16 -> 23734 | Q16: ALLOTED WEF APR 22. ADV 10K. RENT 2200
A17: 12 | B17: GOPAL SINGH | C17: 1/2 | D17: 38292 | F17: 3300 | G17: 6322 | H17: ='DEC 23'!G17 -> 6261 | I17: =G17-H17 -> 61 | J17: =I17*12 -> 732 | K17: 500 | L17: ='DEC 23'!O17 -> 26882 | M17: =F17+J17+K17+L17 -> 31414 | N17: 8000 | O17: =M17-N17 -> 23414 | Q17: ALLOTED WEF DEC 23. ADV 8000. LAST RENT 2800
A18: 13 | B18: AJAY DUBEY | C18: 1/3 | D18: 38292 | E18: 500 | F18: 3100 | G18: 5178 | H18: ='DEC 23'!G18 -> 5167 | I18: =G18-H18 -> 11 | J18: =I18*12 -> 132 | K18: 500 | L18: ='DEC 23'!O18 -> 33274 | M18: =F18+J18+K18+L18 -> 37006 | N18: 0 | O18: =M18-N18 -> 37006 | Q18: RENT INCREASED WEF JUL 21 FROM 2600, ADV 15000
A19: 14 | B19: AMLESH RAM | C19: 1/4 | D19: 38292 | E19: 500 | F19: 3000 | G19: 3730 | H19: ='DEC 23'!G19 -> 3728 | I19: =G19-H19 -> 2 | J19: =I19*12 -> 24 | K19: 500 | L19: ='DEC 23'!O19 -> 3256 | M19: =F19+J19+K19+L19 -> 6780 | N19: 0 | O19: =M19-N19 -> 6780 | Q19: SHIFTED FM 2/4 AUG 23 ALLOTED MAR 23 RENT 3K ADV 10K
A20: 15 | B20: VACANT | C20: 1/5 | D20: 37469 | E20: 500 | F20: 0 | G20: 4232 | H20: ='DEC 23'!G20 -> 4231 | I20: =G20-H20 -> 1 | J20: =I20*12 -> 12 | K20: 0 | L20: ='DEC 23'!O20 -> 0 | M20: =F20+J20+K20+L20 -> 12 | N20: 0 | O20: =M20-N20 -> 12 | Q20: VACANT WEF NOV 2023
A21: 16 | B21: SHAILENDRA PANDEY | C21: 1/6 | D21: 37681 | E21: 500 | F21: 3000 | G21: 2815 | H21: ='DEC 23'!G21 -> 2792 | I21: =G21-H21 -> 23 | J21: =I21*12 -> 276 | K21: 500 | L21: ='DEC 23'!O21 -> 15518 | M21: =F21+J21+K21+L21 -> 19294 | N21: 0 | O21: =M21-N21 -> 19294 | Q21: RENT INCREASED WEF MAR 21 FROM 2300. ADV 10000
A22: 17 | B22: BIRENDAR YADAV | C22: 2/1 | D22: 38292 | E22: 500 | F22: 2800 | G22: 345 | H22: ='DEC 23'!G22 -> 337 | I22: =G22-H22 -> 8 | J22: =I22*12 -> 96 | K22: 300 | L22: ='DEC 23'!O22 -> 39120 | M22: =F22+J22+K22+L22 -> 42316 | N22: 5000 | O22: =M22-N22 -> 37316 | Q22: RENT INCREASED WEF DEC 22 FROM 2200. ADV NIL
A23: 18 | B23: HARI SHANKER SHUKLA | C23: 2/2 | D23: 38292 | E23: 500 | F23: 2700 | G23: 800 | H23: ='DEC 23'!G23 -> 800 | I23: =G23-H23 -> 0 | J23: =I23*12 -> 0 | K23: 300 | L23: ='DEC 23'!O23 -> 9222 | M23: =F23+J23+K23+L23 -> 12222 | N23: 0 | O23: =M23-N23 -> 12222 | Q23: RENT INCRESED WEF JUL 21 FROM 2200. ADV 10000
A24: 19 | B24: SHIV SHANKER PANDEY | C24: 2/3 | D24: 37681 | E24: 500 | F24: 2800 | G24: 5170 | H24: ='DEC 23'!G24 -> 5158 | I24: =G24-H24 -> 12 | J24: =I24*12 -> 144 | K24: 300 | L24: ='DEC 23'!O24 -> 0 | M24: =F24+J24+K24+L24 -> 3244 | N24: 3244 | O24: =M24-N24 -> 0 | Q24: REALLOTED WEF DEC 22. RENT 2800. ADV NIL
A25: 20 | B25: FUA TEMPORARY | C25: 2/4 | D25: 37681 | E25: 0 | F25: 2800 | G25: 589 | H25: ='DEC 23'!G25 -> 580 | I25: =G25-H25 -> 9 | J25: =I25*12 -> 108 | K25: 300 | L25: ='DEC 23'!O25 -> 3256 | M25: =F25+J25+K25+L25 -> 6464 | N25: 0 | O25: =M25-N25 -> 6464 | Q25: TEMPORARY FOR 1 MTH
A26: 21 | B26: VACANT | C26: 2/5 | D26: 37681 | E26: 500 | F26: 0 | G26: 3254 | H26: ='DEC 23'!G26 -> 3254 | I26: =G26-H26 -> 0 | J26: =I26*12 -> 0 | K26: 0 | L26: ='DEC 23'!O26 -> 48 | M26: =F26+J26+K26+L26 -> 48 | N26: 0 | O26: =M26-N26 -> 48 | Q26: VACATED WEF NOV 23. ALL DUES CLEAR
A27: 22 | B27: SUNIL MONDAL | C27: 2/6 | D27: 37681 | E27: 0 | F27: 3600 | G27: 4075 | H27: ='DEC 23'!G27 -> 4041 | I27: =G27-H27 -> 34 | J27: =I27*12 -> 408 | K27: 300 | L27: ='DEC 23'!O27 -> 69830 | M27: =F27+J27+K27+L27 -> 74138 | N27: 25000 | O27: =M27-N27 -> 49138 | Q27: REALLOTED WEF DEC 23. LAST RENT 3300. ADV 10K
C28: TOTAL | E28: =SUM(E6:E27) -> 7000 | F28: =SUM(F6:F27) -> 49200 | I28: =SUM(I6:I27) -> 213 | J28: =SUM(J6:J27) -> 2556 | K28: =SUM(K6:K27) -> 6000 | L28: =SUM(L6:L27) -> 258472 | M28: =SUM(M6:M27) -> 316228 | N28: =SUM(N6:N27) -> 77074 | O28: =SUM(O6:O27) -> 239154

Sheet DEC 23
A1: SITA DEVI PANDEY HOUSING PROJECT
A2: 11/1B/1 GANPAT RAI KHEMKA LANE LILUAH HOWRAH(W. B.) 711204
A3: FOR THE MONTH OF - DEC 2023 | U3: 44
A4: SNO | B4: NAME | C4: ROOM | D4: DATE OF | E4: ELECTRIC | F4: MONTHLY | G4: ELECTRIC | K4: MISC | L4: B/F & | M4: TOTAL | N4: AMT | O4: B/F OR | P4: PAYMENT | Q4: REMARKS
C5: NO | D5: ALLOTMENT | E5: SECURITY | F5: RENT | G5: NEW | H5: PREV | I5: T UNIT | J5: AMOUNT | K5: RENT | L5: ADV | M5: AMT DUE | N5: PAID | O5: ADV | P5: DATE
A6: 1 | B6: SUNNY PRAJAPATI | C6: G/1 | D6: 38754 | E6: 0 | F6: 2000 | G6: 1078 | H6: ='NOV 23'!G6 -> 1070 | I6: =G6-H6 -> 8 | J6: =I6*12 -> 96 | K6: 200 | L6: ='NOV 23'!O6 -> -10 | M6: =F6+J6+K6+L6 -> 2286 | N6: 2286 | O6: =M6-N6 -> 0 | Q6: ALLOTED WEF SEP 21. ADV 10000. RENT 2000
A7: 2 | B7: NEW | C7: G/2 | D7: 37653 | E7: 0 | F7: 2000 | G7: 327 | H7: ='NOV 23'!G7 -> 321 | I7: =G7-H7 -> 6 | J7: =I7*12 -> 72 | K7: 200 | L7: ='NOV 23'!O7 -> 438 | M7: =F7+J7+K7+L7 -> 2710 | N7: 2400 | O7: =M7-N7 -> 310 | Q7: ALLLTED WEF SEP 23. ADV 5K RENT 2000.
A8: 3 | B8: PANKAJ PATEL | C8: G/3 | D8: 37895 | E8: 0 | F8: 2000 | G8: 4284 | H8: 4268 | I8: =G8-H8 -> 16 | J8: =I8*12 -> 192 | K8: 200 | L8: ='NOV 23'!O8 -> 17390 | M8: =F8+J8+K8+L8 -> 19782 | N8: 5000 | O8: =M8-N8 -> 14782 | Q8: ALLOTED WEF JUL 21. ADV 5K, RENT 2000.
A9: 4 | B9: BADRI MANDAL | C9: G/4 | D9: 38292 | E9: 500 | F9: 2000 | G9: 14125 | H9: 14107 | I9: =G9-H9 -> 18 | J9: =I9*12 -> 216 | K9: 200 | L9: ='NOV 23'!O9 -> 4710 | M9: =F9+J9+K9+L9 -> 7126 | N9: 0 | O9: =M9-N9 -> 7126 | Q9: ALLOTED WEF 15 DEC 2022. RENT 2000. ADV 5000
A10: 5 | B10: NEW | C10: G/5 | F10: 2000 | G10: 4031 | H10: ='NOV 23'!G10 -> 4026 | I10: =G10-H10 -> 5 | J10: =I10*12 -> 60 | K10: 200 | L10: ='NOV 23'!O10 -> 0 | M10: =F10+J10+K10+L10 -> 2260 | N10: 2260 | O10: =M10-N10 -> 0 | Q10: ALLOTED WEF SEP 23. ADV 5K. RENT 2K
A11: 6 | B11: BC PATEL | C11: G/6 | D11: 37667 | E11: 500 | F11: 2000 | G11: 1725 | H11: 1720 | I11: =G11-H11 -> 5 | J11: =I11*12 -> 60 | K11: 200 | L11: ='NOV 23'!O11 -> 0 | M11: =F11+J11+K11+L11 -> 2260 | N11: 0 | O11: =M11-N11 -> 2260 | Q11: ALLOTED WEF JAN 22. ADV NIL. RENT 2000
A12: 7 | B12: RAM P SHRESTHA | C12: G/7 | D12: 37773 | E12: 500 | F12: 2000 | G12: 4744 | H12: 4742 | I12: =G12-H12 -> 2 | J12: =I12*12 -> 24 | K12: 200 | L12: ='NOV 23'!O12 -> 5118 | M12: =F12+J12+K12+L12 -> 7342 | N12: 7342 | O12: =M12-N12 -> 0 | Q12: ALLOTED WEF SEP 21. ADV 10000. RENT 2000
A13: 8 | B13: AJAY BAG | C13: G/8 | D13: 37469 | E13: 500 | F13: 1800 | G13: 2781 | H13: ='NOV 23'!G13 -> 2744 | I13: =G13-H13 -> 37 | J13: =I13*12 -> 444 | K13: 200 | L13: ='NOV 23'!O13 -> 10230 | M13: =F13+J13+K13+L13 -> 12674 | N13: 0 | O13: =M13-N13 -> 12674 | Q13: ALLOTED WEF MAR 22. ADV 10000. RENT 1800
A14: 9 | B14: PRAMOD MANDAL | C14: G/9 | D14: 37347 | E14: 500 | F14: 2100 | G14: 12487 | H14: ='NOV 23'!G14 -> 12475 | I14: =G14-H14 -> 12 | J14: =I14*12 -> 144 | K14: 200 | L14: ='NOV 23'!O14 -> 0 | M14: =F14+J14+K14+L14 -> 2444 | N14: 2500 | O14: =M14-N14 -> -56 | Q14: ALLOTED WEF SEP 22. ADV 10000 RENT 2100 SHIFTJUL 23
A15: 10 | B15: PRAMOD MANDAL | C15: G/10 | D15: 37165 | E15: 500 | F15: 2000 | G15: 3171 | H15: ='NOV 23'!G15 -> 3163 | I15: =G15-H15 -> 8 | J15: =I15*12 -> 96 | K15: 200 | L15: ='NOV 23'!O15 -> 0 | M15: =F15+J15+K15+L15 -> 2296 | N15: 2300 | O15: =M15-N15 -> -4 | Q15: ALLOTED WEF SEP 22. ADV 10000 RENT 2000
A16: 11 | B16: SONU PRAJAPATI | C16: 1/1 | D16: 38443 | E16: 0 | F16: 2200 | G16: 567 | H16: ='NOV 23'!G16 -> 555 | I16: =G16-H16 -> 12 | J16: =I16*12 -> 144 | K16: 300 | L16: ='NOV 23'!O16 -> 18330 | M16: =F16+J16+K16+L16 -> 20974 | N16: 0 | O16: =M16-N16 -> 20974 | Q16: ALLOTED WEF APR 22. ADV 10K. RENT 2200
A17: 12 | B17: GOPAL SINGH | C17: 1/2 | D17: 38292 | F17: 3300 | G17: 6261 | H17: ='NOV 23'!G17 -> 6217 | I17: =G17-H17 -> 44 | J17: =I17*12 -> 528 | K17: 300 | L17: ='NOV 23'!O17 -> 30754 | M17: =F17+J17+K17+L17 -> 34882 | N17: 8000 | O17: =M17-N17 -> 26882 | Q17: ALLOTED WEF DEC 23. ADV 8000. LAST RENT 2800
A18: 13 | B18: AJAY DUBEY | C18: 1/3 | D18: 38292 | E18: 500 | F18: 3100 | G18: 5167 | H18: ='NOV 23'!G18 -> 5145 | I18: =G18-H18 -> 22 | J18: =I18*12 -> 264 | K18: 300 | L18: ='NOV 23'!O18 -> 39610 | M18: =F18+J18+K18+L18 -> 43274 | N18: 10000 | O18: =M18-N18 -> 33274 | Q18: RENT INCREASED WEF JUL 21 FROM 2600, ADV 15000
A19: 14 | B19: AMLESH RAM | C19: 1/4 | D19: 38292 | E19: 500 | F19: 3000 | G19: 3728 | H19: ='NOV 23'!G19 -> 3728 | I19: =G19-H19 -> 0 | J19: =I19*12 -> 0 | K19: 300 | L19: ='NOV 23'!O19 -> 6956 | M19: =F19+J19+K19+L19 -> 10256 | N19: 7000 | O19: =M19-N19 -> 3256 | Q19: SHIFTED FM 2/4 AUG 23 ALLOTED MAR 23 RENT 3K ADV 5K
A20: 15 | B20: VACANT | C20: 1/5 | D20: 37469 | E20: 500 | F20: 0 | G20: 4231 | H20: ='NOV 23'!G20 -> 4231 | I20: =G20-H20 -> 0 | J20: =I20*12 -> 0 | K20: 0 | L20: ='NOV 23'!O20 -> 0 | M20: =F20+J20+K20+L20 -> 0 | N20: 0 | O20: =M20-N20 -> 0 | Q20: VACANT WEF NOV 2023
A21: 16 | B21: SHAILENDRA PANDEY | C21: 1/6 | D21: 37681 | E21: 500 | F21: 3000 | G21: 2792 | H21: ='NOV 23'!G21 -> 2764 | I21: =G21-H21 -> 28 | J21: =I21*12 -> 336 | K21: 300 | L21: ='NOV 23'!O21 -> 36882 | M21: =F21+J21+K21+L21 -> 40518 | N21: 25000 | O21: =M21-N21 -> 15518 | Q21: RENT INCREASED WEF MAR 21 FROM 2300. ADV 10000
A22: 17 | B22: BIRENDAR YADAV | C22: 2/1 | D22: 38292 | E22: 500 | F22: 2800 | G22: 337 | H22: ='NOV 23'!G22 -> 317 | I22: =G22-H22 -> 20 | J22: =I22*12 -> 240 | K22: 300 | L22: ='NOV 23'!O22 -> 45780 | M22: =F22+J22+K22+L22 -> 49120 | N22: 10000 | O22: =M22-N22 -> 39120 | Q22: RENT INCREASED WEF DEC 22 FROM 2200. ADV NIL
A23: 18 | B23: HARI SHANKER SHUKLA | C23: 2/2 | D23: 38292 | E23: 500 | F23: 2700 | G23: 800 | H23: ='NOV 23'!G23 -> 799 | I23: =G23-H23 -> 1 | J23: =I23*12 -> 12 | K23: 300 | L23: ='NOV 23'!O23 -> 9210 | M23: =F23+J23+K23+L23 -> 12222 | N23: 3000 | O23: =M23-N23 -> 9222 | Q23: RENT INCRESED WEF JUL 21 FROM 2200. ADV 10000
A24: 19 | B24: SHIV SHANKER PANDEY | C24: 2/3 | D24: 37681 | E24: 500 | F24: 2800 | G24: 5158 | H24: ='NOV 23'!G24 -> 5140 | I24: =G24-H24 -> 18 | J24: =I24*12 -> 216 | K24: 300 | L24: ='NOV 23'!O24 -> 0 | M24: =F24+J24+K24+L24 -> 3316 | N24: 3316 | O24: =M24-N24 -> 0 | Q24: REALLOTED WEF DEC 22. RENT 2800. ADV NIL
A25: 20 | B25: BLANK | C25: 2/4 | D25: 37681 | E25: 0 | F25: 2800 | G25: 580 | H25: ='NOV 23'!G25 -> 567 | I25: =G25-H25 -> 13 | J25: =I25*12 -> 156 | K25: 300 | L25: ='NOV 23'!O25 -> 0 | M25: =F25+J25+K25+L25 -> 3256 | N25: 0 | O25: =M25-N25 -> 3256 | Q25: TEMPORARY FOR 1 MTH
A26: 21 | B26: BLABK | C26: 2/5 | D26: 37681 | E26: 500 | F26: 0 | G26: 3254 | H26: ='NOV 23'!G26 -> 3250 | I26: =G26-H26 -> 4 | J26: =I26*12 -> 48 | K26: 0 | L26: ='NOV 23'!O26 -> 0 | M26: =F26+J26+K26+L26 -> 48 | N26: 0 | O26: =M26-N26 -> 48 | Q26: VACATED WEF NOV 23. ALL DUES CLEAR
A27: 22 | B27: SUNIL MONDAL | C27: 2/6 | D27: 37681 | E27: 0 | F27: 3600 | G27: 4041 | H27: ='NOV 23'!G27 -> 4001 | I27: =G27-H27 -> 40 | J27: =I27*12 -> 480 | K27: 300 | L27: ='NOV 23'!O27 -> 65450 | M27: =F27+J27+K27+L27 -> 69830 | N27: 0 | O27: =M27-N27 -> 69830 | Q27: REALLOTED WEF DEC 23. LAST RENT 3300. ADV 10K
C28: TOTAL | E28: =SUM(E6:E27) -> 7000 | F28: =SUM(F6:F27) -> 49200 | I28: =SUM(I6:I27) -> 319 | J28: =SUM(J6:J27) -> 3828 | K28: =SUM(K6:K27) -> 5000 | L28: =SUM(L6:L27) -> 290848 | M28: =SUM(M6:M27) -> 348876 | N28: =SUM(N6:N27) -> 90404 | O28: =SUM(O6:O27) -> 258472

Sheet NOV 23
A1: SITA DEVI PANDEY HOUSING PROJECT
A2: 11/1B/1 GANPAT RAI KHEMKA LANE LILUAH HOWRAH(W. B.) 711204
A3: FOR THE MONTH OF - NOV 2023 | U3: 44
A4: SNO | B4: NAME | C4: ROOM | D4: DATE OF | E4: ELECTRIC | F4: MONTHLY | G4: ELECTRIC | K4: MISC | L4: B/F & | M4: TOTAL | N4: AMT | O4: B/F OR | P4: PAYMENT | Q4: REMARKS
C5: NO | D5: ALLOTMENT | E5: SECURITY | F5: RENT | G5: NEW | H5: PREV | I5: T UNIT | J5: AMOUNT | K5: RENT | L5: ADV | M5: AMT DUE | N5: PAID | O5: ADV | P5: DATE
A6: 1 | B6: SUNNY PRAJAPATI | C6: G/1 | D6: 38754 | E6: 0 | F6: 2000 | G6: 1070 | H6: ='OCT 23'!G6 -> 1048 | I6: =G6-H6 -> 22 | J6: =I6*12 -> 264 | K6: 270 | L6: ='OCT 23'!O6 -> 2656 | M6: =F6+J6+K6+L6 -> 5190 | N6: 5200 | O6: =M6-N6 -> -10 | Q6: ALLOTED WEF SEP 21. ADV 10000. RENT 2000
A7: 2 | B7: NEW | C7: G/2 | D7: 37653 | E7: 0 | F7: 2000 | G7: 321 | H7: ='OCT 23'!G7 -> 314 | I7: =G7-H7 -> 7 | J7: =I7*12 -> 84 | K7: 270 | L7: ='OCT 23'!O7 -> 484 | M7: =F7+J7+K7+L7 -> 2838 | N7: 2400 | O7: =M7-N7 -> 438 | Q7: ALLLTED WEF SEP 23. ADV 5K RENT 2000.
A8: 3 | B8: PANKAJ PATEL | C8: G/3 | D8: 37895 | E8: 0 | F8: 2000 | G8: 4295 | H8: ='OCT 23'!G8 -> 4285 | I8: =G8-H8 -> 10 | J8: =I8*12 -> 120 | K8: 270 | L8: ='OCT 23'!O8 -> 15000 | M8: =F8+J8+K8+L8 -> 17390 | N8: 0 | O8: =M8-N8 -> 17390 | Q8: ALLOTED WEF JUL 21. ADV 5K, RENT 2000.
A9: 4 | B9: BADRI MANDAL | C9: G/4 | D9: 38292 | E9: 500 | F9: 2000 | G9: 13016 | H9: ='OCT 23'!G9 -> 13002 | I9: =G9-H9 -> 14 | J9: =I9*12 -> 168 | K9: 270 | L9: ='OCT 23'!O9 -> 2272 | M9: =F9+J9+K9+L9 -> 4710 | N9: 0 | O9: =M9-N9 -> 4710 | Q9: ALLOTED WEF 15 DEC 2022. RENT 2000. ADV 5000
A10: 5 | B10: NEW | C10: G/5 | F10: 2000 | G10: 4026 | H10: ='OCT 23'!G10 -> 4018 | I10: =G10-H10 -> 8 | J10: =I10*12 -> 96 | K10: 270 | L10: ='OCT 23'!O10 -> 0 | M10: =F10+J10+K10+L10 -> 2366 | N10: 2366 | O10: =M10-N10 -> 0 | Q10: ALLOTED WEF SEP 23. ADV 5K. RENT 2K
A11: 6 | B11: BC PATEL | C11: G/6 | D11: 37667 | E11: 500 | F11: 2000 | G11: 1720 | H11: ='OCT 23'!G11 -> 1703 | I11: =G11-H11 -> 17 | J11: =I11*12 -> 204 | K11: 270 | L11: ='OCT 23'!O11 -> 3380 | M11: =F11+J11+K11+L11 -> 5854 | N11: 5854 | O11: =M11-N11 -> 0 | Q11: ALLOTED WEF JAN 22. ADV NIL. RENT 2000
A12: 7 | B12: RAM P SHRESTHA | C12: G/7 | D12: 37773 | E12: 500 | F12: 2000 | G12: 4745 | H12: ='OCT 23'!G12 -> 4720 | I12: =G12-H12 -> 25 | J12: =I12*12 -> 300 | K12: 270 | L12: ='OCT 23'!O12 -> 2548 | M12: =F12+J12+K12+L12 -> 5118 | N12: 0 | O12: =M12-N12 -> 5118 | Q12: ALLOTED WEF SEP 21. ADV 10000. RENT 2000
A13: 8 | B13: AJAY BAG | C13: G/8 | D13: 37469 | E13: 500 | F13: 1800 | G13: 2744 | H13: ='OCT 23'!G13 -> 2739 | I13: =G13-H13 -> 5 | J13: =I13*12 -> 60 | K13: 270 | L13: ='OCT 23'!O13 -> 14100 | M13: =F13+J13+K13+L13 -> 16230 | N13: 6000 | O13: =M13-N13 -> 10230 | Q13: ALLOTED WEF MAR 22. ADV 10000. RENT 1800
A14: 9 | B14: PRAMOD MANDAL | C14: G/9 | D14: 37347 | E14: 500 | F14: 2100 | G14: 12475 | H14: ='OCT 23'!G14 -> 12448 | I14: =G14-H14 -> 27 | J14: =I14*12 -> 324 | K14: 270 | L14: ='OCT 23'!O14 -> 2744 | M14: =F14+J14+K14+L14 -> 5438 | N14: 5438 | O14: =M14-N14 -> 0 | Q14: ALLOTED WEF SEP 22. ADV 10000 RENT 2100 SHIFTJUL 23
A15: 10 | B15: PRAMOD MANDAL | C15: G/10 | D15: 37165 | E15: 500 | F15: 2000 | G15: 3163 | H15: ='OCT 23'!G15 -> 3154 | I15: =G15-H15 -> 9 | J15: =I15*12 -> 108 | K15: 270 | L15: ='OCT 23'!O15 -> 0 | M15: =F15+J15+K15+L15 -> 2378 | N15: 2378 | O15: =M15-N15 -> 0 | Q15: ALLOTED WEF SEP 22. ADV 10000 RENT 2000
A16: 11 | B16: SONU PRAJAPATI | C16: 1/1 | D16: 38443 | E16: 0 | F16: 2200 | G16: 555 | H16: ='OCT 23'!G16 -> 508 | I16: =G16-H16 -> 47 | J16: =I16*12 -> 564 | K16: 370 | L16: ='OCT 23'!O16 -> 31696 | M16: =F16+J16+K16+L16 -> 34830 | N16: 16500 | O16: =M16-N16 -> 18330 | Q16: ALLOTED WEF APR 22. ADV 10K. RENT 2200
A17: 12 | B17: GOPAL SINGH | C17: 1/2 | D17: 38292 | F17: 2800 | G17: 6217 | H17: ='OCT 23'!G17 -> 6166 | I17: =G17-H17 -> 51 | J17: =I17*12 -> 612 | K17: 370 | L17: ='OCT 23'!O17 -> 31972 | M17: =F17+J17+K17+L17 -> 35754 | N17: 5000 | O17: =M17-N17 -> 30754 | Q17: ALLOTED WEF DEC 20. ADV 8000. RENT 2800
A18: 13 | B18: AJAY DUBEY | C18: 1/3 | D18: 38292 | E18: 500 | F18: 3100 | G18: 5145 | H18: ='OCT 23'!G18 -> 5103 | I18: =G18-H18 -> 42 | J18: =I18*12 -> 504 | K18: 370 | L18: ='OCT 23'!O18 -> 35636 | M18: =F18+J18+K18+L18 -> 39610 | N18: 0 | O18: =M18-N18 -> 39610 | Q18: RENT INCREASED WEF JUL 21 FROM 2600, ADV 15000
A19: 14 | B19: AMLESH RAM | C19: 1/4 | D19: 38292 | E19: 500 | F19: 3000 | G19: 3728 | H19: ='OCT 23'!G19 -> 3727 | I19: =G19-H19 -> 1 | J19: =I19*12 -> 12 | K19: 370 | L19: ='OCT 23'!O19 -> 3574 | M19: =F19+J19+K19+L19 -> 6956 | N19: 0 | O19: =M19-N19 -> 6956 | Q19: SHIFTED FM 2/4 AUG 23 ALLOTED MAR 23 RENT 3K ADV 5K
A20: 15 | B20: BIPIN KUMAR THAKUR | C20: 1/5 | D20: 37469 | E20: 500 | F20: 3000 | G20: 4231 | H20: ='OCT 23'!G20 -> 4203 | I20: =G20-H20 -> 28 | J20: =I20*12 -> 336 | K20: 370 | L20: ='OCT 23'!O20 -> 23100 | M20: =F20+J20+K20+L20 -> 26806 | N20: 26806 | O20: =M20-N20 -> 0 | Q20: VACATED WEF NOV 23. ALL DUES CLEAR
A21: 16 | B21: SHAILENDRA PANDEY | C21: 1/6 | D21: 37681 | E21: 500 | F21: 3000 | G21: 2764 | H21: ='OCT 23'!G21 -> 2720 | I21: =G21-H21 -> 44 | J21: =I21*12 -> 528 | K21: 370 | L21: ='OCT 23'!O21 -> 32984 | M21: =F21+J21+K21+L21 -> 36882 | N21: 0 | O21: =M21-N21 -> 36882 | Q21: RENT INCREASED WEF MAR 21 FROM 2300. ADV 10000
A22: 17 | B22: BIRENDAR YADAV | C22: 2/1 | D22: 38292 | E22: 500 | F22: 2800 | G22: 317 | H22: ='OCT 23'!G22 -> 295 | I22: =G22-H22 -> 22 | J22: =I22*12 -> 264 | K22: 370 | L22: ='OCT 23'!O22 -> 42346 | M22: =F22+J22+K22+L22 -> 45780 | N22: 0 | O22: =M22-N22 -> 45780 | Q22: RENT INCREASED WEF DEC 22 FROM 2200. ADV NIL
A23: 18 | B23: HARI SHANKER SHUKLA | C23: 2/2 | D23: 38292 | E23: 500 | F23: 2700 | G23: 799 | H23: ='OCT 23'!G23 -> 780 | I23: =G23-H23 -> 19 | J23: =I23*12 -> 228 | K23: 370 | L23: ='OCT 23'!O23 -> 5912 | M23: =F23+J23+K23+L23 -> 9210 | N23: 0 | O23: =M23-N23 -> 9210 | Q23: RENT INCRESED WEF JUL 21 FROM 2200. ADV 10000
A24: 19 | B24: SHIV SHANKER PANDEY | C24: 2/3 | D24: 37681 | E24: 500 | F24: 2800 | G24: 5140 | H24: ='OCT 23'!G24 -> 5098 | I24: =G24-H24 -> 42 | J24: =I24*12 -> 504 | K24: 370 | L24: ='OCT 23'!O24 -> 0 | M24: =F24+J24+K24+L24 -> 3674 | N24: 3674 | O24: =M24-N24 -> 0 | Q24: REALLOTED WEF DEC 22. RENT 2800. ADV NIL
A25: 20 | B25: BLANK | C25: 2/4 | D25: 37681 | E25: 0 | F25: 0 | G25: 567 | H25: ='OCT 23'!G25 -> 567 | I25: =G25-H25 -> 0 | J25: =I25*12 -> 0 | K25: 0 | L25: ='OCT 23'!O25 -> 0 | M25: =F25+J25+K25+L25 -> 0 | N25: 0 | O25: =M25-N25 -> 0 | Q25: VACANT WEF AUG 2023
A26: 21 | B26: JAIRAM MUDULI | C26: 2/5 | D26: 37681 | E26: 500 | F26: 2800 | G26: 3250 | H26: ='OCT 23'!G26 -> 3238 | I26: =G26-H26 -> 12 | J26: =I26*12 -> 144 | K26: 370 | L26: ='OCT 23'!O26 -> 6968 | M26: =F26+J26+K26+L26 -> 10282 | N26: 10282 | O26: =M26-N26 -> 0 | Q26: VACATED WEF NOV 23. ALL DUES CLEAR
A27: 22 | B27: SUNIL MONDAL | C27: 2/6 | D27: 37681 | E27: 0 | F27: 3300 | G27: 4001 | H27: ='OCT 23'!G27 -> 3934 | I27: =G27-H27 -> 67 | J27: =I27*12 -> 804 | K27: 370 | L27: ='OCT 23'!O27 -> 60976 | M27: =F27+J27+K27+L27 -> 65450 | N27: 0 | O27: =M27-N27 -> 65450 | Q27: REALLOTED WEF DEC 20. RENT 3300. ADV 10K
C28: TOTAL | E28: =SUM(E6:E27) -> 7000 | F28: =SUM(F6:F27) -> 51400 | I28: =SUM(I6:I27) -> 519 | J28: =SUM(J6:J27) -> 6228 | K28: =SUM(K6:K27) -> 6770 | L28: =SUM(L6:L27) -> 318348 | M28: =SUM(M6:M27) -> 382746 | N28: =SUM(N6:N27) -> 91898 | O28: =SUM(O6:O27) -> 290848

Sheet OCT 23
A1: SITA DEVI PANDEY HOUSING PROJECT
A2: 11/1B/1 GANPAT RAI KHEMKA LANE LILUAH HOWRAH(W. B.) 711204
A3: FOR THE MONTH OF - OCT 2023 | U3: 44
A4: SNO | B4: NAME | C4: ROOM | D4: DATE OF | E4: ELECTRIC | F4: MONTHLY | G4: ELECTRIC | K4: MISC | L4: B/F & | M4: TOTAL | N4: AMT | O4: B/F OR | P4: PAYMENT | Q4: REMARKS
C5: NO | D5: ALLOTMENT | E5: SECURITY | F5: RENT | G5: NEW | H5: PREV | I5: T UNIT | J5: AMOUNT | K5: RENT | L5: ADV | M5: AMT DUE | N5: PAID | O5: ADV | P5: DATE
A6: 1 | B6: SUNNY PRAJAPATI | C6: G/1 | D6: 38754 | E6: 0 | F6: 2000 | G6: 1048 | H6: ='SEP 23'!G6 -> 1010 | I6: =G6-H6 -> 38 | J6: =I6*12 -> 456 | K6: 200 | L6: ='SEP 23'!O6 -> 0 | M6: =F6+J6+K6+L6 -> 2656 | N6: 0 | O6: =M6-N6 -> 2656 | Q6: ALLOTED WEF SEP 21. ADV 10000. RENT 2000 | S6: 1050
A7: 2 | B7: NEW | C7: G/2 | D7: 37653 | E7: 0 | F7: 2000 | G7: 314 | H7: ='SEP 23'!G7 -> 235 | I7: =G7-H7 -> 79 | J7: =I7*12 -> 948 | K7: 200 | L7: ='SEP 23'!O7 -> -664 | M7: =F7+J7+K7+L7 -> 2484 | N7: 2000 | O7: =M7-N7 -> 484 | Q7: ALLLTED WEF SEP 23. ADV 5K RENT 2000. | S7: 321
A8: 3 | B8: PANKAJ PATEL | C8: G/3 | D8: 37895 | E8: 0 | F8: 2000 | G8: 4285 | H8: ='SEP 23'!G8 -> 4261 | I8: =G8-H8 -> 24 | J8: =I8*12 -> 288 | K8: 200 | L8: ='SEP 23'!O8 -> 16612 | M8: =F8+J8+K8+L8 -> 19100 | N8: 4100 | O8: =M8-N8 -> 15000 | Q8: ALLOTED WEF JUL 21. ADV 5K, RENT 2000. | S8: 4285
A9: 4 | B9: BADRI MANDAL | C9: G/4 | D9: 38292 | E9: 500 | F9: 2000 | G9: 13002 | H9: 12967 | I9: =G9-H9 -> 35 | J9: =I9*12 -> 420 | K9: 200 | L9: ='SEP 23'!O9 -> -348 | M9: =F9+J9+K9+L9 -> 2272 | N9: 0 | O9: =M9-N9 -> 2272 | Q9: ALLOTED WEF 15 DEC 2022. RENT 2000. ADV 5000 | S9: 13008
A10: 5 | B10: NEW | C10: G/5 | F10: 2000 | G10: 4018 | H10: ='SEP 23'!G10 -> 3980 | I10: =G10-H10 -> 38 | J10: =I10*12 -> 456 | K10: 200 | L10: ='SEP 23'!O10 -> 0 | M10: =F10+J10+K10+L10 -> 2656 | N10: 2656 | O10: =M10-N10 -> 0 | Q10: ALLOTED WEF SEP 23. ADV 5K. RENT 2K | S10: 4022
A11: 6 | B11: BC PATEL | C11: G/6 | D11: 37667 | E11: 500 | F11: 2000 | G11: 1703 | H11: ='SEP 23'!G11 -> 1677 | I11: =G11-H11 -> 26 | J11: =I11*12 -> 312 | K11: 200 | L11: ='SEP 23'!O11 -> 868 | M11: =F11+J11+K11+L11 -> 3380 | N11: 0 | O11: =M11-N11 -> 3380 | Q11: ALLOTED WEF JAN 22. ADV NIL. RENT 2000 | S11: 1710
A12: 7 | B12: RAM P SHRESTHA | C12: G/7 | D12: 37773 | E12: 500 | F12: 2000 | G12: 4720 | H12: ='SEP 23'!G12 -> 4691 | I12: =G12-H12 -> 29 | J12: =I12*12 -> 348 | K12: 200 | L12: ='SEP 23'!O12 -> 0 | M12: =F12+J12+K12+L12 -> 2548 | N12: 0 | O12: =M12-N12 -> 2548 | Q12: ALLOTED WEF SEP 21. ADV 10000. RENT 2000 | S12: 4725
A13: 8 | B13: AJAY BAG | C13: G/8 | D13: 37469 | E13: 500 | F13: 1800 | G13: 2739 | H13: ='SEP 23'!G13 -> 2704 | I13: =G13-H13 -> 35 | J13: =I13*12 -> 420 | K13: 200 | L13: ='SEP 23'!O13 -> 11680 | M13: =F13+J13+K13+L13 -> 14100 | N13: 0 | O13: =M13-N13 -> 14100 | Q13: ALLOTED WEF MAR 22. ADV 10000. RENT 1800 | S13: 2742
A14: 9 | B14: PRAMOD MANDAL | C14: G/9 | D14: 37347 | E14: 500 | F14: 2100 | G14: 12448 | H14: 12411 | I14: =G14-H14 -> 37 | J14: =I14*12 -> 444 | K14: 200 | L14: ='SEP 23'!O14 -> 0 | M14: =F14+J14+K14+L14 -> 2744 | N14: 0 | O14: =M14-N14 -> 2744 | Q14: ALLOTED WEF SEP 22. ADV 10000 RENT 2100 SHIFTJUL 23 | S14: 12454
A15: 10 | B15: PRAMOD MANDAL | C15: G/10 | D15: 37165 | E15: 500 | F15: 2000 | G15: 3154 | H15: ='SEP 23'!G15 -> 3112 | I15: =G15-H15 -> 42 | J15: =I15*12 -> 504 | K15: 200 | L15: ='SEP 23'!O15 -> 0 | M15: =F15+J15+K15+L15 -> 2704 | N15: 2704 | O15: =M15-N15 -> 0 | Q15: ALLOTED WEF SEP 22. ADV 10000 RENT 2000 | S15: 3158
A16: 11 | B16: SONU PRAJAPATI | C16: 1/1 | D16: 38443 | E16: 0 | F16: 2200 | G16: 508 | H16: ='SEP 23'!G16 -> 432 | I16: =G16-H16 -> 76 | J16: =I16*12 -> 912 | K16: 300 | L16: ='SEP 23'!O16 -> 28284 | M16: =F16+J16+K16+L16 -> 31696 | N16: 0 | O16: =M16-N16 -> 31696 | Q16: ALLOTED WEF APR 22. ADV 10K. RENT 2200
A17: 12 | B17: GOPAL SINGH | C17: 1/2 | D17: 38292 | F17: 2800 | G17: 6166 | H17: ='SEP 23'!G17 -> 6107 | I17: =G17-H17 -> 59 | J17: =I17*12 -> 708 | K17: 300 | L17: ='SEP 23'!O17 -> 28164 | M17: =F17+J17+K17+L17 -> 31972 | N17: 0 | O17: =M17-N17 -> 31972 | Q17: ALLOTED WEF DEC 20. ADV 8000. RENT 2800
A18: 13 | B18: AJAY DUBEY | C18: 1/3 | D18: 38292 | E18: 500 | F18: 3100 | G18: 5103 | H18: ='SEP 23'!G18 -> 5046 | I18: =G18-H18 -> 57 | J18: =I18*12 -> 684 | K18: 300 | L18: ='SEP 23'!O18 -> 31552 | M18: =F18+J18+K18+L18 -> 35636 | N18: 0 | O18: =M18-N18 -> 35636 | Q18: RENT INCREASED WEF JUL 21 FROM 2600, ADV 15000
A19: 14 | B19: AMLESH RAM | C19: 1/4 | D19: 38292 | E19: 500 | F19: 3000 | G19: 3727 | H19: ='SEP 23'!G19 -> 3704 | I19: =G19-H19 -> 23 | J19: =I19*12 -> 276 | K19: 300 | L19: ='SEP 23'!O19 -> -2 | M19: =F19+J19+K19+L19 -> 3574 | N19: 0 | O19: =M19-N19 -> 3574 | Q19: SHIFTED FM 2/4 AUG 23 ALLOTED MAR 23 RENT 3K ADV 5K
A20: 15 | B20: BIPIN KUMAR THAKUR | C20: 1/5 | D20: 37469 | E20: 500 | F20: 3000 | G20: 4203 | H20: ='SEP 23'!G20 -> 4143 | I20: =G20-H20 -> 60 | J20: =I20*12 -> 720 | K20: 300 | L20: ='SEP 23'!O20 -> 19080 | M20: =F20+J20+K20+L20 -> 23100 | N20: 0 | O20: =M20-N20 -> 23100 | Q20: RENT INCREASED WEF AUG 21 FROM 2400. ADV 10000
A21: 16 | B21: SHAILENDRA PANDEY | C21: 1/6 | D21: 37681 | E21: 500 | F21: 3000 | G21: 2720 | H21: ='SEP 23'!G21 -> 2667 | I21: =G21-H21 -> 53 | J21: =I21*12 -> 636 | K21: 300 | L21: ='SEP 23'!O21 -> 33148 | M21: =F21+J21+K21+L21 -> 37084 | N21: 4100 | O21: =M21-N21 -> 32984 | Q21: RENT INCREASED WEF MAR 21 FROM 2300. ADV 10000
A22: 17 | B22: BIRENDAR YADAV | C22: 2/1 | D22: 38292 | E22: 500 | F22: 2800 | G22: 295 | H22: ='SEP 23'!G22 -> 255 | I22: =G22-H22 -> 40 | J22: =I22*12 -> 480 | K22: 300 | L22: ='SEP 23'!O22 -> 43766 | M22: =F22+J22+K22+L22 -> 47346 | N22: 5000 | O22: =M22-N22 -> 42346 | Q22: RENT INCREASED WEF DEC 22 FROM 2200. ADV NIL
A23: 18 | B23: HARI SHANKER SHUKLA | C23: 2/2 | D23: 38292 | E23: 500 | F23: 2700 | G23: 780 | H23: ='SEP 23'!G23 -> 751 | I23: =G23-H23 -> 29 | J23: =I23*12 -> 348 | K23: 300 | L23: ='SEP 23'!O23 -> 12564 | M23: =F23+J23+K23+L23 -> 15912 | N23: 10000 | O23: =M23-N23 -> 5912 | Q23: RENT INCRESED WEF JUL 21 FROM 2200. ADV 10000
A24: 19 | B24: SHIV SHANKER PANDEY | C24: 2/3 | D24: 37681 | E24: 500 | F24: 2800 | G24: 5098 | H24: ='SEP 23'!G24 -> 5061 | I24: =G24-H24 -> 37 | J24: =I24*12 -> 444 | K24: 300 | L24: ='SEP 23'!O24 -> 0 | M24: =F24+J24+K24+L24 -> 3544 | N24: 3544 | O24: =M24-N24 -> 0 | Q24: REALLOTED WEF DEC 22. RENT 2800. ADV NIL
A25: 20 | B25: BLANK | C25: 2/4 | D25: 37681 | E25: 0 | F25: 0 | G25: 567 | H25: ='SEP 23'!G25 -> 567 | I25: =G25-H25 -> 0 | J25: =I25*12 -> 0 | K25: 0 | L25: ='SEP 23'!O25 -> 0 | M25: =F25+J25+K25+L25 -> 0 | N25: 0 | O25: =M25-N25 -> 0 | Q25: VACANT WEF AUG 2023
A26: 21 | B26: JAIRAM MUDULI | C26: 2/5 | D26: 37681 | E26: 500 | F26: 2800 | G26: 3238 | H26: ='SEP 23'!G26 -> 3207 | I26: =G26-H26 -> 31 | J26: =I26*12 -> 372 | K26: 300 | L26: ='SEP 23'!O26 -> 3496 | M26: =F26+J26+K26+L26 -> 6968 | N26: 0 | O26: =M26-N26 -> 6968 | Q26: ALLOTED WEF SEP 21. ADV 10000, RENT 2800
A27: 22 | B27: SUNIL MONDAL | C27: 2/6 | D27: 37681 | E27: 0 | F27: 3300 | G27: 3934 | H27: ='SEP 23'!G27 -> 3830 | I27: =G27-H27 -> 104 | J27: =I27*12 -> 1248 | K27: 300 | L27: ='SEP 23'!O27 -> 56128 | M27: =F27+J27+K27+L27 -> 60976 | N27: 0 | O27: =M27-N27 -> 60976 | Q27: REALLOTED WEF DEC 20. RENT 3300. ADV 10K
C28: TOTAL | E28: =SUM(E6:E27) -> 7000 | F28: =SUM(F6:F27) -> 51400 | I28: =SUM(I6:I27) -> 952 | J28: =SUM(J6:J27) -> 11424 | K28: =SUM(K6:K27) -> 5300 | L28: =SUM(L6:L27) -> 284328 | M28: =SUM(M6:M27) -> 352452 | N28: =SUM(N6:N27) -> 34104 | O28: =SUM(O6:O27) -> 318348

Sheet SEP 23
A1: SITA DEVI PANDEY HOUSING PROJECT
A2: 11/1B/1 GANPAT RAI KHEMKA LANE LILUAH HOWRAH(W. B.) 711204
A3: FOR THE MONTH OF - SEP 2023
A4: SNO | B4: NAME | C4: ROOM | D4: DATE OF | E4: ELECTRIC | F4: MONTHLY | G4: ELECTRIC | K4: MISC | L4: B/F & | M4: TOTAL | N4: AMT | O4: B/F OR | P4: PAYMENT | Q4: REMARKS
C5: NO | D5: ALLOTMENT | E5: SECURITY | F5: RENT | G5: NEW | H5: PREV | I5: T UNIT | J5: AMOUNT | K5: RENT | L5: ADV | M5: AMT DUE | N5: PAID | O5: ADV | P5: DATE
A6: 1 | B6: SUNNY PRAJAPATI | C6: G/1 | D6: 38754 | E6: 0 | F6: 2000 | G6: 1010 | H6: ='AUG 23'!G6 -> 971 | I6: =G6-H6 -> 39 | J6: =I6*12 -> 468 | K6: 200 | L6: ='AUG 23'!O6 -> -4 | M6: =F6+J6+K6+L6 -> 2664 | N6: 2664 | O6: =M6-N6 -> 0 | Q6: ALLOTED WEF SEP 21. ADV 10000. RENT 2000
A7: 2 | B7: NEW | C7: G/2 | D7: 37653 | E7: 0 | F7: 1000 | G7: 235 | H7: ='AUG 23'!G7 -> 207 | I7: =G7-H7 -> 28 | J7: =I7*12 -> 336 | K7: 200 | L7: ='AUG 23'!O7 -> 0 | M7: =F7+J7+K7+L7 -> 1536 | N7: 2200 | O7: =M7-N7 -> -664 | Q7: ALLLTED WEF SEP 23. ADV 7K RENT 2000.
A8: 3 | B8: PANKAJ PATEL | C8: G/3 | D8: 37895 | E8: 0 | F8: 2000 | G8: 4261 | H8: ='AUG 23'!G8 -> 4237 | I8: =G8-H8 -> 24 | J8: =I8*12 -> 288 | K8: 200 | L8: ='AUG 23'!O8 -> 14124 | M8: =F8+J8+K8+L8 -> 16612 | N8: 0 | O8: =M8-N8 -> 16612 | Q8: ALLOTED WEF JUL 21. ADV 5K, RENT 2000.
A9: 4 | B9: BADRI MANDAL | C9: G/4 | D9: 38292 | E9: 500 | F9: 2000 | G9: 12967 | H9: 12934 | I9: =G9-H9 -> 33 | J9: =I9*12 -> 396 | K9: 200 | L9: ='AUG 23'!O9 -> 2556 | M9: 5152 | N9: 5500 | O9: =M9-N9 -> -348 | Q9: ALLOTED WEF 15 DEC 2022. RENT 2000. ADV 5000
A10: 5 | B10: BLANK | C10: G/5 | F10: 2000 | G10: 3980 | H10: 3951 | I10: =G10-H10 -> 29 | J10: =I10*12 -> 348 | K10: 200 | L10: ='AUG 23'!O10 -> 0 | M10: =F10+J10+K10+L10 -> 2548 | N10: 2548 | O10: =M10-N10 -> 0 | Q10: ALLOTED WEF SEP 23. ADV 5K. RENT 2K
A11: 6 | B11: BC PATEL | C11: G/6 | D11: 37667 | E11: 500 | F11: 2000 | G11: 1677 | H11: ='AUG 23'!G11 -> 1651 | I11: =G11-H11 -> 26 | J11: =I11*12 -> 312 | K11: 200 | L11: ='AUG 23'!O11 -> 3356 | M11: =F11+J11+K11+L11 -> 5868 | N11: 5000 | O11: =M11-N11 -> 868 | Q11: ALLOTED WEF JAN 22. ADV NIL. RENT 2000
A12: 7 | B12: RAM P SHRESTHA | C12: G/7 | D12: 37773 | E12: 500 | F12: 2000 | G12: 4691 | H12: ='AUG 23'!G12 -> 4664 | I12: =G12-H12 -> 27 | J12: =I12*12 -> 324 | K12: 200 | L12: ='AUG 23'!O12 -> 2884 | M12: =F12+J12+K12+L12 -> 5408 | N12: 5408 | O12: =M12-N12 -> 0 | Q12: ALLOTED WEF SEP 21. ADV 10000. RENT 2000
A13: 8 | B13: AJAY BAG | C13: G/8 | D13: 37469 | E13: 500 | F13: 1800 | G13: 2704 | H13: ='AUG 23'!G13 -> 2677 | I13: =G13-H13 -> 27 | J13: =I13*12 -> 324 | K13: 200 | L13: ='AUG 23'!O13 -> 9356 | M13: =F13+J13+K13+L13 -> 11680 | N13: 0 | O13: =M13-N13 -> 11680 | Q13: ALLOTED WEF MAR 22. ADV 10000. RENT 1800
A14: 9 | B14: PRAMOD MANDAL | C14: G/9 | D14: 37347 | E14: 500 | F14: 2100 | G14: 2411 | H14: ='AUG 23'!G14 -> 2374 | I14: =G14-H14 -> 37 | J14: =I14*12 -> 444 | K14: 200 | L14: ='AUG 23'!O14 -> 3070 | M14: =F14+J14+K14+L14 -> 5814 | N14: 5814 | O14: =M14-N14 -> 0 | Q14: ALLOTED WEF SEP 22. ADV 10000 RENT 2100 SHIFTJUL 23
A15: 10 | B15: PRAMOD MANDAL | C15: G/10 | D15: 37165 | E15: 500 | F15: 2000 | G15: 3112 | H15: ='AUG 23'!G15 -> 3054 | I15: =G15-H15 -> 58 | J15: =I15*12 -> 696 | K15: 200 | L15: ='AUG 23'!O15 -> 6 | M15: =F15+J15+K15+L15 -> 2902 | N15: 2902 | O15: =M15-N15 -> 0 | Q15: ALLOTED WEF SEP 22. ADV 10000 RENT 2000
A16: 11 | B16: SONU PRAJAPATI | C16: 1/1 | D16: 38443 | E16: 0 | F16: 2200 | G16: 432 | H16: ='AUG 23'!G16 -> 356 | I16: =G16-H16 -> 76 | J16: =I16*12 -> 912 | K16: 300 | L16: ='AUG 23'!O16 -> 31872 | M16: =F16+J16+K16+L16 -> 35284 | N16: 7000 | O16: =M16-N16 -> 28284 | Q16: ALLOTED WEF APR 22. ADV 10K. RENT 2200
A17: 12 | B17: GOPAL SINGH | C17: 1/2 | D17: 38292 | F17: 2800 | G17: 6107 | H17: ='AUG 23'!G17 -> 6038 | I17: =G17-H17 -> 69 | J17: =I17*12 -> 828 | K17: 300 | L17: ='AUG 23'!O17 -> 32236 | M17: =F17+J17+K17+L17 -> 36164 | N17: 8000 | O17: =M17-N17 -> 28164 | Q17: ALLOTED WEF DEC 20. ADV 8000. RENT 2800
A18: 13 | B18: AJAY DUBEY | C18: 1/3 | D18: 38292 | E18: 500 | F18: 3100 | G18: 5046 | H18: ='AUG 23'!G18 -> 4993 | I18: =G18-H18 -> 53 | J18: =I18*12 -> 636 | K18: 300 | L18: ='AUG 23'!O18 -> 27516 | M18: =F18+J18+K18+L18 -> 31552 | N18: 0 | O18: =M18-N18 -> 31552 | Q18: RENT INCREASED WEF JUL 21 FROM 2600, ADV 15000
A19: 14 | B19: AMLESH RAM | C19: 1/4 | D19: 38292 | E19: 500 | F19: 3000 | G19: 3704 | H19: ='AUG 23'!G19 -> 3666 | I19: =G19-H19 -> 38 | J19: =I19*12 -> 456 | K19: 300 | L19: ='AUG 23'!O19 -> 662 | M19: =F19+J19+K19+L19 -> 4418 | N19: 4420 | O19: =M19-N19 -> -2 | Q19: SHIFTED FM 2/4 AUG 23 ALLOTED MAR 23 RENT 3K ADV 5000
A20: 15 | B20: BIPIN KUMAR THAKUR | C20: 1/5 | D20: 37469 | E20: 500 | F20: 3000 | G20: 4143 | H20: ='AUG 23'!G20 -> 4084 | I20: =G20-H20 -> 59 | J20: =I20*12 -> 708 | K20: 300 | L20: ='AUG 23'!O20 -> 15072 | M20: =F20+J20+K20+L20 -> 19080 | N20: 0 | O20: =M20-N20 -> 19080 | Q20: RENT INCREASED WEF AUG 21 FROM 2400. ADV 10000
A21: 16 | B21: SHAILENDRA PANDEY | C21: 1/6 | D21: 37681 | E21: 500 | F21: 3000 | G21: 2667 | H21: ='AUG 23'!G21 -> 2572 | I21: =G21-H21 -> 95 | J21: =I21*12 -> 1140 | K21: 300 | L21: ='AUG 23'!O21 -> 32708 | M21: =F21+J21+K21+L21 -> 37148 | N21: 4000 | O21: =M21-N21 -> 33148 | Q21: RENT INCREASED WEF MAR 21 FROM 2300. ADV 10000
A22: 17 | B22: BIRENDAR YADAV | C22: 2/1 | D22: 38292 | E22: 500 | F22: 2800 | G22: 255 | H22: ='AUG 23'!G22 -> 218 | I22: =G22-H22 -> 37 | J22: =I22*12 -> 444 | K22: 300 | L22: ='AUG 23'!O22 -> 40222 | M22: =F22+J22+K22+L22 -> 43766 | N22: 0 | O22: =M22-N22 -> 43766 | Q22: RENT INCREASED WEF DEC 22 FROM 2200. ADV NIL
A23: 18 | B23: HARI SHANKER SHUKLA | C23: 2/2 | D23: 38292 | E23: 500 | F23: 2700 | G23: 751 | H23: ='AUG 23'!G23 -> 731 | I23: =G23-H23 -> 20 | J23: =I23*12 -> 240 | K23: 300 | L23: ='AUG 23'!O23 -> 9324 | M23: =F23+J23+K23+L23 -> 12564 | N23: 0 | O23: =M23-N23 -> 12564 | Q23: RENT INCRESED WEF JUL 21 FROM 2200. ADV 10000
A24: 19 | B24: SHIV SHANKER PANDEY | C24: 2/3 | D24: 37681 | E24: 500 | F24: 2800 | G24: 5061 | H24: ='AUG 23'!G24 -> 5034 | I24: =G24-H24 -> 27 | J24: =I24*12 -> 324 | K24: 300 | L24: ='AUG 23'!O24 -> -68 | M24: =F24+J24+K24+L24 -> 3356 | N24: 3356 | O24: =M24-N24 -> 0 | Q24: REALLOTED WEF DEC 22. RENT 2800. ADV NIL
A25: 20 | B25: BLANK | C25: 2/4 | D25: 37681 | E25: 0 | F25: 0 | G25: 567 | H25: ='AUG 23'!G25 -> 567 | I25: =G25-H25 -> 0 | J25: =I25*12 -> 0 | K25: 0 | L25: ='AUG 23'!O25 -> 0 | M25: =F25+J25+K25+L25 -> 0 | N25: 0 | O25: =M25-N25 -> 0 | Q25: VACANT WEF AUG 2023
A26: 21 | B26: JAIRAM MUDULI | C26: 2/5 | D26: 37681 | E26: 500 | F26: 2800 | G26: 3207 | H26: ='AUG 23'!G26 -> 3174 | I26: =G26-H26 -> 33 | J26: =I26*12 -> 396 | K26: 300 | L26: ='AUG 23'!O26 -> 0 | M26: =F26+J26+K26+L26 -> 3496 | N26: 0 | O26: =M26-N26 -> 3496 | Q26: ALLOTED WEF SEP 21. ADV 10000, RENT 2800
A27: 22 | B27: SUNIL MONDAL | C27: 2/6 | D27: 37681 | E27: 0 | F27: 3300 | G27: 3830 | H27: ='AUG 23'!G27 -> 3728 | I27: =G27-H27 -> 102 | J27: =I27*12 -> 1224 | K27: 300 | L27: ='AUG 23'!O27 -> 51304 | M27: =F27+J27+K27+L27 -> 56128 | N27: 0 | O27: =M27-N27 -> 56128 | Q27: REALLOTED WEF DEC 20. RENT 3300. ADV 10K
C28: TOTAL | E28: =SUM(E6:E27) -> 7000 | F28: =SUM(F6:F27) -> 50400 | I28: =SUM(I6:I27) -> 937 | J28: =SUM(J6:J27) -> 11244 | K28: =SUM(K6:K27) -> 5300 | L28: =SUM(L6:L27) -> 276196 | M28: =SUM(M6:M27) -> 343140 | N28: =SUM(N6:N27) -> 58812 | O28: =SUM(O6:O27) -> 284328

Sheet AUG 23
A1: SITA DEVI PANDEY HOUSING PROJECT
A2: 11/1B/1 GANPAT RAI KHEMKA LANE LILUAH HOWRAH(W. B.) 711204
A3: FOR THE MONTH OF - AUG 2023
A4: SNO | B4: NAME | C4: ROOM | D4: DATE OF | E4: ELECTRIC | F4: MONTHLY | G4: ELECTRIC | K4: MISC | L4: B/F & | M4: TOTAL | N4: AMT | O4: B/F OR | P4: PAYMENT | Q4: REMARKS
C5: NO | D5: ALLOTMENT | E5: SECURITY | F5: RENT | G5: NEW | H5: PREV | I5: T UNIT | J5: AMOUNT | K5: RENT | L5: ADV | M5: AMT DUE | N5: PAID | O5: ADV | P5: DATE
A6: 1 | B6: SUNNY PRAJAPATI | C6: G/1 | D6: 38754 | E6: 0 | F6: 2000 | G6: 971 | H6: ='JUL 23'!G6 -> 938 | I6: =G6-H6 -> 33 | J6: =I6*12 -> 396 | K6: 500 | L6: ='JUL 23'!O6 -> 10 | M6: =F6+J6+K6+L6 -> 2906 | N6: 2910 | O6: =M6-N6 -> -4 | Q6: ALLOTED WEF SEP 21. ADV 10000. RENT 2000
A7: 2 | B7: NEW | C7: G/2 | D7: 37653 | E7: 0 | F7: 2000 | G7: 207 | H7: ='JUL 23'!G7 -> 158 | I7: =G7-H7 -> 49 | J7: =I7*12 -> 588 | K7: 500 | L7: ='JUL 23'!O7 -> 3900 | M7: =F7+J7+K7+L7 -> 6988 | N7: 6988 | O7: =M7-N7 -> 0 | Q7: VACATED WEF 30-08-2023.ALL DUES SETTLED
A8: 3 | B8: PANKAJ PATEL | C8: G/3 | D8: 37895 | E8: 0 | F8: 2000 | G8: 4237 | H8: ='JUL 23'!G8 -> 4231 | I8: =G8-H8 -> 6 | J8: =I8*12 -> 72 | K8: 500 | L8: ='JUL 23'!O8 -> 17052 | M8: =F8+J8+K8+L8 -> 19624 | N8: 5500 | O8: =M8-N8 -> 14124 | Q8: ALLOTED WEF JUL 21. ADV 5K, RENT 2000.
A9: 4 | B9: BADRI MANDAL | C9: G/4 | D9: 38292 | E9: 500 | F9: 2000 | G9: 3995 | H9: ='JUL 23'!G9 -> 3989 | I9: =G9-H9 -> 6 | J9: =I9*12 -> 72 | K9: 500 | L9: ='JUL 23'!O9 -> -16 | M9: =F9+J9+K9+L9 -> 2556 | N9: 0 | O9: =M9-N9 -> 2556 | Q9: ALLOTED WEF 15 DEC 2022. RENT 2000. ADV 5000
A10: 5 | B10: BLANK | C10: G/5 | F10: 0 | G10: 3936 | H10: ='JUL 23'!G10 -> 3936 | I10: =G10-H10 -> 0 | J10: =I10*12 -> 0 | K10: 0 | L10: 0 | M10: =F10+J10+K10+L10 -> 0 | N10: 0 | O10: =M10-N10 -> 0 | Q10: VACANT WEF JUL 2023
A11: 6 | B11: BC PATEL | C11: G/6 | D11: 37667 | E11: 500 | F11: 2000 | G11: 1651 | H11: ='JUL 23'!G11 -> 1609 | I11: =G11-H11 -> 42 | J11: =I11*12 -> 504 | K11: 500 | L11: ='JUL 23'!O11 -> 352 | M11: =F11+J11+K11+L11 -> 3356 | N11: 0 | O11: =M11-N11 -> 3356 | Q11: ALLOTED WEF JAN 22. ADV NIL. RENT 2000
A12: 7 | B12: RAM P SHRESTHA | C12: G/7 | D12: 37773 | E12: 500 | F12: 2000 | G12: 4664 | H12: ='JUL 23'!G12 -> 4632 | I12: =G12-H12 -> 32 | J12: =I12*12 -> 384 | K12: 500 | L12: ='JUL 23'!O12 -> 0 | M12: =F12+J12+K12+L12 -> 2884 | N12: 0 | O12: =M12-N12 -> 2884 | Q12: ALLOTED WEF SEP 21. ADV 10000. RENT 2000
A13: 8 | B13: AJAY BAG | C13: G/8 | D13: 37469 | E13: 500 | F13: 1800 | G13: 2677 | H13: ='JUL 23'!G13 -> 2647 | I13: =G13-H13 -> 30 | J13: =I13*12 -> 360 | K13: 500 | L13: ='JUL 23'!O13 -> 6696 | M13: =F13+J13+K13+L13 -> 9356 | N13: 0 | O13: =M13-N13 -> 9356 | Q13: ALLOTED WEF MAR 22. ADV 10000. RENT 1800
A14: 9 | B14: PRAMOD MANDAL | C14: G/9 | D14: 37347 | E14: 500 | F14: 2100 | G14: 2374 | H14: ='JUL 23'!G14 -> 2335 | I14: =G14-H14 -> 39 | J14: =I14*12 -> 468 | K14: 500 | L14: ='JUL 23'!O14 -> 2 | M14: =F14+J14+K14+L14 -> 3070 | N14: 0 | O14: =M14-N14 -> 3070 | Q14: ALLOTED WEF SEP 22. ADV 10000 RENT 2100 SHIFTJUL 23
A15: 10 | B15: PRAMOD MANDAL | C15: G/10 | D15: 37165 | E15: 500 | F15: 2000 | G15: 3054 | H15: ='JUL 23'!G15 -> 2987 | I15: =G15-H15 -> 67 | J15: =I15*12 -> 804 | K15: 500 | L15: ='JUL 23'!O15 -> 2 | M15: =F15+J15+K15+L15 -> 3306 | N15: 3300 | O15: =M15-N15 -> 6 | Q15: ALLOTED WEF SEP 22. ADV 10000 RENT 2000
A16: 11 | B16: SONU PRAJAPATI | C16: 1/1 | D16: 38443 | E16: 0 | F16: 2200 | G16: 356 | H16: ='JUL 23'!G16 -> 279 | I16: =G16-H16 -> 77 | J16: =I16*12 -> 924 | K16: 600 | L16: ='JUL 23'!O16 -> 28148 | M16: =F16+J16+K16+L16 -> 31872 | N16: 0 | O16: =M16-N16 -> 31872 | Q16: ALLOTED WEF APR 22. ADV 10K. RENT 2200
A17: 12 | B17: GOPAL SINGH | C17: 1/2 | D17: 38292 | F17: 2800 | G17: 6038 | H17: ='JUL 23'!G17 -> 5965 | I17: =G17-H17 -> 73 | J17: =I17*12 -> 876 | K17: 600 | L17: ='JUL 23'!O17 -> 27960 | M17: =F17+J17+K17+L17 -> 32236 | N17: 0 | O17: =M17-N17 -> 32236 | Q17: ALLOTED WEF DEC 20. ADV 8000. RENT 2800
A18: 13 | B18: AJAY DUBEY | C18: 1/3 | D18: 38292 | E18: 500 | F18: 3100 | G18: 4993 | H18: ='JUL 23'!G18 -> 4932 | I18: =G18-H18 -> 61 | J18: =I18*12 -> 732 | K18: 600 | L18: ='JUL 23'!O18 -> 23084 | M18: =F18+J18+K18+L18 -> 27516 | N18: 0 | O18: =M18-N18 -> 27516 | Q18: RENT INCREASED WEF JUL 21 FROM 2600, ADV 15000
A19: 14 | B19: AMLESH RAM | C19: 1/4 | D19: 38292 | E19: 500 | F19: 3000 | G19: 3666 | H19: ='JUL 23'!G19 -> 3640 | I19: =G19-H19 -> 26 | J19: =I19*12 -> 312 | K19: 600 | L19: 3750 | M19: =F19+J19+K19+L19 -> 7662 | N19: 7000 | O19: =M19-N19 -> 662 | Q19: SHIFTED FM 2/4 AUG 23 ALLOTED MAR 23 RENT 3K ADV 5000
A20: 15 | B20: BIPIN KUMAR THAKUR | C20: 1/5 | D20: 37469 | E20: 500 | F20: 3000 | G20: 4084 | H20: ='JUL 23'!G20 -> 4020 | I20: =G20-H20 -> 64 | J20: =I20*12 -> 768 | K20: 600 | L20: ='JUL 23'!O20 -> 18804 | M20: =F20+J20+K20+L20 -> 23172 | N20: 8100 | O20: =M20-N20 -> 15072 | Q20: RENT INCREASED WEF AUG 21 FROM 2400. ADV 10000
A21: 16 | B21: SHAILENDRA PANDEY | C21: 1/6 | D21: 37681 | E21: 500 | F21: 3000 | G21: 2572 | H21: ='JUL 23'!G21 -> 2495 | I21: =G21-H21 -> 77 | J21: =I21*12 -> 924 | K21: 600 | L21: ='JUL 23'!O21 -> 32184 | M21: =F21+J21+K21+L21 -> 36708 | N21: 4000 | O21: =M21-N21 -> 32708 | Q21: RENT INCREASED WEF MAR 21 FROM 2300. ADV 10000
A22: 17 | B22: BIRENDAR YADAV | C22: 2/1 | D22: 38292 | E22: 500 | F22: 2800 | G22: 218 | H22: ='JUL 23'!G22 -> 169 | I22: =G22-H22 -> 49 | J22: =I22*12 -> 588 | K22: 300 | L22: ='JUL 23'!O22 -> 36534 | M22: =F22+J22+K22+L22 -> 40222 | N22: 0 | O22: =M22-N22 -> 40222 | Q22: RENT INCREASED WEF DEC 22 FROM 2200. ADV NIL
A23: 18 | B23: HARI SHANKER SHUKLA | C23: 2/2 | D23: 38292 | E23: 500 | F23: 2700 | G23: 731 | H23: ='JUL 23'!G23 -> 689 | I23: =G23-H23 -> 42 | J23: =I23*12 -> 504 | K23: 300 | L23: ='JUL 23'!O23 -> 19820 | M23: =F23+J23+K23+L23 -> 23324 | N23: 14000 | O23: =M23-N23 -> 9324 | Q23: RENT INCRESED WEF JUL 21 FROM 2200. ADV 10000
A24: 19 | B24: SHIV SHANKER PANDEY | C24: 2/3 | D24: 37681 | E24: 500 | F24: 2800 | G24: 5034 | H24: ='JUL 23'!G24 -> 5006 | I24: =G24-H24 -> 28 | J24: =I24*12 -> 336 | K24: 300 | L24: ='JUL 23'!O24 -> -4 | M24: =F24+J24+K24+L24 -> 3432 | N24: 3500 | O24: =M24-N24 -> -68 | Q24: REALLOTED WEF DEC 22. RENT 2800. ADV NIL
A25: 20 | B25: BLANK | C25: 2/4 | D25: 37681 | E25: 0 | F25: 0 | G25: 567 | H25: ='JUL 23'!G25 -> 567 | I25: =G25-H25 -> 0 | J25: =I25*12 -> 0 | K25: 0 | L25: 0 | M25: =F25+J25+K25+L25 -> 0 | N25: 0 | O25: =M25-N25 -> 0 | Q25: VACANT WEF AUG 2023
A26: 21 | B26: JAIRAM MUDULI | C26: 2/5 | D26: 37681 | E26: 500 | F26: 2800 | G26: 3174 | H26: ='JUL 23'!G26 -> 3126 | I26: =G26-H26 -> 48 | J26: =I26*12 -> 576 | K26: 300 | L26: ='JUL 23'!O26 -> 0 | M26: =F26+J26+K26+L26 -> 3676 | N26: 3676 | O26: =M26-N26 -> 0 | Q26: ALLOTED WEF SEP 21. ADV 10000, RENT 2800
A27: 22 | B27: SUNIL MONDAL | C27: 2/6 | D27: 37681 | E27: 0 | F27: 3300 | G27: 3728 | H27: ='JUL 23'!G27 -> 3614 | I27: =G27-H27 -> 114 | J27: =I27*12 -> 1368 | K27: 300 | L27: ='JUL 23'!O27 -> 46336 | M27: =F27+J27+K27+L27 -> 51304 | N27: 0 | O27: =M27-N27 -> 51304 | Q27: REALLOTED WEF DEC 20. RENT 3300. ADV 10K
C28: TOTAL | E28: =SUM(E6:E27) -> 7000 | F28: =SUM(F6:F27) -> 49400 | I28: =SUM(I6:I27) -> 963 | J28: =SUM(J6:J27) -> 11556 | K28: =SUM(K6:K27) -> 9600 | L28: =SUM(L6:L27) -> 264614 | M28: =SUM(M6:M27) -> 335170 | N28: =SUM(N6:N27) -> 58974 | O28: =SUM(O6:O27) -> 276196

Sheet JUL 23
A1: SITA DEVI PANDEY HOUSING PROJECT
A2: 11/1B/1 GANPAT RAI KHEMKA LANE LILUAH HOWRAH(W. B.) 711204
A3: FOR THE MONTH OF - JUL 2023
A4: SNO | B4: NAME | C4: ROOM | D4: DATE OF | E4: ELECTRIC | F4: MONTHLY | G4: ELECTRIC | K4: MISC | L4: B/F & | M4: TOTAL | N4: AMT | O4: B/F OR | P4: PAYMENT | Q4: REMARKS
C5: NO | D5: ALLOTMENT | E5: SECURITY | F5: RENT | G5: NEW | H5: PREV | I5: T UNIT | J5: AMOUNT | K5: RENT | L5: ADV | M5: AMT DUE | N5: PAID | O5: ADV | P5: DATE
A6: 1 | B6: SUNNY PRAJAPATI | C6: G/1 | D6: 38754 | E6: 0 | F6: 2000 | G6: 938 | H6: ='JUN 23'!G6 -> 885 | I6: =G6-H6 -> 53 | J6: =I6*12 -> 636 | K6: 200 | L6: ='JUN 23'!O6 -> -26 | M6: =F6+J6+K6+L6 -> 2810 | N6: 2800 | O6: =M6-N6 -> 10 | Q6: ALLOTED WEF SEP 21. ADV 10000. RENT 2000
A7: 2 | B7: NEW | C7: G/2 | D7: 37653 | E7: 0 | F7: 2000 | G7: 158 | H7: ='JUN 23'!G7 -> 108 | I7: =G7-H7 -> 50 | J7: =I7*12 -> 600 | K7: 200 | L7: ='JUN 23'!O7 -> 1100 | M7: =F7+J7+K7+L7 -> 3900 | N7: 0 | O7: =M7-N7 -> 3900 | Q7: ALLLTED WEF JUN 23. ADV 5K RENT 2000
A8: 3 | B8: PANKAJ PATEL | C8: G/3 | D8: 37895 | E8: 0 | F8: 2000 | G8: 4231 | H8: ='JUN 23'!G8 -> 4208 | I8: =G8-H8 -> 23 | J8: =I8*12 -> 276 | K8: 200 | L8: ='JUN 23'!O8 -> 14576 | M8: =F8+J8+K8+L8 -> 17052 | N8: 0 | O8: =M8-N8 -> 17052 | Q8: ALLOTED WEF JUL 21. ADV 5K, RENT 2000.
A9: 4 | B9: BADRI MANDAL | C9: G/4 | D9: 38292 | E9: 500 | F9: 2000 | G9: 3989 | H9: ='JUN 23'!G9 -> 3944 | I9: =G9-H9 -> 45 | J9: =I9*12 -> 540 | K9: 200 | L9: ='JUN 23'!O9 -> 4244 | M9: =F9+J9+K9+L9 -> 6984 | N9: 7000 | O9: =M9-N9 -> -16 | Q9: ALLOTED WEF 15 DEC 2022. RENT 2000. ADV 5000
A10: 5 | B10: PRAMOD MANDAL | C10: G/5 | F10: 0 | G10: 3936 | H10: ='JUN 23'!G10 -> 3915 | I10: =G10-H10 -> 21 | J10: =I10*12 -> 252 | K10: 0 | L10: 0 | M10: =F10+J10+K10+L10 -> 252 | N10: 252 | O10: =M10-N10 -> 0 | Q10: VACANT WEF JUL 23
A11: 6 | B11: BC PATEL | C11: G/6 | D11: 37667 | E11: 500 | F11: 2000 | G11: 1609 | H11: ='JUN 23'!G11 -> 1564 | I11: =G11-H11 -> 45 | J11: =I11*12 -> 540 | K11: 200 | L11: ='JUN 23'!O11 -> 2612 | M11: =F11+J11+K11+L11 -> 5352 | N11: 5000 | O11: =M11-N11 -> 352 | Q11: ALLOTED WEF JAN 22. ADV NIL. RENT 2000
A12: 7 | B12: RAM P SHRESTHA | C12: G/7 | D12: 37773 | E12: 500 | F12: 2000 | G12: 4632 | H12: ='JUN 23'!G12 -> 4599 | I12: =G12-H12 -> 33 | J12: =I12*12 -> 396 | K12: 200 | L12: ='JUN 23'!O12 -> 2548 | M12: =F12+J12+K12+L12 -> 5144 | N12: 5144 | O12: =M12-N12 -> 0 | Q12: ALLOTED WEF SEP 21. ADV 10000. RENT 2000
A13: 8 | B13: AJAY BAG | C13: G/8 | D13: 37469 | E13: 500 | F13: 1800 | G13: 2647 | H13: ='JUN 23'!G13 -> 2620 | I13: =G13-H13 -> 27 | J13: =I13*12 -> 324 | K13: 200 | L13: ='JUN 23'!O13 -> 10372 | M13: =F13+J13+K13+L13 -> 12696 | N13: 6000 | O13: =M13-N13 -> 6696 | Q13: ALLOTED WEF MAR 22. ADV 10000. RENT 1800
A14: 9 | B14: PRAMOD MANDAL | C14: G/9 | D14: 37347 | E14: 500 | F14: 2100 | G14: 2335 | H14: ='JUN 23'!G14 -> 2317 | I14: =G14-H14 -> 18 | J14: =I14*12 -> 216 | K14: 200 | L14: 284 | M14: =F14+J14+K14+L14 -> 2800 | N14: 2798 | O14: =M14-N14 -> 2 | Q14: ALLOTED WEF 10 SEP 22. ADV 10000 RENT 2100 SHIFTJUL 23
A15: 10 | B15: PRAMOD MANDAL | C15: G/10 | D15: 37165 | E15: 500 | F15: 2000 | G15: 2987 | H15: ='JUN 23'!G15 -> 2916 | I15: =G15-H15 -> 71 | J15: =I15*12 -> 852 | K15: 200 | L15: ='JUN 23'!O15 -> 0 | M15: =F15+J15+K15+L15 -> 3052 | N15: 3050 | O15: =M15-N15 -> 2 | Q15: ALLOTED WEF SEP 22. ADV 10000 RENT 2000
A16: 11 | B16: SONU PRAJAPATI | C16: 1/1 | D16: 38443 | E16: 0 | F16: 2200 | G16: 279 | H16: ='JUN 23'!G16 -> 200 | I16: =G16-H16 -> 79 | J16: =I16*12 -> 948 | K16: 300 | L16: ='JUN 23'!O16 -> 24700 | M16: =F16+J16+K16+L16 -> 28148 | N16: 0 | O16: =M16-N16 -> 28148 | Q16: ALLOTED WEF APR 22. ADV 10K. RENT 2200
A17: 12 | B17: GOPAL SINGH | C17: 1/2 | D17: 38292 | F17: 2800 | G17: 5965 | H17: ='JUN 23'!G17 -> 5888 | I17: =G17-H17 -> 77 | J17: =I17*12 -> 924 | K17: 300 | L17: ='JUN 23'!O17 -> 28936 | M17: =F17+J17+K17+L17 -> 32960 | N17: 5000 | O17: =M17-N17 -> 27960 | Q17: ALLOTED WEF DEC 20. ADV 8000. RENT 2800
A18: 13 | B18: AJAY DUBEY | C18: 1/3 | D18: 38292 | E18: 500 | F18: 3100 | G18: 4932 | H18: ='JUN 23'!G18 -> 4874 | I18: =G18-H18 -> 58 | J18: =I18*12 -> 696 | K18: 300 | L18: ='JUN 23'!O18 -> 18988 | M18: =F18+J18+K18+L18 -> 23084 | N18: 0 | O18: =M18-N18 -> 23084 | Q18: RENT INCREASED WEF JUL 21 FROM 2600, ADV 15000
A19: 14 | B19: BLANK | C19: 1/4 | D19: 38292 | E19: 500 | F19: 0 | G19: 3640 | H19: ='JUN 23'!G19 -> 3635 | I19: =G19-H19 -> 5 | J19: =I19*12 -> 60 | K19: 0 | L19: 0 | M19: =F19+J19+K19+L19 -> 60 | N19: 60 | O19: =M19-N19 -> 0 | Q19: VACANT WEF JUL 23
A20: 15 | B20: BIPIN KUMAR THAKUR | C20: 1/5 | D20: 37469 | E20: 500 | F20: 3000 | G20: 4020 | H20: ='JUN 23'!G20 -> 3960 | I20: =G20-H20 -> 60 | J20: =I20*12 -> 720 | K20: 300 | L20: ='JUN 23'!O20 -> 14784 | M20: =F20+J20+K20+L20 -> 18804 | N20: 0 | O20: =M20-N20 -> 18804 | Q20: RENT INCREASED WEF AUG 21 FROM 2400. ADV 10000
A21: 16 | B21: SHAILENDRA PANDEY | C21: 1/6 | D21: 37681 | E21: 500 | F21: 3000 | G21: 2495 | H21: ='JUN 23'!G21 -> 2421 | I21: =G21-H21 -> 74 | J21: =I21*12 -> 888 | K21: 300 | L21: ='JUN 23'!O21 -> 32996 | M21: =F21+J21+K21+L21 -> 37184 | N21: 5000 | O21: =M21-N21 -> 32184 | Q21: RENT INCREASED WEF MAR 21 FROM 2300. ADV 10000
A22: 17 | B22: BIRENDAR YADAV | C22: 2/1 | D22: 38292 | E22: 500 | F22: 2800 | G22: 169 | H22: ='JUN 23'!G22 -> 124 | I22: =G22-H22 -> 45 | J22: =I22*12 -> 540 | K22: 300 | L22: ='JUN 23'!O22 -> 37894 | M22: =F22+J22+K22+L22 -> 41534 | N22: 5000 | O22: =M22-N22 -> 36534 | Q22: RENT INCREASED WEF DEC 22 FROM 2200. ADV NIL
A23: 18 | B23: HARI SHANKER SHUKLA | C23: 2/2 | D23: 38292 | E23: 500 | F23: 2700 | G23: 689 | H23: ='JUN 23'!G23 -> 653 | I23: =G23-H23 -> 36 | J23: =I23*12 -> 432 | K23: 300 | L23: ='JUN 23'!O23 -> 16388 | M23: =F23+J23+K23+L23 -> 19820 | N23: 0 | O23: =M23-N23 -> 19820 | Q23: RENT INCRESED WEF JUL 21 FROM 2200. ADV 10000
A24: 19 | B24: SHIV SHANKER PANDEY | C24: 2/3 | D24: 37681 | E24: 500 | F24: 2800 | G24: 5006 | H24: ='JUN 23'!G24 -> 4973 | I24: =G24-H24 -> 33 | J24: =I24*12 -> 396 | K24: 300 | L24: ='JUN 23'!O24 -> 0 | M24: =F24+J24+K24+L24 -> 3496 | N24: 3500 | O24: =M24-N24 -> -4 | Q24: REALLOTED WEF DEC 22. RENT 2800. ADV NIL
A25: 20 | B25: AMLESH RAM | C25: 2/4 | D25: 37681 | E25: 0 | F25: 3000 | G25: 567 | H25: ='JUN 23'!G25 -> 529 | I25: =G25-H25 -> 38 | J25: =I25*12 -> 456 | K25: 300 | L25: ='JUN 23'!O25 -> -6 | M25: =F25+J25+K25+L25 -> 3750 | N25: 0 | O25: =M25-N25 -> 3750 | Q25: ALLOTED WEF MAR 23. RENT 3300. ADV 5000 SHIFTED TO 1/4
A26: 21 | B26: JAIRAM MUDULI | C26: 2/5 | D26: 37681 | E26: 500 | F26: 2800 | G26: 3126 | H26: ='JUN 23'!G26 -> 3077 | I26: =G26-H26 -> 49 | J26: =I26*12 -> 588 | K26: 300 | L26: ='JUN 23'!O26 -> 0 | M26: =F26+J26+K26+L26 -> 3688 | N26: 3688 | O26: =M26-N26 -> 0 | Q26: ALLOTED WEF SEP 21. ADV 10000, RENT 2800
A27: 22 | B27: SUNIL MONDAL | C27: 2/6 | D27: 37681 | E27: 0 | F27: 3300 | G27: 3614 | H27: ='JUN 23'!G27 -> 3482 | I27: =G27-H27 -> 132 | J27: =I27*12 -> 1584 | K27: 300 | L27: ='JUN 23'!O27 -> 41152 | M27: =F27+J27+K27+L27 -> 46336 | N27: 0 | O27: =M27-N27 -> 46336 | Q27: REALLOTED WEF DEC 20. RENT 3300. ADV 10K
C28: TOTAL | E28: =SUM(E6:E27) -> 7000 | F28: =SUM(F6:F27) -> 49400 | I28: =SUM(I6:I27) -> 1072 | J28: =SUM(J6:J27) -> 12864 | K28: =SUM(K6:K27) -> 5100 | L28: =SUM(L6:L27) -> 251542 | M28: =SUM(M6:M27) -> 318906 | N28: =SUM(N6:N27) -> 54292 | O28: =SUM(O6:O27) -> 264614

Sheet JUN 23
A1: SITA DEVI PANDEY HOUSING PROJECT
A2: 11/1B/1 GANPAT RAI KHEMKA LANE LILUAH HOWRAH(W. B.) 711204
A3: FOR THE MONTH OF - JUN 2023
A4: SNO | B4: NAME | C4: ROOM | D4: DATE OF | E4: ELECTRIC | F4: MONTHLY | G4: ELECTRIC | K4: MISC | L4: B/F & | M4: TOTAL | N4: AMT | O4: B/F OR | P4: PAYMENT | Q4: REMARKS
C5: NO | D5: ALLOTMENT | E5: SECURITY | F5: RENT | G5: NEW | H5: PREV | I5: T UNIT | J5: AMOUNT | K5: RENT | L5: ADV | M5: AMT DUE | N5: PAID | O5: ADV | P5: DATE
A6: 1 | B6: SUNNY PRAJAPATI | C6: G/1 | D6: 38754 | E6: 0 | F6: 2000 | G6: 885 | H6: ='MAY 23'!G6 -> 866 | I6: =G6-H6 -> 19 | J6: =I6*12 -> 228 | K6: 200 | L6: ='MAY 23'!O6 -> 2446 | M6: =F6+J6+K6+L6 -> 4874 | N6: 4900 | O6: =M6-N6 -> -26 | Q6: ALLOTED WEF SEP 21. ADV 10000. RENT 2000
A7: 2 | B7: NEW | C7: G/2 | D7: 37653 | E7: 0 | F7: 1000 | G7: 108 | H7: ='MAY 23'!G7 -> 108 | I7: =G7-H7 -> 0 | J7: =I7*12 -> 0 | K7: 100 | L7: ='MAY 23'!O7 -> 0 | M7: =F7+J7+K7+L7 -> 1100 | N7: 0 | O7: =M7-N7 -> 1100 | Q7: ALLLTED WEF 15 JUN 23. ADV 5K RENT 2000
A8: 3 | B8: PANKAJ PATEL | C8: G/3 | D8: 37895 | E8: 0 | F8: 2000 | G8: 4208 | H8: ='MAY 23'!G8 -> 4197 | I8: =G8-H8 -> 11 | J8: =I8*12 -> 132 | K8: 200 | L8: ='MAY 23'!O8 -> 12244 | M8: =F8+J8+K8+L8 -> 14576 | N8: 0 | O8: =M8-N8 -> 14576 | Q8: ALLOTED WEF JUL 21. ADV 5K, RENT 2000.
A9: 4 | B9: BADRI MANDAL | C9: G/4 | D9: 38292 | E9: 500 | F9: 2000 | G9: 3944 | H9: ='MAY 23'!G9 -> 3871 | I9: =G9-H9 -> 73 | J9: =I9*12 -> 876 | K9: 200 | L9: ='MAY 23'!O9 -> 1168 | M9: =F9+J9+K9+L9 -> 4244 | N9: 0 | O9: =M9-N9 -> 4244 | Q9: ALLOTED WEF 15 DEC 2022. RENT 2000. ADV 5000
A10: 5 | B10: PRAMOD MANDAL | C10: G/5 | F10: 2100 | G10: 3915 | H10: ='MAY 23'!G10 -> 3887 | I10: =G10-H10 -> 28 | J10: =I10*12 -> 336 | K10: 200 | L10: ='MAY 23'!O10 -> 2648 | M10: =F10+J10+K10+L10 -> 5284 | N10: 5000 | O10: =M10-N10 -> 284 | Q10: ALLOTED WEF 10 SEP 22. ADV 10000 RENT 2100
A11: 6 | B11: BC PATEL | C11: G/6 | D11: 37667 | E11: 500 | F11: 2000 | G11: 1564 | H11: ='MAY 23'!G11 -> 1530 | I11: =G11-H11 -> 34 | J11: =I11*12 -> 408 | K11: 200 | L11: ='MAY 23'!O11 -> 4 | M11: =F11+J11+K11+L11 -> 2612 | N11: 0 | O11: =M11-N11 -> 2612 | Q11: ALLOTED WEF JAN 22. ADV NIL. RENT 2000
A12: 7 | B12: RAM P SHRESTHA | C12: G/7 | D12: 37773 | E12: 500 | F12: 2000 | G12: 4599 | H12: ='MAY 23'!G12 -> 4570 | I12: =G12-H12 -> 29 | J12: =I12*12 -> 348 | K12: 200 | L12: ='MAY 23'!O12 -> 0 | M12: =F12+J12+K12+L12 -> 2548 | N12: 0 | O12: =M12-N12 -> 2548 | Q12: ALLOTED WEF SEP 21. ADV 10000. RENT 2000
A13: 8 | B13: AJAY BAG | C13: G/8 | D13: 37469 | E13: 500 | F13: 1800 | G13: 2620 | H13: ='MAY 23'!G13 -> 2592 | I13: =G13-H13 -> 28 | J13: =I13*12 -> 336 | K13: 200 | L13: ='MAY 23'!O13 -> 8036 | M13: =F13+J13+K13+L13 -> 10372 | N13: 0 | O13: =M13-N13 -> 10372 | Q13: ALLOTED WEF MAR 22. ADV 10000. RENT 1800
A14: 9 | B14: VACANT | C14: G/9 | D14: 37347 | E14: 500 | F14: 2000 | G14: 2317 | H14: ='MAY 23'!G14 -> 2317 | I14: =G14-H14 -> 0 | J14: =I14*12 -> 0 | K14: 0 | L14: ='MAY 23'!O14 -> 0 | M14: 0 | N14: 0 | O14: =M14-N14 -> 0 | Q14: VACATED WEF APR 22. BAL ADJ WITH 5K ADV. ALL CLEAR
A15: 10 | B15: PRAMOD MANDAL | C15: G/10 | D15: 37165 | E15: 500 | F15: 2000 | G15: 2916 | H15: ='MAY 23'!G15 -> 2841 | I15: =G15-H15 -> 75 | J15: =I15*12 -> 900 | K15: 200 | L15: ='MAY 23'!O15 -> 0 | M15: =F15+J15+K15+L15 -> 3100 | N15: 3100 | O15: =M15-N15 -> 0 | Q15: ALLOTED WEF SEP 22. ADV 10000 RENT 2000
A16: 11 | B16: SONU PRAJAPATI | C16: 1/1 | D16: 38443 | E16: 0 | F16: 2200 | G16: 200 | H16: ='MAY 23'!G16 -> 129 | I16: =G16-H16 -> 71 | J16: =I16*12 -> 852 | K16: 300 | L16: ='MAY 23'!O16 -> 21348 | M16: =F16+J16+K16+L16 -> 24700 | N16: 0 | O16: =M16-N16 -> 24700 | Q16: ALLOTED WEF APR 22. ADV 10K. RENT 2200
A17: 12 | B17: GOPAL SINGH | C17: 1/2 | D17: 38292 | F17: 2800 | G17: 5888 | H17: ='MAY 23'!G17 -> 5823 | I17: =G17-H17 -> 65 | J17: =I17*12 -> 780 | K17: 300 | L17: ='MAY 23'!O17 -> 32056 | M17: =F17+J17+K17+L17 -> 35936 | N17: 7000 | O17: =M17-N17 -> 28936 | Q17: ALLOTED WEF DEC 20. ADV 8000. RENT 2800
A18: 13 | B18: AJAY DUBEY | C18: 1/3 | D18: 38292 | E18: 500 | F18: 3100 | G18: 4874 | H18: ='MAY 23'!G18 -> 4826 | I18: =G18-H18 -> 48 | J18: =I18*12 -> 576 | K18: 300 | L18: ='MAY 23'!O18 -> 15012 | M18: =F18+J18+K18+L18 -> 18988 | N18: 0 | O18: =M18-N18 -> 18988 | Q18: RENT INCREASED WEF JUL 21 FROM 2600, ADV 15000
A19: 14 | B19: BAJRANG L PAREEK | C19: 1/4 | D19: 38292 | E19: 500 | F19: 2700 | G19: 3635 | H19: ='MAY 23'!G19 -> 3635 | I19: =G19-H19 -> 0 | J19: =I19*12 -> 0 | K19: 300 | L19: ='MAY 23'!O19 -> 48576 | M19: =F19+J19+K19+L19 -> 51576 | N19: 40000 | O19: =M19-N19 -> 11576 | Q19: SURRENDERED WEF JUN 23. CASH 30K, ADV 10K, DUE 11576
A20: 15 | B20: BIPIN KUMAR THAKUR | C20: 1/5 | D20: 37469 | E20: 500 | F20: 3000 | G20: 3960 | H20: ='MAY 23'!G20 -> 3907 | I20: =G20-H20 -> 53 | J20: =I20*12 -> 636 | K20: 300 | L20: ='MAY 23'!O20 -> 20348 | M20: =F20+J20+K20+L20 -> 24284 | N20: 9500 | O20: =M20-N20 -> 14784 | Q20: RENT INCREASED WEF AUG 21 FROM 2400. ADV 10000
A21: 16 | B21: SHAILENDRA PANDEY | C21: 1/6 | D21: 37681 | E21: 500 | F21: 3000 | G21: 2421 | H21: ='MAY 23'!G21 -> 2374 | I21: =G21-H21 -> 47 | J21: =I21*12 -> 564 | K21: 300 | L21: ='MAY 23'!O21 -> 35132 | M21: =F21+J21+K21+L21 -> 38996 | N21: 6000 | O21: =M21-N21 -> 32996 | Q21: RENT INCREASED WEF MAR 21 FROM 2300. ADV 10000
A22: 17 | B22: BIRENDAR YADAV | C22: 2/1 | D22: 38292 | E22: 500 | F22: 2800 | G22: 124 | H22: ='MAY 23'!G22 -> 83 | I22: =G22-H22 -> 41 | J22: =I22*12 -> 492 | K22: 300 | L22: ='MAY 23'!O22 -> 39302 | M22: =F22+J22+K22+L22 -> 42894 | N22: 5000 | O22: =M22-N22 -> 37894 | Q22: RENT INCREASED WEF DEC 22 FROM 2200. ADV NIL
A23: 18 | B23: HARI SHANKER SHUKLA | C23: 2/2 | D23: 38292 | E23: 500 | F23: 2700 | G23: 653 | H23: ='MAY 23'!G23 -> 653 | I23: =G23-H23 -> 0 | J23: =I23*12 -> 0 | K23: 300 | L23: ='MAY 23'!O23 -> 13388 | M23: =F23+J23+K23+L23 -> 16388 | N23: 0 | O23: =M23-N23 -> 16388 | Q23: RENT INCRESED WEF JUL 21 FROM 2200. ADV 10000
A24: 19 | B24: SHIV SHANKER PANDEY | C24: 2/3 | D24: 37681 | E24: 500 | F24: 2800 | G24: 4973 | H24: ='MAY 23'!G24 -> 4945 | I24: =G24-H24 -> 28 | J24: =I24*12 -> 336 | K24: 300 | L24: ='MAY 23'!O24 -> 0 | M24: =F24+J24+K24+L24 -> 3436 | N24: 3436 | O24: =M24-N24 -> 0 | Q24: REALLOTED WEF DEC 22. RENT 2800. ADV NIL
A25: 20 | B25: AMLESH RAM | C25: 2/4 | D25: 37681 | E25: 0 | F25: 3000 | G25: 529 | H25: ='MAY 23'!G25 -> 492 | I25: =G25-H25 -> 37 | J25: =I25*12 -> 444 | K25: 300 | L25: ='MAY 23'!O25 -> 0 | M25: =F25+J25+K25+L25 -> 3744 | N25: 3750 | O25: =M25-N25 -> -6 | Q25: ALLOTED WEF MAR 23. RENT 3300. ADV 5000
A26: 21 | B26: JAIRAM MUDULI | C26: 2/5 | D26: 37681 | E26: 500 | F26: 2800 | G26: 3077 | H26: ='MAY 23'!G26 -> 3037 | I26: =G26-H26 -> 40 | J26: =I26*12 -> 480 | K26: 300 | L26: ='MAY 23'!O26 -> 0 | M26: =F26+J26+K26+L26 -> 3580 | N26: 3580 | O26: =M26-N26 -> 0 | Q26: ALLOTED WEF SEP 21. ADV 10000, RENT 2800
A27: 22 | B27: SUNIL MONDAL | C27: 2/6 | D27: 37681 | E27: 0 | F27: 3300 | G27: 3482 | H27: ='MAY 23'!G27 -> 3355 | I27: =G27-H27 -> 127 | J27: =I27*12 -> 1524 | K27: 300 | L27: ='MAY 23'!O27 -> 56028 | M27: =F27+J27+K27+L27 -> 61152 | N27: 20000 | O27: =M27-N27 -> 41152 | Q27: REALLOTED WEF DEC 20. RENT 3300. ADV 10K
C28: TOTAL | E28: =SUM(E6:E27) -> 7000 | F28: =SUM(F6:F27) -> 53100 | I28: =SUM(I6:I27) -> 854 | J28: =SUM(J6:J27) -> 10248 | K28: =SUM(K6:K27) -> 5300 | L28: =SUM(L6:L27) -> 307736 | M28: =SUM(M6:M27) -> 374384 | N28: =SUM(N6:N27) -> 111266 | O28: =SUM(O6:O27) -> 263118

Sheet MAY 23
A1: SITA DEVI PANDEY HOUSING PROJECT
A2: 11/1B/1 GANPAT RAI KHEMKA LANE LILUAH HOWRAH(W. B.) 711204
A3: FOR THE MONTH OF - MAY 2023
A4: SNO | B4: NAME | C4: ROOM | D4: DATE OF | E4: ELECTRIC | F4: MONTHLY | G4: ELECTRIC | K4: MISC | L4: B/F & | M4: TOTAL | N4: AMT | O4: B/F OR | P4: PAYMENT | Q4: REMARKS
C5: NO | D5: ALLOTMENT | E5: SECURITY | F5: RENT | G5: NEW | H5: PREV | I5: T UNIT | J5: AMOUNT | K5: RENT | L5: ADV | M5: AMT DUE | N5: PAID | O5: ADV | P5: DATE
A6: 1 | B6: SUNNY PRAJAPATI | C6: G/1 | D6: 38754 | E6: 0 | F6: 2000 | G6: 866 | H6: ='APR 23'!G6 -> 845 | I6: =G6-H6 -> 21 | J6: =I6*12 -> 252 | K6: 200 | L6: ='APR 23'!O6 -> -6 | M6: =F6+J6+K6+L6 -> 2446 | N6: 0 | O6: =M6-N6 -> 2446 | Q6: ALLOTED WEF SEP 21. ADV 10000. RENT 2000
A7: 2 | B7: VACANT | C7: G/2 | D7: 37653 | E7: 0 | F7: 0 | G7: 108 | H7: ='APR 23'!G7 -> 108 | I7: =G7-H7 -> 0 | J7: =I7*12 -> 0 | K7: 0 | L7: ='APR 23'!O7 -> 0 | M7: =F7+J7+K7+L7 -> 0 | N7: 0 | O7: =M7-N7 -> 0 | Q7: VACATED WEF SEP 22
A8: 3 | B8: PANKAJ PATEL | C8: G/3 | D8: 37895 | E8: 0 | F8: 2000 | G8: 4197 | H8: ='APR 23'!G8 -> 4141 | I8: =G8-H8 -> 56 | J8: =I8*12 -> 672 | K8: 200 | L8: ='APR 23'!O8 -> 12372 | M8: =F8+J8+K8+L8 -> 15244 | N8: 3000 | O8: =M8-N8 -> 12244 | Q8: ALLOTED WEF JUL 21. ADV 5K, RENT 2000.
A9: 4 | B9: BADRI MANDAL | C9: G/4 | D9: 38292 | E9: 500 | F9: 2000 | G9: 3871 | H9: ='APR 23'!G9 -> 3866 | I9: =G9-H9 -> 5 | J9: =I9*12 -> 60 | K9: 200 | L9: ='APR 23'!O9 -> 2908 | M9: =F9+J9+K9+L9 -> 5168 | N9: 4000 | O9: =M9-N9 -> 1168 | Q9: ALLOTED WEF 15 DEC 2022. RENT 2000. ADV 5000
A10: 5 | B10: PRAMOD MANDAL | C10: G/5 | F10: 2100 | G10: 3887 | H10: ='APR 23'!G10 -> 3858 | I10: =G10-H10 -> 29 | J10: =I10*12 -> 348 | K10: 200 | L10: ='APR 23'!O10 -> 0 | M10: =F10+J10+K10+L10 -> 2648 | N10: 0 | O10: =M10-N10 -> 2648 | Q10: ALLOTED WEF 10 SEP 22. ADV 10000 RENT 2100
A11: 6 | B11: BC PATEL | C11: G/6 | D11: 37667 | E11: 500 | F11: 2000 | G11: 1530 | H11: ='APR 23'!G11 -> 1487 | I11: =G11-H11 -> 43 | J11: =I11*12 -> 516 | K11: 200 | L11: ='APR 23'!O11 -> 7288 | M11: =F11+J11+K11+L11 -> 10004 | N11: 10000 | O11: =M11-N11 -> 4 | Q11: ALLOTED WEF JAN 22. ADV NIL. RENT 2000
A12: 7 | B12: RAM P SHRESTHA | C12: G/7 | D12: 37773 | E12: 500 | F12: 2000 | G12: 4570 | H12: ='APR 23'!G12 -> 4540 | I12: =G12-H12 -> 30 | J12: =I12*12 -> 360 | K12: 200 | L12: ='APR 23'!O12 -> 2524 | M12: =F12+J12+K12+L12 -> 5084 | N12: 5084 | O12: =M12-N12 -> 0 | Q12: ALLOTED WEF SEP 21. ADV 10000. RENT 2000
A13: 8 | B13: AJAY BAG | C13: G/8 | D13: 37469 | E13: 500 | F13: 1800 | G13: 2592 | H13: ='APR 23'!G13 -> 2563 | I13: =G13-H13 -> 29 | J13: =I13*12 -> 348 | K13: 200 | L13: ='APR 23'!O13 -> 5688 | M13: =F13+J13+K13+L13 -> 8036 | N13: 0 | O13: =M13-N13 -> 8036 | Q13: ALLOTED WEF MAR 22. ADV 10000. RENT 1800
A14: 9 | B14: SAPAN PATRA | C14: G/9 | D14: 37347 | E14: 500 | F14: 2000 | G14: 2317 | H14: ='APR 23'!G14 -> 2317 | I14: =G14-H14 -> 0 | J14: =I14*12 -> 0 | K14: 0 | L14: ='APR 23'!O14 -> 0 | M14: 0 | N14: 0 | O14: =M14-N14 -> 0 | Q14: VACATED WEF APR 22. BAL ADJ WITH 5K ADV. ALL CLEAR
A15: 10 | B15: PRAMOD MANDAL | C15: G/10 | D15: 37165 | E15: 500 | F15: 2000 | G15: 2841 | H15: ='APR 23'!G15 -> 2772 | I15: =G15-H15 -> 69 | J15: =I15*12 -> 828 | K15: 200 | L15: ='APR 23'!O15 -> 0 | M15: =F15+J15+K15+L15 -> 3028 | N15: 3028 | O15: =M15-N15 -> 0 | Q15: ALLOTED WEF SEP 22. ADV 10000 RENT 2000
A16: 11 | B16: SONU PRAJAPATI | C16: 1/1 | D16: 38443 | E16: 0 | F16: 2200 | G16: 129 | H16: ='APR 23'!G16 -> 57 | I16: =G16-H16 -> 72 | J16: =I16*12 -> 864 | K16: 300 | L16: ='APR 23'!O16 -> 17984 | M16: =F16+J16+K16+L16 -> 21348 | N16: 0 | O16: =M16-N16 -> 21348 | Q16: ALLOTED WEF APR 22. ADV 10K. RENT 2200
A17: 12 | B17: GOPAL SINGH | C17: 1/2 | D17: 38292 | F17: 2800 | G17: 5823 | H17: ='APR 23'!G17 -> 5765 | I17: =G17-H17 -> 58 | J17: =I17*12 -> 696 | K17: 300 | L17: ='APR 23'!O17 -> 28260 | M17: =F17+J17+K17+L17 -> 32056 | N17: 0 | O17: =M17-N17 -> 32056 | Q17: ALLOTED WEF DEC 20. ADV 8000. RENT 2800
A18: 13 | B18: AJAY DUBEY | C18: 1/3 | D18: 38292 | E18: 500 | F18: 3100 | G18: 4826 | H18: ='APR 23'!G18 -> 4797 | I18: =G18-H18 -> 29 | J18: =I18*12 -> 348 | K18: 300 | L18: ='APR 23'!O18 -> 11264 | M18: =F18+J18+K18+L18 -> 15012 | N18: 0 | O18: =M18-N18 -> 15012 | Q18: RENT INCREASED WEF JUL 21 FROM 2600, ADV 15000
A19: 14 | B19: BAJRANG L PAREEK | C19: 1/4 | D19: 38292 | E19: 500 | F19: 2700 | G19: 3635 | H19: ='APR 23'!G19 -> 3635 | I19: =G19-H19 -> 0 | J19: =I19*12 -> 0 | K19: 300 | L19: ='APR 23'!O19 -> 45576 | M19: =F19+J19+K19+L19 -> 48576 | N19: 0 | O19: =M19-N19 -> 48576 | Q19: RENT INCREASED WEF JUN 20 FROM 2200 ADV 10000
A20: 15 | B20: BIPIN KUMAR THAKUR | C20: 1/5 | D20: 37469 | E20: 500 | F20: 3000 | G20: 3907 | H20: ='APR 23'!G20 -> 3848 | I20: =G20-H20 -> 59 | J20: =I20*12 -> 708 | K20: 300 | L20: ='APR 23'!O20 -> 16340 | M20: =F20+J20+K20+L20 -> 20348 | N20: 0 | O20: =M20-N20 -> 20348 | Q20: RENT INCREASED WEF AUG 21 FROM 2400. ADV 10000
A21: 16 | B21: SHAILENDRA PANDEY | C21: 1/6 | D21: 37681 | E21: 500 | F21: 3000 | G21: 2374 | H21: ='APR 23'!G21 -> 2370 | I21: =G21-H21 -> 4 | J21: =I21*12 -> 48 | K21: 300 | L21: ='APR 23'!O21 -> 31784 | M21: =F21+J21+K21+L21 -> 35132 | N21: 0 | O21: =M21-N21 -> 35132 | Q21: RENT INCREASED WEF MAR 21 FROM 2300. ADV 10000
A22: 17 | B22: BIRENDAR YADAV | C22: 2/1 | D22: 38292 | E22: 500 | F22: 2800 | G22: 83 | H22: ='APR 23'!G22 -> 38 | I22: =G22-H22 -> 45 | J22: =I22*12 -> 540 | K22: 300 | L22: ='APR 23'!O22 -> 35662 | M22: =F22+J22+K22+L22 -> 39302 | N22: 0 | O22: =M22-N22 -> 39302 | Q22: RENT INCREASED WEF DEC 22 FROM 2200. ADV NIL
A23: 18 | B23: HARI SHANKER SHUKLA | C23: 2/2 | D23: 38292 | E23: 500 | F23: 2700 | G23: 653 | H23: ='APR 23'!G23 -> 638 | I23: =G23-H23 -> 15 | J23: =I23*12 -> 180 | K23: 300 | L23: ='APR 23'!O23 -> 10208 | M23: =F23+J23+K23+L23 -> 13388 | N23: 0 | O23: =M23-N23 -> 13388 | Q23: RENT INCRESED WEF JUL 21 FROM 2200. ADV 10000
A24: 19 | B24: SHIV SHANKER PANDEY | C24: 2/3 | D24: 37681 | E24: 500 | F24: 2800 | G24: 4945 | H24: ='APR 23'!G24 -> 4921 | I24: =G24-H24 -> 24 | J24: =I24*12 -> 288 | K24: 300 | L24: ='APR 23'!O24 -> 0 | M24: =F24+J24+K24+L24 -> 3388 | N24: 3388 | O24: =M24-N24 -> 0 | Q24: REALLOTED WEF DEC 22. RENT 2800. ADV NIL
A25: 20 | B25: AMLESH RAM | C25: 2/4 | D25: 37681 | E25: 0 | F25: 3000 | G25: 492 | H25: ='APR 23'!G25 -> 458 | I25: =G25-H25 -> 34 | J25: =I25*12 -> 408 | K25: 300 | L25: ='APR 23'!O25 -> 32 | M25: =F25+J25+K25+L25 -> 3740 | N25: 3740 | O25: =M25-N25 -> 0 | Q25: ALLOTED WEF MAR 23. RENT 3300. ADV 5000
A26: 21 | B26: JAIRAM MUDULI | C26: 2/5 | D26: 37681 | E26: 500 | F26: 2800 | G26: 3037 | H26: ='APR 23'!G26 -> 2998 | I26: =G26-H26 -> 39 | J26: =I26*12 -> 468 | K26: 300 | L26: ='APR 23'!O26 -> 3544 | M26: =F26+J26+K26+L26 -> 7112 | N26: 7112 | O26: =M26-N26 -> 0 | Q26: ALLOTED WEF SEP 21. ADV 10000, RENT 2800
A27: 22 | B27: SUNIL MONDAL | C27: 2/6 | D27: 37681 | E27: 0 | F27: 3300 | G27: 3355 | H27: ='APR 23'!G27 -> 3218 | I27: =G27-H27 -> 137 | J27: =I27*12 -> 1644 | K27: 300 | L27: ='APR 23'!O27 -> 50784 | M27: =F27+J27+K27+L27 -> 56028 | N27: 0 | O27: =M27-N27 -> 56028 | Q27: REALLOTED WEF DEC 20. RENT 3300. ADV 10K
C28: TOTAL | E28: =SUM(E6:E27) -> 7000 | F28: =SUM(F6:F27) -> 52100 | I28: =SUM(I6:I27) -> 798 | J28: =SUM(J6:J27) -> 9576 | K28: =SUM(K6:K27) -> 5200 | L28: =SUM(L6:L27) -> 282212 | M28: =SUM(M6:M27) -> 347088 | N28: =SUM(N6:N27) -> 39352 | O28: =SUM(O6:O27) -> 307736

Sheet APR 23
A1: SITA DEVI PANDEY HOUSING PROJECT
A2: 11/1B/1 GANPAT RAI KHEMKA LANE LILUAH HOWRAH(W. B.) 711204
A3: FOR THE MONTH OF - APR 2023
A4: SNO | B4: NAME | C4: ROOM | D4: DATE OF | E4: ELECTRIC | F4: MONTHLY | G4: ELECTRIC | K4: MISC | L4: B/F & | M4: TOTAL | N4: AMT | O4: B/F OR | P4: PAYMENT | Q4: REMARKS
C5: NO | D5: ALLOTMENT | E5: SECURITY | F5: RENT | G5: NEW | H5: PREV | I5: T UNIT | J5: AMOUNT | K5: RENT | L5: ADV | M5: AMT DUE | N5: PAID | O5: ADV | P5: DATE
A6: 1 | B6: SUNNY PRAJAPATI | C6: G/1 | D6: 38754 | E6: 0 | F6: 2000 | G6: 845 | H6: ='MAR 23'!G6 -> 820 | I6: =G6-H6 -> 25 | J6: =I6*12 -> 300 | K6: 200 | L6: ='MAR 23'!O6 -> -6 | M6: =F6+J6+K6+L6 -> 2494 | N6: 2500 | O6: =M6-N6 -> -6 | Q6: ALLOTED WEF SEP 21. ADV 10000. RENT 2000
A7: 2 | B7: VACANT | C7: G/2 | D7: 37653 | E7: 0 | F7: 0 | G7: 108 | H7: ='MAR 23'!G7 -> 108 | I7: =G7-H7 -> 0 | J7: =I7*12 -> 0 | K7: 0 | L7: ='MAR 23'!O7 -> 0 | M7: =F7+J7+K7+L7 -> 0 | N7: 0 | O7: =M7-N7 -> 0 | Q7: VACATED WEF SEP 22
A8: 3 | B8: PANKAJ PATEL | C8: G/3 | D8: 37895 | E8: 0 | F8: 2000 | G8: 4141 | H8: ='MAR 23'!G8 -> 4137 | I8: =G8-H8 -> 4 | J8: =I8*12 -> 48 | K8: 200 | L8: ='MAR 23'!O8 -> 13124 | M8: =F8+J8+K8+L8 -> 15372 | N8: 3000 | O8: =M8-N8 -> 12372 | Q8: ALLOTED WEF JUL 21. ADV 5K, RENT 2000.
A9: 4 | B9: BADRI MANDAL | C9: G/4 | D9: 38292 | E9: 500 | F9: 2000 | G9: 3866 | H9: ='MAR 23'!G9 -> 3831 | I9: =G9-H9 -> 35 | J9: =I9*12 -> 420 | K9: 200 | L9: ='MAR 23'!O9 -> 288 | M9: =F9+J9+K9+L9 -> 2908 | N9: 0 | O9: =M9-N9 -> 2908 | Q9: ALLOTED WEF 15 DEC 2022. RENT 2000. ADV 5000
